Workbook

Sheet Inicio
A1: SIMULADOR DE INVESTIMENTOS Ferramenta de apoio à conversa com o cliente
A5: O motor faz contas sofisticadas — mês a mês, com imposto, come-cotas, custos e inflação. O painel mostra pouca coisa: quanto entra, por quanto tempo, quanto pode virar, quando dá para retirar e qual o risco. A profundidade fica a um clique de distância, na aba Consultor.
A7: COMEÇAR O ATENDIMENTO
B8: 1 · CLIENTE | D8: As cinco perguntas e o resultado em linguagem simples. É a tela para virar o monitor para o cliente.
B9: 2 · COMPARAR | D9: As alternativas lado a lado e os gráficos de evolução, composição e renda.
B10: 3 · RELATÓRIO | D10: Resumo de uma página, pronto para imprimir ou salvar em PDF e entregar ao cliente.
A12: APROFUNDAR (MODO CONSULTOR)
B13: CONSULTOR | D13: Premissas, taxas, tributação, alertas e o painel técnico completo.
B14: MÊS A MÊS | D14: A projeção linha a linha: saldo, rendimento, aporte, custos e imposto.
B15: IMÓVEL | D15: Comprar para alugar: aluguel, vacância, IPTU, manutenção, compra e venda.
B16: PREVIDÊNCIA | D16: PGBL x VGBL, progressivo x regressivo e o valor real do benefício fiscal.
B17: ADERÊNCIA | D17: Como a planilha decide o que sugerir — e por que não é um ranking de rentabilidade.
A19: MANUTENÇÃO DA FERRAMENTA
B20: PRODUTOS | D20: Base de produtos: cadastrar, alterar taxa, ativar ou desativar.
B21: PREMISSAS | D21: Indicadores, cenários e todas as tabelas de tributação.
B22: FONTES | D22: De onde vem cada dado, com que atraso, e o registro de atualizações.
B23: GLOSSÁRIO | D23: Explicações curtas para usar na conversa com o cliente.
A25: SITUAÇÃO DOS DADOS AGORA
B26: Cenário em uso | E26: =CENARIO -> Base | G26: =IF(E29>0,"⚠ Há produtos com taxa de exemplo. Confira antes de usar com cliente.","Todos os produtos da base estão marcados como conferidos.") -> ⚠ Há produtos com taxa de exemplo. Confira antes de usar com cliente.
B27: Data de atualização dos dados | E27: =DATA_DADOS -> 2026-08-23
B28: Produtos ativos na base | E28: =COUNTIF(Produtos!$AD$9:$AD$78,"SIM") -> 24
B29: Produtos ainda não conferidos | E29: =COUNTIF(Produtos!$AB$9:$AB$78,"EXEMPLO*") -> 24
A31: ⚠ Ferramenta de apoio à conversa, de uso do profissional. Não é peça oficial de oferta e não substitui a lâmina, o regulamento, o prospecto do produto nem o questionário oficial de perfil (suitability).
A32: ⚠ Simulação baseada nas informações e premissas registradas nesta planilha. Os resultados reais podem ser diferentes. Rentabilidade passada não é garantia de rentabilidade futura e nenhum número aqui representa promessa de retorno.

Sheet Cliente
A1: SUA SIMULAÇÃO
A2: Poucas perguntas, e você vê o que pode acontecer com o seu dinheiro
A4: PASSO 1 · QUEM ESTAMOS ATENDENDO
B5: Nome do cliente | F5: (preencher)
B6: Data desta simulação | F6: =TODAY() -> 46257
A8: PASSO 2 · CINCO PERGUNTAS
A9: Só o que está em amarelo precisa ser preenchido. O resto a planilha calcula sozinha.
B10: Quanto você pretende investir agora? | F10: 150000
B11: Se ainda não tem certeza, use um valor aproximado — dá para mudar durante a conversa.
B12: Você pretende guardar mais alguma coisa por mês? | F12: 0
B13: Se não pretende, deixe zero.
B14: Por quanto tempo você pode deixar esse dinheiro investido? | F14: 5 a 10 anos
B15: Se escolheu “Prazo personalizado”, quantos meses? | F15: 120
B16: ➜ Prazo usado na simulação (meses) | F16: =IF(IN_HORIZONTE="Prazo personalizado",MAX(1,MIN(240,IN_PRAZO_CUSTOM)),IFERROR(INDEX(Premissas!$B$85:$B$90,MATCH(IN_HORIZONTE,Premissas!$A$85:$A$90,0)),120)) -> 120 | H16: ="Isso equivale a cerca de "&ROUND(IN_PRAZO/12,1)&" anos." -> Isso equivale a cerca de 10 anos.
B18: Você pode precisar desse dinheiro antes do prazo? | F18: Talvez
B19: Essa resposta pesa muito: ela define se vale a pena travar o dinheiro por uma taxa melhor.
B20: O que é mais importante para você? | F20: Equilíbrio entre segurança e rentabilidade
B21: Não existe resposta certa. Existe a resposta que combina com o seu momento.
B22: Perfil de investidor (do questionário oficial) | F22: Moderado
B23: Este campo repete o perfil já apurado no sistema da instituição. A planilha não substitui esse processo.
B24: =IF(IN_CAPITAL<=0,"⚠ Informe quanto o cliente pretende investir para a simulação começar.",IF(COUNTIF(Motor!$B$9:$G$9,1)=0,"⚠ Nenhuma alternativa escolhida ainda. Vá até a aba Consultor ou ligue a sugestão automática.","Tudo certo. Os resultados abaixo já refletem estas respostas.")) -> Tudo certo. Os resultados abaixo já refletem estas respostas.
A26: PASSO 3 · COMO SEU DINHEIRO PODE EVOLUIR
A27: Escolha uma alternativa para olhar de perto. A comparação completa está logo abaixo.
B28: Vamos olhar esta alternativa: | F28: A | H28: =IF(IN_DESTAQUE="Imóvel","Imóvel para aluguel",IFERROR(INDEX(Motor!$B$6:$G$6,MATCH("ALTERNATIVA "&IN_DESTAQUE,Motor!$B$5:$G$5,0)),"(não escolhida)")) -> Tesouro Prefixado 2031
B30: HOJE VOCÊ COLOCA | D30: ="EM "&ROUND(INT(IN_PRAZO/2)/12,0)&" ANOS" -> EM 5 ANOS | F30: ="EM "&ROUND(IN_PRAZO/12,0)&" ANOS" -> EM 10 ANOS | H30: GANHO ESTIMADO
B31: =IN_CAPITAL -> 150000 | D31: =IF(IN_DESTAQUE="Imóvel",MotorImovel!$B$35,IFERROR(INDEX(Motor!$B$41:$G$41,MATCH("ALTERNATIVA "&IN_DESTAQUE,Motor!$B$5:$G$5,0)),0)) -> 244983.51 | F31: =IF(IN_DESTAQUE="Imóvel",MotorImovel!$B$34,IFERROR(INDEX(Motor!$B$40:$G$40,MATCH("ALTERNATIVA "&IN_DESTAQUE,Motor!$B$5:$G$5,0)),0)) -> 410726.75 | H31: =IF(IN_DESTAQUE="Imóvel",MotorImovel!$B$38,IFERROR(INDEX(Motor!$B$44:$G$44,MATCH("ALTERNATIVA "&IN_DESTAQUE,Motor!$B$5:$G$5,0)),0)) -> 260726.75
B32: ="Mais "&TEXT(IN_APORTE,"R$ #,##0")&" por mês" -> Mais R$ 0 por mês | D32: ="Metade do caminho" -> Metade do caminho | F32: ="Já com imposto e custos descontados" -> Já com imposto e custos descontados | H32: ="Equivale a "&TEXT(IF(IN_DESTAQUE="Imóvel",MotorImovel!$B$41,IFERROR(INDEX(Motor!$B$47:$G$47,MATCH("ALTERNATIVA "&IN_DESTAQUE,Motor!$B$5:$G$5,0)),0)),"0.0%")&" sobre o investido" -> Equivale a 173.8% sobre o investido
A34: PASSO 4 · O QUE MAIS IMPORTA SABER SOBRE ESSA ALTERNATIVA
B35: PARA RETIRAR | D35: OSCILAÇÃO | F35: RENDA MENSAL POSSÍVEL | H35: IMPOSTO ESTIMADO | J35: ="O valor acima já está descontado de imposto e de custos. Em poder de compra de hoje, equivale a "&TEXT(IF(IN_DESTAQUE="Imóvel",MotorImovel!$B$36,IFERROR(INDEX(Motor!$B$42:$G$42,MATCH("ALTERNATIVA "&IN_DESTAQUE,Motor!$B$5:$G$5,0)),0)),"R$ #,##0")&"." -> O valor acima já está descontado de imposto e de custos. Em poder de compra de hoje, equivale a R$ 277,472.
B36: =IF(IN_DESTAQUE="Imóvel",MotorImovel!$B$50,IFERROR(INDEX(Motor!$B$56:$G$56,MATCH("ALTERNATIVA "&IN_DESTAQUE,Motor!$B$5:$G$5,0)),0)) -> Em 1 dia útil | D36: =IF(IN_DESTAQUE="Imóvel",MotorImovel!$B$51,IFERROR(INDEX(Motor!$B$57:$G$57,MATCH("ALTERNATIVA "&IN_DESTAQUE,Motor!$B$5:$G$5,0)),0)) -> Baixa | F36: =IF(IN_DESTAQUE="Imóvel",MotorImovel!$B$45,IFERROR(INDEX(Motor!$B$51:$G$51,MATCH("ALTERNATIVA "&IN_DESTAQUE,Motor!$B$5:$G$5,0)),0)) -> 3254.5196 | H36: =IF(IN_DESTAQUE="Imóvel",MotorImovel!$B$39,IFERROR(INDEX(Motor!$B$45:$G$45,MATCH("ALTERNATIVA "&IN_DESTAQUE,Motor!$B$5:$G$5,0)),0)) -> 46010.603
A38: PASSO 5 · OPÇÕES QUE PODEM FAZER SENTIDO PARA O SEU OBJETIVO
A39: Esta não é uma lista do que rende mais. É uma lista do que combina com o seu prazo, com a sua necessidade de retirar e com o que você disse ser mais importante. A escolha final é sua.
B40: Alternativa | C40: Você teria cerca de | D40: Ganho estimado | E40: Renda mensal possível | F40: Para retirar | G40: Oscilação | H40: Em R$ de hoje | I40: Aderência ao seu objetivo | J40: Ponto forte | K40: Ponto de atenção
B41: =IF(Motor!$B$9=0,"—",Motor!$B$6) -> Tesouro Prefixado 2031 | C41: =IF(Motor!$B$9=0,"",Motor!$B$40) -> 410726.75 | D41: =IF(Motor!$B$9=0,"",Motor!$B$44) -> 260726.75 | E41: =IF(Motor!$B$9=0,"",Motor!$B$51) -> 3254.5196 | F41: =IF(Motor!$B$9=0,"",Motor!$B$56) -> Em 1 dia útil | G41: =IF(Motor!$B$9=0,"",Motor!$B$57) -> Baixa | H41: =IF(Motor!$B$9=0,"",Motor!$B$42) -> 277472.27 | I41: =IF(Motor!$B$9=0,"",IFERROR(INDEX(Adequacao!$S$9:$S$78,MATCH(Motor!$B$6,Adequacao!$B$9:$B$78,0)),"—")) -> Pode fazer sentido | J41: =IF(Motor!$B$9=0,"",IFERROR(INDEX(Adequacao!$T$9:$T$78,MATCH(Motor!$B$6,Adequacao!$B$9:$B$78,0)),"")) -> A taxa fica travada na contratação: não cai se os juros da economia caírem. | K41: =IF(Motor!$B$9=0,"",IFERROR(INDEX(Adequacao!$U$9:$U$78,MATCH(Motor!$B$6,Adequacao!$B$9:$B$78,0)),"")) -> Se vender antes do vencimento, o preço pode estar abaixo do que você pagou.
B42: =IF(Motor!$C$9=0,"—",Motor!$C$6) -> Tesouro IPCA+ 2035 | C42: =IF(Motor!$C$9=0,"",Motor!$C$40) -> 353849.19 | D42: =IF(Motor!$C$9=0,"",Motor!$C$44) -> 203849.19 | E42: =IF(Motor!$C$9=0,"",Motor!$C$51) -> 2403.3348 | F42: =IF(Motor!$C$9=0,"",Motor!$C$56) -> Em 1 dia útil | G42: =IF(Motor!$C$9=0,"",Motor!$C$57) -> Baixa | H42: =IF(Motor!$C$9=0,"",Motor!$C$42) -> 239047.83 | I42: =IF(Motor!$C$9=0,"",IFERROR(INDEX(Adequacao!$S$9:$S$78,MATCH(Motor!$C$6,Adequacao!$B$9:$B$78,0)),"—")) -> Pode fazer sentido | J42: =IF(Motor!$C$9=0,"",IFERROR(INDEX(Adequacao!$T$9:$T$78,MATCH(Motor!$C$6,Adequacao!$B$9:$B$78,0)),"")) -> Protege o poder de compra: rende a inflação mais uma taxa fixa por cima. | K42: =IF(Motor!$C$9=0,"",IFERROR(INDEX(Adequacao!$U$9:$U$78,MATCH(Motor!$C$6,Adequacao!$B$9:$B$78,0)),"")) -> Se vender antes do vencimento, o preço pode estar abaixo do que você pagou.
B43: =IF(Motor!$D$9=0,"—",Motor!$D$6) -> Fundo CAIXA RF Crédito Privado LP | C43: =IF(Motor!$D$9=0,"",Motor!$D$40) -> 344477.27 | D43: =IF(Motor!$D$9=0,"",Motor!$D$44) -> 194477.27 | E43: =IF(Motor!$D$9=0,"",Motor!$D$51) -> 2387.9368 | F43: =IF(Motor!$D$9=0,"",Motor!$D$56) -> Em até 30 dias | G43: =IF(Motor!$D$9=0,"",Motor!$D$57) -> Baixa | H43: =IF(Motor!$D$9=0,"",Motor!$D$42) -> 232716.5 | I43: =IF(Motor!$D$9=0,"",IFERROR(INDEX(Adequacao!$S$9:$S$78,MATCH(Motor!$D$6,Adequacao!$B$9:$B$78,0)),"—")) -> Pode fazer sentido | J43: =IF(Motor!$D$9=0,"",IFERROR(INDEX(Adequacao!$T$9:$T$78,MATCH(Motor!$D$6,Adequacao!$B$9:$B$78,0)),"")) -> Combina com o prazo, a liquidez e a prioridade informados. | K43: =IF(Motor!$D$9=0,"",IFERROR(INDEX(Adequacao!$U$9:$U$78,MATCH(Motor!$D$6,Adequacao!$B$9:$B$78,0)),"")) -> Tem come-cotas em maio e novembro, que antecipam parte do imposto.
B44: =IF(Motor!$E$9=0,"—",Motor!$E$6) -> VGBL CAIXA Composto 30 — Regressivo | C44: =IF(Motor!$E$9=0,"",Motor!$E$40) -> 376188.27 | D44: =IF(Motor!$E$9=0,"",Motor!$E$44) -> 226188.27 | E44: =IF(Motor!$E$9=0,"",Motor!$E$51) -> 2730.3495 | F44: =IF(Motor!$E$9=0,"",Motor!$E$56) -> Em até 5 dias | G44: =IF(Motor!$E$9=0,"",Motor!$E$57) -> Média | H44: =IF(Motor!$E$9=0,"",Motor!$E$42) -> 254139.32 | I44: =IF(Motor!$E$9=0,"",IFERROR(INDEX(Adequacao!$S$9:$S$78,MATCH(Motor!$E$6,Adequacao!$B$9:$B$78,0)),"—")) -> Pode fazer sentido | J44: =IF(Motor!$E$9=0,"",IFERROR(INDEX(Adequacao!$T$9:$T$78,MATCH(Motor!$E$6,Adequacao!$B$9:$B$78,0)),"")) -> No prazo escolhido a previdência alcança a menor alíquota de imposto (10%). | K44: =IF(Motor!$E$9=0,"",IFERROR(INDEX(Adequacao!$U$9:$U$78,MATCH(Motor!$E$6,Adequacao!$B$9:$B$78,0)),"")) -> Não tem cobertura do FGC: quem responde pelo dinheiro é a seguradora.
B45: =IF(Motor!$F$9=0,"—",Motor!$F$6) -> PGBL CAIXA Composto 30 — Regressivo | C45: =IF(Motor!$F$9=0,"",Motor!$F$40) -> 353688.27 | D45: =IF(Motor!$F$9=0,"",Motor!$F$44) -> 203688.27 | E45: =IF(Motor!$F$9=0,"",Motor!$F$51) -> 2567.046 | F45: =IF(Motor!$F$9=0,"",Motor!$F$56) -> Em até 5 dias | G45: =IF(Motor!$F$9=0,"",Motor!$F$57) -> Média | H45: =IF(Motor!$F$9=0,"",Motor!$F$42) -> 238939.12 | I45: =IF(Motor!$F$9=0,"",IFERROR(INDEX(Adequacao!$S$9:$S$78,MATCH(Motor!$F$6,Adequacao!$B$9:$B$78,0)),"—")) -> Pode fazer sentido | J45: =IF(Motor!$F$9=0,"",IFERROR(INDEX(Adequacao!$T$9:$T$78,MATCH(Motor!$F$6,Adequacao!$B$9:$B$78,0)),"")) -> No prazo escolhido a previdência alcança a menor alíquota de imposto (10%). | K45: =IF(Motor!$F$9=0,"",IFERROR(INDEX(Adequacao!$U$9:$U$78,MATCH(Motor!$F$6,Adequacao!$B$9:$B$78,0)),"")) -> Não tem cobertura do FGC: quem responde pelo dinheiro é a seguradora.
B46: =IF(Motor!$G$9=0,"—",Motor!$G$6) -> Fundo CAIXA RF IPCA Longo Prazo | C46: =IF(Motor!$G$9=0,"",Motor!$G$40) -> 316495.51 | D46: =IF(Motor!$G$9=0,"",Motor!$G$44) -> 166495.51 | E46: =IF(Motor!$G$9=0,"",Motor!$G$51) -> 1970.2821 | F46: =IF(Motor!$G$9=0,"",Motor!$G$56) -> Em até 5 dias | G46: =IF(Motor!$G$9=0,"",Motor!$G$57) -> Média | H46: =IF(Motor!$G$9=0,"",Motor!$G$42) -> 213813.03 | I46: =IF(Motor!$G$9=0,"",IFERROR(INDEX(Adequacao!$S$9:$S$78,MATCH(Motor!$G$6,Adequacao!$B$9:$B$78,0)),"—")) -> Pode fazer sentido | J46: =IF(Motor!$G$9=0,"",IFERROR(INDEX(Adequacao!$T$9:$T$78,MATCH(Motor!$G$6,Adequacao!$B$9:$B$78,0)),"")) -> Protege o poder de compra: rende a inflação mais uma taxa fixa por cima. | K46: =IF(Motor!$G$9=0,"",IFERROR(INDEX(Adequacao!$U$9:$U$78,MATCH(Motor!$G$6,Adequacao!$B$9:$B$78,0)),"")) -> O valor oscila mês a mês: em prazo curto pode estar abaixo do que você aplicou.
B47: =IF(MotorImovel!$B$5=0,"—","Imóvel para aluguel") -> Imóvel para aluguel | C47: =IF(MotorImovel!$B$5=0,"",MotorImovel!$B$34) -> 329895.57 | D47: =IF(MotorImovel!$B$5=0,"",MotorImovel!$B$38) -> 174645.57 | E47: =IF(MotorImovel!$B$5=0,"",MotorImovel!$B$45) -> 827.86264 | F47: =IF(MotorImovel!$B$5=0,"",MotorImovel!$B$50) -> Depende de encontrar comprador — normalmente meses | G47: =IF(MotorImovel!$B$5=0,"",MotorImovel!$B$51) -> Média | H47: =IF(MotorImovel!$B$5=0,"",MotorImovel!$B$36) -> 222865.63 | I47: =IF(MotorImovel!$B$5=0,"",IFERROR(INDEX(Adequacao!$S$9:$S$78,MATCH("Imóvel para aluguel",Adequacao!$B$9:$B$78,0)),"—")) -> Pode fazer sentido | J47: =IF(MotorImovel!$B$5=0,"",IFERROR(INDEX(Adequacao!$T$9:$T$78,MATCH("Imóvel para aluguel",Adequacao!$B$9:$B$78,0)),"")) -> Combina com o prazo, a liquidez e a prioridade informados. | K47: =IF(MotorImovel!$B$5=0,"",IFERROR(INDEX(Adequacao!$U$9:$U$78,MATCH("Imóvel para aluguel",Adequacao!$B$9:$B$78,0)),"")) -> Não é dinheiro rápido: leva meses para virar caixa.
A49: ⚠ Simulação baseada nas informações e premissas registradas nesta planilha. Os resultados reais podem ser diferentes. Rentabilidade passada não é garantia de rentabilidade futura e nenhum número aqui representa promessa de retorno.
B51: ◀ INÍCIO | D51: VER GRÁFICOS ▶ | F51: VER MÊS A MÊS | H51: O QUE SIGNIFICA? | J51: GERAR RELATÓRIO | L51: MODO CONSULTOR

Sheet Comparar
A1: COMPARANDO AS ALTERNATIVAS
A2: As mesmas premissas, o mesmo prazo, o mesmo valor — para a comparação ser justa
A4: RESULTADO NO PRAZO ESCOLHIDO
A5: =" Cliente: "&IN_NOME&" · Valor: "&TEXT(IN_CAPITAL,"R$ #,##0")&" · Aporte mensal: "&TEXT(IN_APORTE,"R$ #,##0")&" · Prazo: "&IN_PRAZO&" meses · Cenário: "&CENARIO&" · Dados de "&DATA_DADOS -> Cliente: (preencher) · Valor: R$ 150,000 · Aporte mensal: R$ 0 · Prazo: 120 meses · Cenário: Base · Dados de 2026-08-23
B6: Alternativa | C6: Patrimônio líquido | D6: Total investido | E6: Ganho líquido | F6: Impostos | G6: Custos | H6: Em R$ de hoje | I6: Rent. acum. | J6: Taxa a.a. | K6: Ganho real a.a. | L6: Renda mensal | M6: Para retirar | N6: Oscilação | O6: Aderência ao objetivo | Q6: Auxiliar (só as em uso)
B7: =IF(Motor!$B$9=0,"— alternativa A não usada",Motor!$B$6) -> Tesouro Prefixado 2031 | C7: =IF(Motor!$B$9=0,0,Motor!$B$40) -> 410726.75 | D7: =IF(Motor!$B$9=0,0,Motor!$B$43) -> 150000 | E7: =IF(Motor!$B$9=0,0,Motor!$B$44) -> 260726.75 | F7: =IF(Motor!$B$9=0,0,Motor!$B$45) -> 46010.603 | G7: =IF(Motor!$B$9=0,0,Motor!$B$46) -> 5484.0377 | H7: =IF(Motor!$B$9=0,0,Motor!$B$42) -> 277472.27 | I7: =IF(Motor!$B$9=0,0,Motor!$B$47) -> 1.7381783 | J7: =IF(Motor!$B$9=0,0,Motor!$B$48) -> 0.1059772 | K7: =IF(Motor!$B$9=0,0,Motor!$B$49) -> 0.063439613 | L7: =IF(Motor!$B$9=0,0,Motor!$B$51) -> 3254.5196 | M7: =IF(Motor!$B$9=0,"",Motor!$B$56) -> Em 1 dia útil | N7: =IF(Motor!$B$9=0,"",Motor!$B$57) -> Baixa | O7: =IF(Motor!$B$9=0,"",IFERROR(INDEX(Adequacao!$S$9:$S$78,MATCH(Motor!$B$6,Adequacao!$B$9:$B$78,0)),"—")) -> Pode fazer sentido | Q7: =IF(Motor!$B$9=0,"",$C7) -> 410726.75
B8: =IF(Motor!$C$9=0,"— alternativa B não usada",Motor!$C$6) -> Tesouro IPCA+ 2035 | C8: =IF(Motor!$C$9=0,0,Motor!$C$40) -> 353849.19 | D8: =IF(Motor!$C$9=0,0,Motor!$C$43) -> 150000 | E8: =IF(Motor!$C$9=0,0,Motor!$C$44) -> 203849.19 | F8: =IF(Motor!$C$9=0,0,Motor!$C$45) -> 35973.386 | G8: =IF(Motor!$C$9=0,0,Motor!$C$46) -> 5002.2069 | H8: =IF(Motor!$C$9=0,0,Motor!$C$42) -> 239047.83 | I8: =IF(Motor!$C$9=0,0,Motor!$C$47) -> 1.3589946 | J8: =IF(Motor!$C$9=0,0,Motor!$C$48) -> 0.089614049 | K8: =IF(Motor!$C$9=0,0,Motor!$C$49) -> 0.047705816 | L8: =IF(Motor!$C$9=0,0,Motor!$C$51) -> 2403.3348 | M8: =IF(Motor!$C$9=0,"",Motor!$C$56) -> Em 1 dia útil | N8: =IF(Motor!$C$9=0,"",Motor!$C$57) -> Baixa | O8: =IF(Motor!$C$9=0,"",IFERROR(INDEX(Adequacao!$S$9:$S$78,MATCH(Motor!$C$6,Adequacao!$B$9:$B$78,0)),"—")) -> Pode fazer sentido | Q8: =IF(Motor!$C$9=0,"",$C8) -> 353849.19
B9: =IF(Motor!$D$9=0,"— alternativa C não usada",Motor!$D$6) -> Fundo CAIXA RF Crédito Privado LP | C9: =IF(Motor!$D$9=0,0,Motor!$D$40) -> 344477.27 | D9: =IF(Motor!$D$9=0,0,Motor!$D$43) -> 150000 | E9: =IF(Motor!$D$9=0,0,Motor!$D$44) -> 194477.27 | F9: =IF(Motor!$D$9=0,0,Motor!$D$45) -> 34319.518 | G9: =IF(Motor!$D$9=0,0,Motor!$D$46) -> 23378.968 | H9: =IF(Motor!$D$9=0,0,Motor!$D$42) -> 232716.5 | I9: =IF(Motor!$D$9=0,0,Motor!$D$47) -> 1.2965151 | J9: =IF(Motor!$D$9=0,0,Motor!$D$48) -> 0.086693154 | K9: =IF(Motor!$D$9=0,0,Motor!$D$49) -> 0.044897263 | L9: =IF(Motor!$D$9=0,0,Motor!$D$51) -> 2387.9368 | M9: =IF(Motor!$D$9=0,"",Motor!$D$56) -> Em até 30 dias | N9: =IF(Motor!$D$9=0,"",Motor!$D$57) -> Baixa | O9: =IF(Motor!$D$9=0,"",IFERROR(INDEX(Adequacao!$S$9:$S$78,MATCH(Motor!$D$6,Adequacao!$B$9:$B$78,0)),"—")) -> Pode fazer sentido | Q9: =IF(Motor!$D$9=0,"",$C9) -> 344477.27
B10: =IF(Motor!$E$9=0,"— alternativa D não usada",Motor!$E$6) -> VGBL CAIXA Composto 30 — Regressivo | C10: =IF(Motor!$E$9=0,0,Motor!$E$40) -> 376188.27 | D10: =IF(Motor!$E$9=0,0,Motor!$E$43) -> 150000 | E10: =IF(Motor!$E$9=0,0,Motor!$E$44) -> 226188.27 | F10: =IF(Motor!$E$9=0,0,Motor!$E$45) -> 39915.578 | G10: =IF(Motor!$E$9=0,0,Motor!$E$46) -> 38955.35 | H10: =IF(Motor!$E$9=0,0,Motor!$E$42) -> 254139.32 | I10: =IF(Motor!$E$9=0,0,Motor!$E$47) -> 1.5079218 | J10: =IF(Motor!$E$9=0,0,Motor!$E$48) -> 0.096305012 | K10: =IF(Motor!$E$9=0,0,Motor!$E$49) -> 0.054139434 | L10: =IF(Motor!$E$9=0,0,Motor!$E$51) -> 2730.3495 | M10: =IF(Motor!$E$9=0,"",Motor!$E$56) -> Em até 5 dias | N10: =IF(Motor!$E$9=0,"",Motor!$E$57) -> Média | O10: =IF(Motor!$E$9=0,"",IFERROR(INDEX(Adequacao!$S$9:$S$78,MATCH(Motor!$E$6,Adequacao!$B$9:$B$78,0)),"—")) -> Pode fazer sentido | Q10: =IF(Motor!$E$9=0,"",$C10) -> 376188.27
B11: =IF(Motor!$F$9=0,"— alternativa E não usada",Motor!$F$6) -> PGBL CAIXA Composto 30 — Regressivo | C11: =IF(Motor!$F$9=0,0,Motor!$F$40) -> 353688.27 | D11: =IF(Motor!$F$9=0,0,Motor!$F$43) -> 150000 | E11: =IF(Motor!$F$9=0,0,Motor!$F$44) -> 203688.27 | F11: =IF(Motor!$F$9=0,0,Motor!$F$45) -> 62415.578 | G11: =IF(Motor!$F$9=0,0,Motor!$F$46) -> 38955.35 | H11: =IF(Motor!$F$9=0,0,Motor!$F$42) -> 238939.12 | I11: =IF(Motor!$F$9=0,0,Motor!$F$47) -> 1.3579218 | J11: =IF(Motor!$F$9=0,0,Motor!$F$48) -> 0.089564489 | K11: =IF(Motor!$F$9=0,0,Motor!$F$49) -> 0.047658162 | L11: =IF(Motor!$F$9=0,0,Motor!$F$51) -> 2567.046 | M11: =IF(Motor!$F$9=0,"",Motor!$F$56) -> Em até 5 dias | N11: =IF(Motor!$F$9=0,"",Motor!$F$57) -> Média | O11: =IF(Motor!$F$9=0,"",IFERROR(INDEX(Adequacao!$S$9:$S$78,MATCH(Motor!$F$6,Adequacao!$B$9:$B$78,0)),"—")) -> Pode fazer sentido | Q11: =IF(Motor!$F$9=0,"",$C11) -> 353688.27
B12: =IF(Motor!$G$9=0,"— alternativa F não usada",Motor!$G$6) -> Fundo CAIXA RF IPCA Longo Prazo | C12: =IF(Motor!$G$9=0,0,Motor!$G$40) -> 316495.51 | D12: =IF(Motor!$G$9=0,0,Motor!$G$43) -> 150000 | E12: =IF(Motor!$G$9=0,0,Motor!$G$44) -> 166495.51 | F12: =IF(Motor!$G$9=0,0,Motor!$G$45) -> 29381.56 | G12: =IF(Motor!$G$9=0,0,Motor!$G$46) -> 22287.452 | H12: =IF(Motor!$G$9=0,0,Motor!$G$42) -> 213813.03 | I12: =IF(Motor!$G$9=0,0,Motor!$G$47) -> 1.1099701 | J12: =IF(Motor!$G$9=0,0,Motor!$G$48) -> 0.07752568 | K12: =IF(Motor!$G$9=0,0,Motor!$G$49) -> 0.036082385 | L12: =IF(Motor!$G$9=0,0,Motor!$G$51) -> 1970.2821 | M12: =IF(Motor!$G$9=0,"",Motor!$G$56) -> Em até 5 dias | N12: =IF(Motor!$G$9=0,"",Motor!$G$57) -> Média | O12: =IF(Motor!$G$9=0,"",IFERROR(INDEX(Adequacao!$S$9:$S$78,MATCH(Motor!$G$6,Adequacao!$B$9:$B$78,0)),"—")) -> Pode fazer sentido | Q12: =IF(Motor!$G$9=0,"",$C12) -> 316495.51
B13: =IF(MotorImovel!$B$5=0,"— alternativa imóvel não usada","Imóvel para aluguel") -> Imóvel para aluguel | C13: =IF(MotorImovel!$B$5=0,0,MotorImovel!$B$34) -> 329895.57 | D13: =IF(MotorImovel!$B$5=0,0,MotorImovel!$B$37) -> 155250 | E13: =IF(MotorImovel!$B$5=0,0,MotorImovel!$B$38) -> 174645.57 | F13: =IF(MotorImovel!$B$5=0,0,MotorImovel!$B$39) -> 16294.186 | G13: =IF(MotorImovel!$B$5=0,0,MotorImovel!$B$40) -> 68286.677 | H13: =IF(MotorImovel!$B$5=0,0,MotorImovel!$B$36) -> 222865.63 | I13: =IF(MotorImovel!$B$5=0,0,MotorImovel!$B$41) -> 1.1249312 | J13: =IF(MotorImovel!$B$5=0,0,MotorImovel!$B$42) -> 0.078287294 | K13: =IF(MotorImovel!$B$5=0,0,MotorImovel!$B$43) -> 0.036814706 | L13: =IF(MotorImovel!$B$5=0,0,MotorImovel!$B$45) -> 827.86264 | M13: =IF(MotorImovel!$B$5=0,"",MotorImovel!$B$50) -> Depende de encontrar comprador — normalmente meses | N13: =IF(MotorImovel!$B$5=0,"",MotorImovel!$B$51) -> Média | O13: =IF(MotorImovel!$B$5=0,"",IFERROR(INDEX(Adequacao!$S$9:$S$78,MATCH("Imóvel para aluguel",Adequacao!$B$9:$B$78,0)),"—")) -> Pode fazer sentido | Q13: =IF(MotorImovel!$B$5=0,"",$C13) -> 329895.57
A14: O maior patrimônio aparece destacado apenas como informação. Maior patrimônio não significa melhor escolha: liquidez, risco e objetivo pesam tanto quanto o número.
A15: EVOLUÇÃO ANO A ANO (base dos gráficos)
A16: Ano | B16: =IF(Motor!$B$9=0,"(não usada A)",Motor!$B$6) -> Tesouro Prefixado 2031 | C16: =IF(Motor!$C$9=0,"(não usada B)",Motor!$C$6) -> Tesouro IPCA+ 2035 | D16: =IF(Motor!$D$9=0,"(não usada C)",Motor!$D$6) -> Fundo CAIXA RF Crédito Privado LP | E16: =IF(Motor!$E$9=0,"(não usada D)",Motor!$E$6) -> VGBL CAIXA Composto 30 — Regressivo | F16: =IF(Motor!$F$9=0,"(não usada E)",Motor!$F$6) -> PGBL CAIXA Composto 30 — Regressivo | G16: =IF(Motor!$G$9=0,"(não usada F)",Motor!$G$6) -> Fundo CAIXA RF IPCA Longo Prazo | H16: =IF(MotorImovel!$B$5=0,"(não usada imóvel)","Imóvel para aluguel") -> Imóvel para aluguel
A17: 0 | B17: =IF(OR(0>IN_PRAZO,Motor!$B$9=0),"",INDEX(Motor!$R$61:$R$301,0+1)) -> 150000 | C17: =IF(OR(0>IN_PRAZO,Motor!$C$9=0),"",INDEX(Motor!$AG$61:$AG$301,0+1)) -> 150000 | D17: =IF(OR(0>IN_PRAZO,Motor!$D$9=0),"",INDEX(Motor!$AV$61:$AV$301,0+1)) -> 150000 | E17: =IF(OR(0>IN_PRAZO,Motor!$E$9=0),"",INDEX(Motor!$BK$61:$BK$301,0+1)) -> 150000 | F17: =IF(OR(0>IN_PRAZO,Motor!$F$9=0),"",INDEX(Motor!$BZ$61:$BZ$301,0+1)) -> 97500 | G17: =IF(OR(0>IN_PRAZO,Motor!$G$9=0),"",INDEX(Motor!$CO$61:$CO$301,0+1)) -> 150000 | H17: =IF(OR(0>IN_PRAZO,MotorImovel!$B$5=0),"",INDEX(MotorImovel!$W$55:$W$295,0+1)) -> 141000
A18: 1 | B18: =IF(OR(12>IN_PRAZO,Motor!$B$9=0),"",INDEX(Motor!$R$61:$R$301,12+1)) -> 164133.97 | C18: =IF(OR(12>IN_PRAZO,Motor!$C$9=0),"",INDEX(Motor!$AG$61:$AG$301,12+1)) -> 162025.8 | D18: =IF(OR(12>IN_PRAZO,Motor!$D$9=0),"",INDEX(Motor!$AV$61:$AV$301,12+1)) -> 162228.76 | E18: =IF(OR(12>IN_PRAZO,Motor!$E$9=0),"",INDEX(Motor!$BK$61:$BK$301,12+1)) -> 160473.12 | F18: =IF(OR(12>IN_PRAZO,Motor!$F$9=0),"",INDEX(Motor!$BZ$61:$BZ$301,12+1)) -> 107973.12 | G18: =IF(OR(12>IN_PRAZO,Motor!$G$9=0),"",INDEX(Motor!$CO$61:$CO$301,12+1)) -> 160936.56 | H18: =IF(OR(12>IN_PRAZO,MotorImovel!$B$5=0),"",INDEX(MotorImovel!$W$55:$W$295,12+1)) -> 153757.54
A19: 2 | B19: =IF(OR(24>IN_PRAZO,Motor!$B$9=0),"",INDEX(Motor!$R$61:$R$301,24+1)) -> 180868.07 | C19: =IF(OR(24>IN_PRAZO,Motor!$C$9=0),"",INDEX(Motor!$AG$61:$AG$301,24+1)) -> 176046.05 | D19: =IF(OR(24>IN_PRAZO,Motor!$D$9=0),"",INDEX(Motor!$AV$61:$AV$301,24+1)) -> 176326.97 | E19: =IF(OR(24>IN_PRAZO,Motor!$E$9=0),"",INDEX(Motor!$BK$61:$BK$301,24+1)) -> 172071.23 | F19: =IF(OR(24>IN_PRAZO,Motor!$F$9=0),"",INDEX(Motor!$BZ$61:$BZ$301,24+1)) -> 119571.23 | G19: =IF(OR(24>IN_PRAZO,Motor!$G$9=0),"",INDEX(Motor!$CO$61:$CO$301,24+1)) -> 173440.54 | H19: =IF(OR(24>IN_PRAZO,MotorImovel!$B$5=0),"",INDEX(MotorImovel!$W$55:$W$295,24+1)) -> 167675.08
A20: 3 | B20: =IF(OR(36>IN_PRAZO,Motor!$B$9=0),"",INDEX(Motor!$R$61:$R$301,36+1)) -> 200566.72 | C20: =IF(OR(36>IN_PRAZO,Motor!$C$9=0),"",INDEX(Motor!$AG$61:$AG$301,36+1)) -> 192302.04 | D20: =IF(OR(36>IN_PRAZO,Motor!$D$9=0),"",INDEX(Motor!$AV$61:$AV$301,36+1)) -> 192481.69 | E20: =IF(OR(36>IN_PRAZO,Motor!$E$9=0),"",INDEX(Motor!$BK$61:$BK$301,36+1)) -> 187600.96 | F20: =IF(OR(36>IN_PRAZO,Motor!$F$9=0),"",INDEX(Motor!$BZ$61:$BZ$301,36+1)) -> 142600.96 | G20: =IF(OR(36>IN_PRAZO,Motor!$G$9=0),"",INDEX(Motor!$CO$61:$CO$301,36+1)) -> 187653.15 | H20: =IF(OR(36>IN_PRAZO,MotorImovel!$B$5=0),"",INDEX(MotorImovel!$W$55:$W$295,36+1)) -> 182423.97
A21: 4 | B21: =IF(OR(48>IN_PRAZO,Motor!$B$9=0),"",INDEX(Motor!$R$61:$R$301,48+1)) -> 221539.97 | C21: =IF(OR(48>IN_PRAZO,Motor!$C$9=0),"",INDEX(Motor!$AG$61:$AG$301,48+1)) -> 209318.76 | D21: =IF(OR(48>IN_PRAZO,Motor!$D$9=0),"",INDEX(Motor!$AV$61:$AV$301,48+1)) -> 209170.09 | E21: =IF(OR(48>IN_PRAZO,Motor!$E$9=0),"",INDEX(Motor!$BK$61:$BK$301,48+1)) -> 202918.67 | F21: =IF(OR(48>IN_PRAZO,Motor!$F$9=0),"",INDEX(Motor!$BZ$61:$BZ$301,48+1)) -> 157918.67 | G21: =IF(OR(48>IN_PRAZO,Motor!$G$9=0),"",INDEX(Motor!$CO$61:$CO$301,48+1)) -> 202202.3 | H21: =IF(OR(48>IN_PRAZO,MotorImovel!$B$5=0),"",INDEX(MotorImovel!$W$55:$W$295,48+1)) -> 198096.35
A22: 5 | B22: =IF(OR(60>IN_PRAZO,Motor!$B$9=0),"",INDEX(Motor!$R$61:$R$301,60+1)) -> 244983.51 | C22: =IF(OR(60>IN_PRAZO,Motor!$C$9=0),"",INDEX(Motor!$AG$61:$AG$301,60+1)) -> 228040.8 | D22: =IF(OR(60>IN_PRAZO,Motor!$D$9=0),"",INDEX(Motor!$AV$61:$AV$301,60+1)) -> 227305.4 | E22: =IF(OR(60>IN_PRAZO,Motor!$E$9=0),"",INDEX(Motor!$BK$61:$BK$301,60+1)) -> 224873.32 | F22: =IF(OR(60>IN_PRAZO,Motor!$F$9=0),"",INDEX(Motor!$BZ$61:$BZ$301,60+1)) -> 187373.32 | G22: =IF(OR(60>IN_PRAZO,Motor!$G$9=0),"",INDEX(Motor!$CO$61:$CO$301,60+1)) -> 217879.48 | H22: =IF(OR(60>IN_PRAZO,MotorImovel!$B$5=0),"",INDEX(MotorImovel!$W$55:$W$295,60+1)) -> 215279.94
A23: 6 | B23: =IF(OR(72>IN_PRAZO,Motor!$B$9=0),"",INDEX(Motor!$R$61:$R$301,72+1)) -> 271188.3 | C23: =IF(OR(72>IN_PRAZO,Motor!$C$9=0),"",INDEX(Motor!$AG$61:$AG$301,72+1)) -> 248639.08 | D23: =IF(OR(72>IN_PRAZO,Motor!$D$9=0),"",INDEX(Motor!$AV$61:$AV$301,72+1)) -> 247013.06 | E23: =IF(OR(72>IN_PRAZO,Motor!$E$9=0),"",INDEX(Motor!$BK$61:$BK$301,72+1)) -> 245000.34 | F23: =IF(OR(72>IN_PRAZO,Motor!$F$9=0),"",INDEX(Motor!$BZ$61:$BZ$301,72+1)) -> 207500.34 | G23: =IF(OR(72>IN_PRAZO,Motor!$G$9=0),"",INDEX(Motor!$CO$61:$CO$301,72+1)) -> 234772.15 | H23: =IF(OR(72>IN_PRAZO,MotorImovel!$B$5=0),"",INDEX(MotorImovel!$W$55:$W$295,72+1)) -> 234129.65
A24: 7 | B24: =IF(OR(84>IN_PRAZO,Motor!$B$9=0),"",INDEX(Motor!$R$61:$R$301,84+1)) -> 300479.57 | C24: =IF(OR(84>IN_PRAZO,Motor!$C$9=0),"",INDEX(Motor!$AG$61:$AG$301,84+1)) -> 271301.61 | D24: =IF(OR(84>IN_PRAZO,Motor!$D$9=0),"",INDEX(Motor!$AV$61:$AV$301,84+1)) -> 268429.4 | E24: =IF(OR(84>IN_PRAZO,Motor!$E$9=0),"",INDEX(Motor!$BK$61:$BK$301,84+1)) -> 275108.62 | F24: =IF(OR(84>IN_PRAZO,Motor!$F$9=0),"",INDEX(Motor!$BZ$61:$BZ$301,84+1)) -> 245108.62 | G24: =IF(OR(84>IN_PRAZO,Motor!$G$9=0),"",INDEX(Motor!$CO$61:$CO$301,84+1)) -> 252974.55 | H24: =IF(OR(84>IN_PRAZO,MotorImovel!$B$5=0),"",INDEX(MotorImovel!$W$55:$W$295,84+1)) -> 254816.67
A25: 8 | B25: =IF(OR(96>IN_PRAZO,Motor!$B$9=0),"",INDEX(Motor!$R$61:$R$301,96+1)) -> 333220.85 | C25: =IF(OR(96>IN_PRAZO,Motor!$C$9=0),"",INDEX(Motor!$AG$61:$AG$301,96+1)) -> 296235.27 | D25: =IF(OR(96>IN_PRAZO,Motor!$D$9=0),"",INDEX(Motor!$AV$61:$AV$301,96+1)) -> 291702.56 | E25: =IF(OR(96>IN_PRAZO,Motor!$E$9=0),"",INDEX(Motor!$BK$61:$BK$301,96+1)) -> 301437.36 | F25: =IF(OR(96>IN_PRAZO,Motor!$F$9=0),"",INDEX(Motor!$BZ$61:$BZ$301,96+1)) -> 271437.36 | G25: =IF(OR(96>IN_PRAZO,Motor!$G$9=0),"",INDEX(Motor!$CO$61:$CO$301,96+1)) -> 272588.21 | H25: =IF(OR(96>IN_PRAZO,MotorImovel!$B$5=0),"",INDEX(MotorImovel!$W$55:$W$295,96+1)) -> 277530.23
A26: 9 | B26: =IF(OR(108>IN_PRAZO,Motor!$B$9=0),"",INDEX(Motor!$R$61:$R$301,108+1)) -> 369818.51 | C26: =IF(OR(108>IN_PRAZO,Motor!$C$9=0),"",INDEX(Motor!$AG$61:$AG$301,108+1)) -> 323667.66 | D26: =IF(OR(108>IN_PRAZO,Motor!$D$9=0),"",INDEX(Motor!$AV$61:$AV$301,108+1)) -> 316993.54 | E26: =IF(OR(108>IN_PRAZO,Motor!$E$9=0),"",INDEX(Motor!$BK$61:$BK$301,108+1)) -> 341881.39 | F26: =IF(OR(108>IN_PRAZO,Motor!$F$9=0),"",INDEX(Motor!$BZ$61:$BZ$301,108+1)) -> 319381.39 | G26: =IF(OR(108>IN_PRAZO,Motor!$G$9=0),"",INDEX(Motor!$CO$61:$CO$301,108+1)) -> 293722.56 | H26: =IF(OR(108>IN_PRAZO,MotorImovel!$B$5=0),"",INDEX(MotorImovel!$W$55:$W$295,108+1)) -> 302479.47
A27: 10 | B27: =IF(OR(120>IN_PRAZO,Motor!$B$9=0),"",INDEX(Motor!$R$61:$R$301,120+1)) -> 410726.75 | C27: =IF(OR(120>IN_PRAZO,Motor!$C$9=0),"",INDEX(Motor!$AG$61:$AG$301,120+1)) -> 353849.19 | D27: =IF(OR(120>IN_PRAZO,Motor!$D$9=0),"",INDEX(Motor!$AV$61:$AV$301,120+1)) -> 344477.27 | E27: =IF(OR(120>IN_PRAZO,Motor!$E$9=0),"",INDEX(Motor!$BK$61:$BK$301,120+1)) -> 376188.27 | F27: =IF(OR(120>IN_PRAZO,Motor!$F$9=0),"",INDEX(Motor!$BZ$61:$BZ$301,120+1)) -> 353688.27 | G27: =IF(OR(120>IN_PRAZO,Motor!$G$9=0),"",INDEX(Motor!$CO$61:$CO$301,120+1)) -> 316495.51 | H27: =IF(OR(120>IN_PRAZO,MotorImovel!$B$5=0),"",INDEX(MotorImovel!$W$55:$W$295,120+1)) -> 329895.57
A28: 11 | B28: =IF(OR(132>IN_PRAZO,Motor!$B$9=0),"",INDEX(Motor!$R$61:$R$301,132+1)) | C28: =IF(OR(132>IN_PRAZO,Motor!$C$9=0),"",INDEX(Motor!$AG$61:$AG$301,132+1)) | D28: =IF(OR(132>IN_PRAZO,Motor!$D$9=0),"",INDEX(Motor!$AV$61:$AV$301,132+1)) | E28: =IF(OR(132>IN_PRAZO,Motor!$E$9=0),"",INDEX(Motor!$BK$61:$BK$301,132+1)) | F28: =IF(OR(132>IN_PRAZO,Motor!$F$9=0),"",INDEX(Motor!$BZ$61:$BZ$301,132+1)) | G28: =IF(OR(132>IN_PRAZO,Motor!$G$9=0),"",INDEX(Motor!$CO$61:$CO$301,132+1)) | H28: =IF(OR(132>IN_PRAZO,MotorImovel!$B$5=0),"",INDEX(MotorImovel!$W$55:$W$295,132+1))
A29: 12 | B29: =IF(OR(144>IN_PRAZO,Motor!$B$9=0),"",INDEX(Motor!$R$61:$R$301,144+1)) | C29: =IF(OR(144>IN_PRAZO,Motor!$C$9=0),"",INDEX(Motor!$AG$61:$AG$301,144+1)) | D29: =IF(OR(144>IN_PRAZO,Motor!$D$9=0),"",INDEX(Motor!$AV$61:$AV$301,144+1)) | E29: =IF(OR(144>IN_PRAZO,Motor!$E$9=0),"",INDEX(Motor!$BK$61:$BK$301,144+1)) | F29: =IF(OR(144>IN_PRAZO,Motor!$F$9=0),"",INDEX(Motor!$BZ$61:$BZ$301,144+1)) | G29: =IF(OR(144>IN_PRAZO,Motor!$G$9=0),"",INDEX(Motor!$CO$61:$CO$301,144+1)) | H29: =IF(OR(144>IN_PRAZO,MotorImovel!$B$5=0),"",INDEX(MotorImovel!$W$55:$W$295,144+1))
A30: 13 | B30: =IF(OR(156>IN_PRAZO,Motor!$B$9=0),"",INDEX(Motor!$R$61:$R$301,156+1)) | C30: =IF(OR(156>IN_PRAZO,Motor!$C$9=0),"",INDEX(Motor!$AG$61:$AG$301,156+1)) | D30: =IF(OR(156>IN_PRAZO,Motor!$D$9=0),"",INDEX(Motor!$AV$61:$AV$301,156+1)) | E30: =IF(OR(156>IN_PRAZO,Motor!$E$9=0),"",INDEX(Motor!$BK$61:$BK$301,156+1)) | F30: =IF(OR(156>IN_PRAZO,Motor!$F$9=0),"",INDEX(Motor!$BZ$61:$BZ$301,156+1)) | G30: =IF(OR(156>IN_PRAZO,Motor!$G$9=0),"",INDEX(Motor!$CO$61:$CO$301,156+1)) | H30: =IF(OR(156>IN_PRAZO,MotorImovel!$B$5=0),"",INDEX(MotorImovel!$W$55:$W$295,156+1))
A31: 14 | B31: =IF(OR(168>IN_PRAZO,Motor!$B$9=0),"",INDEX(Motor!$R$61:$R$301,168+1)) | C31: =IF(OR(168>IN_PRAZO,Motor!$C$9=0),"",INDEX(Motor!$AG$61:$AG$301,168+1)) | D31: =IF(OR(168>IN_PRAZO,Motor!$D$9=0),"",INDEX(Motor!$AV$61:$AV$301,168+1)) | E31: =IF(OR(168>IN_PRAZO,Motor!$E$9=0),"",INDEX(Motor!$BK$61:$BK$301,168+1)) | F31: =IF(OR(168>IN_PRAZO,Motor!$F$9=0),"",INDEX(Motor!$BZ$61:$BZ$301,168+1)) | G31: =IF(OR(168>IN_PRAZO,Motor!$G$9=0),"",INDEX(Motor!$CO$61:$CO$301,168+1)) | H31: =IF(OR(168>IN_PRAZO,MotorImovel!$B$5=0),"",INDEX(MotorImovel!$W$55:$W$295,168+1))
A32: 15 | B32: =IF(OR(180>IN_PRAZO,Motor!$B$9=0),"",INDEX(Motor!$R$61:$R$301,180+1)) | C32: =IF(OR(180>IN_PRAZO,Motor!$C$9=0),"",INDEX(Motor!$AG$61:$AG$301,180+1)) | D32: =IF(OR(180>IN_PRAZO,Motor!$D$9=0),"",INDEX(Motor!$AV$61:$AV$301,180+1)) | E32: =IF(OR(180>IN_PRAZO,Motor!$E$9=0),"",INDEX(Motor!$BK$61:$BK$301,180+1)) | F32: =IF(OR(180>IN_PRAZO,Motor!$F$9=0),"",INDEX(Motor!$BZ$61:$BZ$301,180+1)) | G32: =IF(OR(180>IN_PRAZO,Motor!$G$9=0),"",INDEX(Motor!$CO$61:$CO$301,180+1)) | H32: =IF(OR(180>IN_PRAZO,MotorImovel!$B$5=0),"",INDEX(MotorImovel!$W$55:$W$295,180+1))
A33: 16 | B33: =IF(OR(192>IN_PRAZO,Motor!$B$9=0),"",INDEX(Motor!$R$61:$R$301,192+1)) | C33: =IF(OR(192>IN_PRAZO,Motor!$C$9=0),"",INDEX(Motor!$AG$61:$AG$301,192+1)) | D33: =IF(OR(192>IN_PRAZO,Motor!$D$9=0),"",INDEX(Motor!$AV$61:$AV$301,192+1)) | E33: =IF(OR(192>IN_PRAZO,Motor!$E$9=0),"",INDEX(Motor!$BK$61:$BK$301,192+1)) | F33: =IF(OR(192>IN_PRAZO,Motor!$F$9=0),"",INDEX(Motor!$BZ$61:$BZ$301,192+1)) | G33: =IF(OR(192>IN_PRAZO,Motor!$G$9=0),"",INDEX(Motor!$CO$61:$CO$301,192+1)) | H33: =IF(OR(192>IN_PRAZO,MotorImovel!$B$5=0),"",INDEX(MotorImovel!$W$55:$W$295,192+1))
A34: 17 | B34: =IF(OR(204>IN_PRAZO,Motor!$B$9=0),"",INDEX(Motor!$R$61:$R$301,204+1)) | C34: =IF(OR(204>IN_PRAZO,Motor!$C$9=0),"",INDEX(Motor!$AG$61:$AG$301,204+1)) | D34: =IF(OR(204>IN_PRAZO,Motor!$D$9=0),"",INDEX(Motor!$AV$61:$AV$301,204+1)) | E34: =IF(OR(204>IN_PRAZO,Motor!$E$9=0),"",INDEX(Motor!$BK$61:$BK$301,204+1)) | F34: =IF(OR(204>IN_PRAZO,Motor!$F$9=0),"",INDEX(Motor!$BZ$61:$BZ$301,204+1)) | G34: =IF(OR(204>IN_PRAZO,Motor!$G$9=0),"",INDEX(Motor!$CO$61:$CO$301,204+1)) | H34: =IF(OR(204>IN_PRAZO,MotorImovel!$B$5=0),"",INDEX(MotorImovel!$W$55:$W$295,204+1))
A35: 18 | B35: =IF(OR(216>IN_PRAZO,Motor!$B$9=0),"",INDEX(Motor!$R$61:$R$301,216+1)) | C35: =IF(OR(216>IN_PRAZO,Motor!$C$9=0),"",INDEX(Motor!$AG$61:$AG$301,216+1)) | D35: =IF(OR(216>IN_PRAZO,Motor!$D$9=0),"",INDEX(Motor!$AV$61:$AV$301,216+1)) | E35: =IF(OR(216>IN_PRAZO,Motor!$E$9=0),"",INDEX(Motor!$BK$61:$BK$301,216+1)) | F35: =IF(OR(216>IN_PRAZO,Motor!$F$9=0),"",INDEX(Motor!$BZ$61:$BZ$301,216+1)) | G35: =IF(OR(216>IN_PRAZO,Motor!$G$9=0),"",INDEX(Motor!$CO$61:$CO$301,216+1)) | H35: =IF(OR(216>IN_PRAZO,MotorImovel!$B$5=0),"",INDEX(MotorImovel!$W$55:$W$295,216+1))
A36: 19 | B36: =IF(OR(228>IN_PRAZO,Motor!$B$9=0),"",INDEX(Motor!$R$61:$R$301,228+1)) | C36: =IF(OR(228>IN_PRAZO,Motor!$C$9=0),"",INDEX(Motor!$AG$61:$AG$301,228+1)) | D36: =IF(OR(228>IN_PRAZO,Motor!$D$9=0),"",INDEX(Motor!$AV$61:$AV$301,228+1)) | E36: =IF(OR(228>IN_PRAZO,Motor!$E$9=0),"",INDEX(Motor!$BK$61:$BK$301,228+1)) | F36: =IF(OR(228>IN_PRAZO,Motor!$F$9=0),"",INDEX(Motor!$BZ$61:$BZ$301,228+1)) | G36: =IF(OR(228>IN_PRAZO,Motor!$G$9=0),"",INDEX(Motor!$CO$61:$CO$301,228+1)) | H36: =IF(OR(228>IN_PRAZO,MotorImovel!$B$5=0),"",INDEX(MotorImovel!$W$55:$W$295,228+1))
A37: 20 | B37: =IF(OR(240>IN_PRAZO,Motor!$B$9=0),"",INDEX(Motor!$R$61:$R$301,240+1)) | C37: =IF(OR(240>IN_PRAZO,Motor!$C$9=0),"",INDEX(Motor!$AG$61:$AG$301,240+1)) | D37: =IF(OR(240>IN_PRAZO,Motor!$D$9=0),"",INDEX(Motor!$AV$61:$AV$301,240+1)) | E37: =IF(OR(240>IN_PRAZO,Motor!$E$9=0),"",INDEX(Motor!$BK$61:$BK$301,240+1)) | F37: =IF(OR(240>IN_PRAZO,Motor!$F$9=0),"",INDEX(Motor!$BZ$61:$BZ$301,240+1)) | G37: =IF(OR(240>IN_PRAZO,Motor!$G$9=0),"",INDEX(Motor!$CO$61:$CO$301,240+1)) | H37: =IF(OR(240>IN_PRAZO,MotorImovel!$B$5=0),"",INDEX(MotorImovel!$W$55:$W$295,240+1))
A92: ⚠ Simulação baseada nas informações e premissas registradas nesta planilha. Os resultados reais podem ser diferentes. Rentabilidade passada não é garantia de rentabilidade futura e nenhum número aqui representa promessa de retorno.
B94: ◀ INÍCIO | D94: ◀ CLIENTE | F94: MÊS A MÊS | H94: VER DETALHES | J94: GERAR RELATÓRIO

Sheet Consultor
A1: MODO CONSULTOR
A2: Premissas, taxas, tributação e a origem de cada número
A4: PARÂMETROS DA SIMULAÇÃO
B5: Cenário de premissas | D5: Base | E5: Cenário não é promessa. É um conjunto de premissas escolhido por você.
B6: Data de início da simulação | D6: =TODAY() -> 46257 | E6: Define o mês do come-cotas e as datas de carência.
B7: Corrigir o aporte mensal pela inflação? | D7: Não | E7: Se Sim, o aporte cresce junto com o IPCA do cenário.
B8: Preencher as alternativas com a sugestão automática? | D8: Sim | E8: Se Sim, os seis lugares usam a ordem de aderência da aba Adequação.
B9: Reinvestir a restituição do PGBL? | D9: Sim | E9: Se Sim, o benefício fiscal volta como aporte extra em maio de cada ano.
B10: Renda bruta anual tributável do cliente | D10: 0 | E10: Base do limite de 12% de dedução do PGBL.
B11: Alíquota marginal do IRPF do cliente | D11: 0.275 | E11: Quanto o cliente deixa de pagar sobre cada real deduzido.
B12: O cliente declara IR no modelo completo? | D12: Não | E12: Sem isso, o PGBL perde a razão de existir e o VGBL costuma ser o caminho.
B13: ➜ Benefício fiscal anual do PGBL | D13: =IF(PGBL_COMPLETA<>"Sim",0,MIN(IN_APORTE*12,PGBL_RENDA*LIMITE_PGBL)*PGBL_ALIQ) -> 0 | E13: =IF(PGBL_COMPLETA<>"Sim","O cliente não declara no modelo completo: o PGBL não gera benefício e o VGBL tende a ser o caminho.","Valor recorrente por ano. No primeiro ano o aporte inicial também é dedutível, gerando um benefício adicional de "&TEXT(MIN(IN_CAPITAL,MAX(0,PGBL_RENDA*LIMITE_PGBL-IN_APORTE*12))*PGBL_ALIQ,"R$ #,##0")&".") -> O cliente não declara no modelo completo: o PGBL não gera benefício e o VGBL tende a ser o caminho.
A15: ALTERNATIVAS EM COMPARAÇÃO
B16: Lugar | C16: Escolha manual | D16: Aderência da escolha | E16: Sugestão automática | G16: Nota | H16: EM USO NA SIMULAÇÃO
B17: A | D17: =IFERROR(IF($C17="","",INDEX(Adequacao!$S$9:$S$78,MATCH($C17,Adequacao!$B$9:$B$78,0))),"") | E17: =Adequacao!$B$82 -> Tesouro Prefixado 2031 | G17: =Adequacao!$C$82 -> 96.3 | H17: =IF(AUTO_SUGESTAO="Sim",Adequacao!$B$82,$C17) -> Tesouro Prefixado 2031 | J17: =IF(AUTO_SUGESTAO="Sim","A sugestão automática está LIGADA: a coluna EM USO segue a ordem de aderência. Para escolher à mão, mude o parâmetro para Não e preencha a coluna Escolha manual.","A sugestão automática está DESLIGADA: vale o que você escolher na coluna Escolha manual. A coluna Sugestão automática continua visível só para comparação.") -> A sugestão automática está LIGADA: a coluna EM USO segue a ordem de aderência. Para escolher à mão, mude o parâmetro para Não e preencha a coluna Escolha manual.
B18: B | D18: =IFERROR(IF($C18="","",INDEX(Adequacao!$S$9:$S$78,MATCH($C18,Adequacao!$B$9:$B$78,0))),"") | E18: =Adequacao!$B$83 -> Tesouro IPCA+ 2035 | G18: =Adequacao!$C$83 -> 96.3 | H18: =IF(AUTO_SUGESTAO="Sim",Adequacao!$B$83,$C18) -> Tesouro IPCA+ 2035
B19: C | D19: =IFERROR(IF($C19="","",INDEX(Adequacao!$S$9:$S$78,MATCH($C19,Adequacao!$B$9:$B$78,0))),"") | E19: =Adequacao!$B$84 -> Fundo CAIXA RF Crédito Privado LP | G19: =Adequacao!$C$84 -> 94 | H19: =IF(AUTO_SUGESTAO="Sim",Adequacao!$B$84,$C19) -> Fundo CAIXA RF Crédito Privado LP
B20: D | D20: =IFERROR(IF($C20="","",INDEX(Adequacao!$S$9:$S$78,MATCH($C20,Adequacao!$B$9:$B$78,0))),"") | E20: =Adequacao!$B$85 -> VGBL CAIXA Composto 30 — Regressivo | G20: =Adequacao!$C$85 -> 91.3 | H20: =IF(AUTO_SUGESTAO="Sim",Adequacao!$B$85,$C20) -> VGBL CAIXA Composto 30 — Regressivo
B21: E | D21: =IFERROR(IF($C21="","",INDEX(Adequacao!$S$9:$S$78,MATCH($C21,Adequacao!$B$9:$B$78,0))),"") | E21: =Adequacao!$B$86 -> PGBL CAIXA Composto 30 — Regressivo | G21: =Adequacao!$C$86 -> 91.3 | H21: =IF(AUTO_SUGESTAO="Sim",Adequacao!$B$86,$C21) -> PGBL CAIXA Composto 30 — Regressivo
B22: F | D22: =IFERROR(IF($C22="","",INDEX(Adequacao!$S$9:$S$78,MATCH($C22,Adequacao!$B$9:$B$78,0))),"") | E22: =Adequacao!$B$87 -> Fundo CAIXA RF IPCA Longo Prazo | G22: =Adequacao!$C$87 -> 90.5 | H22: =IF(AUTO_SUGESTAO="Sim",Adequacao!$B$87,$C22) -> Fundo CAIXA RF IPCA Longo Prazo
A24: PAINEL TÉCNICO — DE ONDE VEM CADA NÚMERO
B25: Parâmetro | D25: =IF(Motor!$B$9=0,"(A) não usada",Motor!$B$6) -> Tesouro Prefixado 2031 | E25: =IF(Motor!$C$9=0,"(B) não usada",Motor!$C$6) -> Tesouro IPCA+ 2035 | F25: =IF(Motor!$D$9=0,"(C) não usada",Motor!$D$6) -> Fundo CAIXA RF Crédito Privado LP | G25: =IF(Motor!$E$9=0,"(D) não usada",Motor!$E$6) -> VGBL CAIXA Composto 30 — Regressivo | H25: =IF(Motor!$F$9=0,"(E) não usada",Motor!$F$6) -> PGBL CAIXA Composto 30 — Regressivo | I25: =IF(Motor!$G$9=0,"(F) não usada",Motor!$G$6) -> Fundo CAIXA RF IPCA Longo Prazo | J25: =IF(MotorImovel!$B$5=0,"(imóvel fora)","Imóvel para aluguel") -> Imóvel para aluguel
B26: Produto | D26: =Motor!$B$6 -> Tesouro Prefixado 2031 | E26: =Motor!$C$6 -> Tesouro IPCA+ 2035 | F26: =Motor!$D$6 -> Fundo CAIXA RF Crédito Privado LP | G26: =Motor!$E$6 -> VGBL CAIXA Composto 30 — Regressivo | H26: =Motor!$F$6 -> PGBL CAIXA Composto 30 — Regressivo | I26: =Motor!$G$6 -> Fundo CAIXA RF IPCA Longo Prazo | J26: ="Imóvel para aluguel" -> Imóvel para aluguel
B27: Categoria | D27: =Motor!$B$10 -> Renda Fixa | E27: =Motor!$C$10 -> Renda Fixa | F27: =Motor!$D$10 -> Fundo | G27: =Motor!$E$10 -> Previdência | H27: =Motor!$F$10 -> Previdência | I27: =Motor!$G$10 -> Fundo | J27: ="Imobiliário" -> Imobiliário
B28: Emissor / gestor | D28: =Motor!$B$11 -> Tesouro Nacional | E28: =Motor!$C$11 -> Tesouro Nacional | F28: =Motor!$D$11 -> CAIXA Asset | G28: =Motor!$E$11 -> CAIXA Vida e Previdência | H28: =Motor!$F$11 -> CAIXA Vida e Previdência | I28: =Motor!$G$11 -> CAIXA Asset | J28: ="Mercado" -> Mercado
B29: Indexador | D29: =Motor!$B$12 -> PRE | E29: =Motor!$C$12 -> IPCA | F29: =Motor!$D$12 -> CDI | G29: =Motor!$E$12 -> CDI | H29: =Motor!$F$12 -> CDI | I29: =Motor!$G$12 -> IPCA | J29: ="Valorização + aluguel" -> Valorização + aluguel
B30: % do indexador | D30: =Motor!$B$13 -> 1 | E30: =Motor!$C$13 -> 1 | F30: =Motor!$D$13 -> 1.04 | G30: =Motor!$E$13 -> 1 | H30: =Motor!$F$13 -> 1 | I30: =Motor!$G$13 -> 1 | J30: =1 -> 1
B31: Spread contratado a.a. | D31: =Motor!$B$14 -> 0.12 | E31: =Motor!$C$14 -> 0.06 | F31: =Motor!$D$14 -> 0 | G31: =Motor!$E$14 -> 0.015 | H31: =Motor!$F$14 -> 0.015 | I31: =Motor!$G$14 -> 0.06 | J31: =MotorImovel!$B$20 -> 0.04
B32: Retorno BRUTO a.a. no cenário | D32: =Motor!$B$17 -> 0.12 | E32: =Motor!$C$17 -> 0.1024 | F32: =Motor!$D$17 -> 0.11336 | G32: =Motor!$E$17 -> 0.124 | H32: =Motor!$F$17 -> 0.124 | I32: =Motor!$G$17 -> 0.1024 | J32: =MotorImovel!$B$20 -> 0.04
B33: Taxa de administração a.a. | D33: =Motor!$B$20 -> 0 | E33: =Motor!$C$20 -> 0 | F33: =Motor!$D$20 -> 0.01 | G33: =Motor!$E$20 -> 0.015 | H33: =Motor!$F$20 -> 0.015 | I33: =Motor!$G$20 -> 0.01 | J33: =MotorImovel!$B$19 -> 0.08
B34: Custódia a.a. | D34: =Motor!$B$21 -> 0.002 | E34: =Motor!$C$21 -> 0.002 | F34: =Motor!$D$21 -> 0 | G34: =Motor!$E$21 -> 0 | H34: =Motor!$F$21 -> 0 | I34: =Motor!$G$21 -> 0 | J34: =MotorImovel!$B$17 -> 0.006
B35: Taxa de performance | D35: =Motor!$B$23 -> 0 | E35: =Motor!$C$23 -> 0 | F35: =Motor!$D$23 -> 0 | G35: =Motor!$E$23 -> 0 | H35: =Motor!$F$23 -> 0 | I35: =Motor!$G$23 -> 0 | J35: =0 -> 0
B36: Carregamento entrada / saída | D36: =TEXT(Motor!$B$24,"0.00%")&" / "&TEXT(Motor!$B$25,"0.00%") -> 0.00% / 0.00% | E36: =TEXT(Motor!$C$24,"0.00%")&" / "&TEXT(Motor!$C$25,"0.00%") -> 0.00% / 0.00% | F36: =TEXT(Motor!$D$24,"0.00%")&" / "&TEXT(Motor!$D$25,"0.00%") -> 0.00% / 0.00% | G36: =TEXT(Motor!$E$24,"0.00%")&" / "&TEXT(Motor!$E$25,"0.00%") -> 0.00% / 0.00% | H36: =TEXT(Motor!$F$24,"0.00%")&" / "&TEXT(Motor!$F$25,"0.00%") -> 0.00% / 0.00% | I36: =TEXT(Motor!$G$24,"0.00%")&" / "&TEXT(Motor!$G$25,"0.00%") -> 0.00% / 0.00% | J36: ="—" -> —
B37: Retorno LÍQUIDO a.a. estimado | D37: =Motor!$B$36 -> 0.11778307 | E37: =Motor!$C$36 -> 0.10021503 | F37: =Motor!$D$36 -> 0.10237557 | G37: =Motor!$E$36 -> 0.10741665 | H37: =Motor!$F$36 -> 0.10741665 | I37: =Motor!$G$36 -> 0.091514773 | J37: =MotorImovel!$B$42 -> 0.078287294
B38: Regime tributário | D38: =Motor!$B$8 -> RF_REGR | E38: =Motor!$C$8 -> RF_REGR | F38: =Motor!$D$8 -> FUNDO_LP | G38: =Motor!$E$8 -> PREV_REGR | H38: =Motor!$F$8 -> PREV_REGR | I38: =Motor!$G$8 -> FUNDO_LP | J38: ="Carnê-leão + ganho de capital" -> Carnê-leão + ganho de capital
B39: Come-cotas | D39: =Motor!$B$27 -> 0 | E39: =Motor!$C$27 -> 0 | F39: =Motor!$D$27 -> 1 | G39: =Motor!$E$27 -> 0 | H39: =Motor!$F$27 -> 0 | I39: =Motor!$G$27 -> 1 | J39: =0 -> 0
B40: Carência (dias) | D40: =Motor!$B$29 -> 0 | E40: =Motor!$C$29 -> 0 | F40: =Motor!$D$29 -> 0 | G40: =Motor!$E$29 -> 0 | H40: =Motor!$F$29 -> 0 | I40: =Motor!$G$29 -> 0 | J40: ="—" -> —
B41: Liquidez após carência (dias) | D41: =Motor!$B$30 -> 1 | E41: =Motor!$C$30 -> 1 | F41: =Motor!$D$30 -> 30 | G41: =Motor!$E$30 -> 5 | H41: =Motor!$F$30 -> 5 | I41: =Motor!$G$30 -> 5 | J41: ="meses" -> meses
B42: Aplicação mínima | D42: =Motor!$B$31 -> 100 | E42: =Motor!$C$31 -> 100 | F42: =Motor!$D$31 -> 5000 | G42: =Motor!$E$31 -> 5000 | H42: =Motor!$F$31 -> 5000 | I42: =Motor!$G$31 -> 5000 | J42: =MotorImovel!$B$10 -> 155250
B43: Risco (1-5) | D43: =Motor!$B$32 -> 2 | E43: =Motor!$C$32 -> 2 | F43: =Motor!$D$32 -> 2 | G43: =Motor!$E$32 -> 3 | H43: =Motor!$F$32 -> 3 | I43: =Motor!$G$32 -> 3 | J43: =3 -> 3
B44: Volatilidade a.a. | D44: =Motor!$B$33 -> 0.06 | E44: =Motor!$C$33 -> 0.08 | F44: =Motor!$D$33 -> 0.01 | G44: =Motor!$E$33 -> 0.06 | H44: =Motor!$F$33 -> 0.06 | I44: =Motor!$G$33 -> 0.08 | J44: =0.07 -> 0.07
B45: Garantia | D45: =Motor!$B$34 -> Tesouro Nacional | E45: =Motor!$C$34 -> Tesouro Nacional | F45: =Motor!$D$34 -> Sem garantia do FGC | G45: =Motor!$E$34 -> Seguradora (sem FGC) | H45: =Motor!$F$34 -> Seguradora (sem FGC) | I45: =Motor!$G$34 -> Sem garantia do FGC | J45: ="Nenhuma" -> Nenhuma
B46: Alíquota de IR no prazo escolhido | D46: =Motor!$B$50 -> 0.15 | E46: =Motor!$C$50 -> 0.15 | F46: =Motor!$D$50 -> 0.15 | G46: =Motor!$E$50 -> 0.15 | H46: =Motor!$F$50 -> 0.15 | I46: =Motor!$G$50 -> 0.15 | J46: =MotorImovel!$B$44 -> 0.15
B47: Imposto total pago no período | D47: =Motor!$B$45 -> 46010.603 | E47: =Motor!$C$45 -> 35973.386 | F47: =Motor!$D$45 -> 34319.518 | G47: =Motor!$E$45 -> 39915.578 | H47: =Motor!$F$45 -> 62415.578 | I47: =Motor!$G$45 -> 29381.56 | J47: =MotorImovel!$B$39 -> 16294.186
B48: Custos totais pagos no período | D48: =Motor!$B$46 -> 5484.0377 | E48: =Motor!$C$46 -> 5002.2069 | F48: =Motor!$D$46 -> 23378.968 | G48: =Motor!$E$46 -> 38955.35 | H48: =Motor!$F$46 -> 38955.35 | I48: =Motor!$G$46 -> 22287.452 | J48: =MotorImovel!$B$40 -> 68286.677
B49: Patrimônio líquido no prazo | D49: =Motor!$B$40 -> 410726.75 | E49: =Motor!$C$40 -> 353849.19 | F49: =Motor!$D$40 -> 344477.27 | G49: =Motor!$E$40 -> 376188.27 | H49: =Motor!$F$40 -> 353688.27 | I49: =Motor!$G$40 -> 316495.51 | J49: =MotorImovel!$B$34 -> 329895.57
B50: Status do dado | D50: =IFERROR(INDEX(Produtos!$AB$9:$AB$78,Motor!$B$7),"—") -> EXEMPLO — VERIFICAR | E50: =IFERROR(INDEX(Produtos!$AB$9:$AB$78,Motor!$C$7),"—") -> EXEMPLO — VERIFICAR | F50: =IFERROR(INDEX(Produtos!$AB$9:$AB$78,Motor!$D$7),"—") -> EXEMPLO — VERIFICAR | G50: =IFERROR(INDEX(Produtos!$AB$9:$AB$78,Motor!$E$7),"—") -> EXEMPLO — VERIFICAR | H50: =IFERROR(INDEX(Produtos!$AB$9:$AB$78,Motor!$F$7),"—") -> EXEMPLO — VERIFICAR | I50: =IFERROR(INDEX(Produtos!$AB$9:$AB$78,Motor!$G$7),"—") -> EXEMPLO — VERIFICAR | J50: ="ver aba Imóvel" -> ver aba Imóvel
B51: Atualizado em | D51: =IFERROR(INDEX(Produtos!$Y$9:$Y$78,Motor!$B$7),"—") -> 2026-08-23 | E51: =IFERROR(INDEX(Produtos!$Y$9:$Y$78,Motor!$C$7),"—") -> 2026-08-23 | F51: =IFERROR(INDEX(Produtos!$Y$9:$Y$78,Motor!$D$7),"—") -> 2026-08-23 | G51: =IFERROR(INDEX(Produtos!$Y$9:$Y$78,Motor!$E$7),"—") -> 2026-08-23 | H51: =IFERROR(INDEX(Produtos!$Y$9:$Y$78,Motor!$F$7),"—") -> 2026-08-23 | I51: =IFERROR(INDEX(Produtos!$Y$9:$Y$78,Motor!$G$7),"—") -> 2026-08-23 | J51: =DATA_DADOS -> 2026-08-23
B52: Tipo de dado | D52: =IFERROR(INDEX(Produtos!$AA$9:$AA$78,Motor!$B$7),"—") -> Diário (D+1) | E52: =IFERROR(INDEX(Produtos!$AA$9:$AA$78,Motor!$C$7),"—") -> Diário (D+1) | F52: =IFERROR(INDEX(Produtos!$AA$9:$AA$78,Motor!$D$7),"—") -> Diário (D+1) | G52: =IFERROR(INDEX(Produtos!$AA$9:$AA$78,Motor!$E$7),"—") -> Cadastral | H52: =IFERROR(INDEX(Produtos!$AA$9:$AA$78,Motor!$F$7),"—") -> Cadastral | I52: =IFERROR(INDEX(Produtos!$AA$9:$AA$78,Motor!$G$7),"—") -> Diário (D+1) | J52: ="ver aba Imóvel" -> ver aba Imóvel
B53: Fonte | D53: =IFERROR(INDEX(Produtos!$Z$9:$Z$78,Motor!$B$7),"—") -> Tesouro Transparente — taxas dos títulos | E53: =IFERROR(INDEX(Produtos!$Z$9:$Z$78,Motor!$C$7),"—") -> Tesouro Transparente — taxas dos títulos | F53: =IFERROR(INDEX(Produtos!$Z$9:$Z$78,Motor!$D$7),"—") -> CAIXA Asset — portfólio de fundos (lâmina) | G53: =IFERROR(INDEX(Produtos!$Z$9:$Z$78,Motor!$E$7),"—") -> Regulamento do plano + tabela de taxas | H53: =IFERROR(INDEX(Produtos!$Z$9:$Z$78,Motor!$F$7),"—") -> Regulamento do plano + tabela de taxas | I53: =IFERROR(INDEX(Produtos!$Z$9:$Z$78,Motor!$G$7),"—") -> CAIXA Asset — portfólio de fundos (lâmina) | J53: ="ver aba Imóvel" -> ver aba Imóvel
A55: CONFERÊNCIAS ANTES DE OFERECER
B56: =IF(SUMIF(Motor!$B$34:$G$34,"FGC*",Motor!$B$40:$G$40)>LIMITE_FGC,"⚠ FGC: a soma projetada em produtos cobertos ultrapassa o limite por CPF e instituição ("&TEXT(LIMITE_FGC,"R$ #,##0")&"). Avalie distribuir entre emissores.","✓ FGC: a soma projetada em produtos cobertos está dentro do limite.") -> ✓ FGC: a soma projetada em produtos cobertos está dentro do limite.
B57: =IF(COUNTIF(Motor!$B$54:$G$54,0)-COUNTIF(Motor!$B$9:$G$9,0)>0,"⚠ Aplicação mínima: alguma alternativa em uso exige mais do que o cliente tem disponível.","✓ Aplicação mínima: todas as alternativas em uso cabem no valor disponível.") -> ✓ Aplicação mínima: todas as alternativas em uso cabem no valor disponível.
B58: =IF(COUNTIF(Motor!$B$55:$G$55,0)-COUNTIF(Motor!$B$9:$G$9,0)>0,"⚠ Perfil: há alternativa em uso com risco acima do perfil declarado. Isso precisa ser tratado no processo oficial de suitability.","✓ Perfil: nenhuma alternativa em uso ultrapassa o perfil declarado.") -> ✓ Perfil: nenhuma alternativa em uso ultrapassa o perfil declarado.
B59: =IF(COUNTIF(Produtos!$AB$9:$AB$78,"EXEMPLO*")>0,"⚠ Dados: há produtos na base com taxa de exemplo, ainda não conferida. Atualize antes de apresentar números ao cliente.","✓ Dados: todos os produtos da base estão marcados como conferidos.") -> ⚠ Dados: há produtos na base com taxa de exemplo, ainda não conferida. Atualize antes de apresentar números ao cliente.
B60: =IF(AND(IMOV_INCLUIR="Sim",MotorImovel!$B$12<0),"⚠ Imóvel: faltam "&TEXT(-MotorImovel!$B$12,"R$ #,##0")&" para fechar a compra com os custos de aquisição. A comparação fica desigual enquanto isso.","✓ Imóvel: o capital disponível cobre o valor do imóvel e os custos de aquisição.") -> ⚠ Imóvel: faltam R$ 5,250 para fechar a compra com os custos de aquisição. A comparação fica desigual enquanto isso.
B61: =IF(AND(PGBL_COMPLETA<>"Sim",COUNTIF(Motor!$B$35:$G$35,1)>0),"⚠ PGBL: há PGBL na comparação, mas o cliente não declara no modelo completo. Sem a dedução, o PGBL costuma perder para o VGBL.","✓ PGBL: a escolha entre PGBL e VGBL está coerente com a forma de declaração informada.") -> ⚠ PGBL: há PGBL na comparação, mas o cliente não declara no modelo completo. Sem a dedução, o PGBL costuma perder para o VGBL.
B62: =IF(AND(IN_RESGATE="Sim",MAX(Motor!$B$29:$G$29)>0),"⚠ Liquidez: o cliente disse que pode precisar do dinheiro antes, mas há alternativa com carência.","✓ Liquidez: as alternativas em uso são compatíveis com a resposta sobre resgate antecipado.") -> ✓ Liquidez: as alternativas em uso são compatíveis com a resposta sobre resgate antecipado.
A64: RESGATE ANTES DE 30 DIAS — IOF (a projeção mensal não cobre esse caso)
B65: Valor aplicado | D65: 10000 | E65: =$D$65*((1+CDI_CENARIO*$D$67)^($D$66/365)-1) -> 28.385061 | F65: Rendimento bruto no período
B66: Dias de aplicação | D66: 10 | E66: =IF($D$66>=30,0,IFERROR(INDEX(Premissas!$B$44:$B$73,MAX(1,$D$66)),0)) -> 0.66 | F66: IOF (% do rendimento)
B67: Taxa do produto (% do CDI) | D67: 1 | E67: =$E$65*$E$66 -> 18.73414 | F67: IOF em reais
E68: =($E$65-$E$67)*0.225 -> 2.1714572 | F68: IR (22,5% sobre o rendimento após IOF)
E69: =$D$65+$E$65-$E$67-$E$68 -> 10007.479 | F69: Valor líquido resgatado
A71: O IOF some a partir do 30º dia. O IR mostrado usa a alíquota máxima da tabela regressiva (22,5%), que é a que vale nos primeiros 180 dias.
A73: ⚠ Ferramenta de apoio à conversa, de uso do profissional. Não é peça oficial de oferta e não substitui a lâmina, o regulamento, o prospecto do produto nem o questionário oficial de perfil (suitability).
B75: ◀ INÍCIO | D75: ◀ CLIENTE | F75: MÊS A MÊS | H75: PREMISSAS | J75: PRODUTOS | L75: FONTES

Sheet MesAMes
A1: PROJEÇÃO MÊS A MÊS
A2: Cada linha mostra exatamente de onde veio cada número
B4: Alternativa em exibição | D4: A | E4: =IFERROR(INDEX(Motor!$B$6:$G$6,$D$5),"(não escolhida)") -> Tesouro Prefixado 2031 | I4: ◀ INÍCIO | J4: ◀ CLIENTE | K4: COMPARAR
B5: (número do lugar escolhido — calculado) | D5: =IFERROR(MATCH("ALTERNATIVA "&MES_DETALHE,Motor!$B$5:$G$5,0),1) -> 1 | E5: ="O imóvel tem mecânica própria e é detalhado na aba MotorImovel, a partir da aba Imóvel." -> O imóvel tem mecânica própria e é detalhado na aba MotorImovel, a partir da aba Imóvel.
A6: As linhas depois do prazo escolhido aparecem esmaecidas: elas mostram o que aconteceria se o cliente deixasse o dinheiro por mais tempo.
A8: Mês | B8: Data | C8: Saldo inicial | D8: Rendimento bruto | E8: Aporte | F8: Custos | G8: Imposto no mês | H8: Saldo final | I8: IR se resgatar agora | J8: Valor líquido no resgate | K8: Valor líquido em R$ de hoje | M8: Legenda
A9: 0 | B9: =EDATE(DATA_INICIO,$A9) -> 46257 | C9: =IFERROR(INDEX(Motor!$F$61:$CP$301,$A9+1,($D$5-1)*15+1),0) -> 0 | D9: =IFERROR(INDEX(Motor!$F$61:$CP$301,$A9+1,($D$5-1)*15+4),0) -> 0 | E9: =IFERROR(INDEX(Motor!$F$61:$CP$301,$A9+1,($D$5-1)*15+2),0) -> 150000 | F9: =IFERROR(INDEX(Motor!$F$61:$CP$301,$A9+1,($D$5-1)*15+3)+INDEX(Motor!$F$61:$CP$301,$A9+1,($D$5-1)*15+5)+INDEX(Motor!$F$61:$CP$301,$A9+1,($D$5-1)*15+6),0) -> 0 | G9: =IFERROR(INDEX(Motor!$F$61:$CP$301,$A9+1,($D$5-1)*15+7),0) -> 0 | H9: =IFERROR(INDEX(Motor!$F$61:$CP$301,$A9+1,($D$5-1)*15+8),0) -> 150000 | I9: =IFERROR(INDEX(Motor!$F$61:$CP$301,$A9+1,($D$5-1)*15+12),0) -> 0 | J9: =IFERROR(INDEX(Motor!$F$61:$CP$301,$A9+1,($D$5-1)*15+13),0) -> 150000 | K9: =IFERROR(INDEX(Motor!$F$61:$CP$301,$A9+1,($D$5-1)*15+14),0) -> 150000 | M9: Linha verde: o mês do prazo escolhido pelo cliente.
A10: 1 | B10: =EDATE(DATA_INICIO,$A10) -> 46288 | C10: =IFERROR(INDEX(Motor!$F$61:$CP$301,$A10+1,($D$5-1)*15+1),0) -> 150000 | D10: =IFERROR(INDEX(Motor!$F$61:$CP$301,$A10+1,($D$5-1)*15+4),0) -> 1423.3189 | E10: =IFERROR(INDEX(Motor!$F$61:$CP$301,$A10+1,($D$5-1)*15+2),0) -> 0 | F10: =IFERROR(INDEX(Motor!$F$61:$CP$301,$A10+1,($D$5-1)*15+3)+INDEX(Motor!$F$61:$CP$301,$A10+1,($D$5-1)*15+5)+INDEX(Motor!$F$61:$CP$301,$A10+1,($D$5-1)*15+6),0) -> 25 | G10: =IFERROR(INDEX(Motor!$F$61:$CP$301,$A10+1,($D$5-1)*15+7),0) -> 0 | H10: =IFERROR(INDEX(Motor!$F$61:$CP$301,$A10+1,($D$5-1)*15+8),0) -> 151398.32 | I10: =IFERROR(INDEX(Motor!$F$61:$CP$301,$A10+1,($D$5-1)*15+12),0) -> 314.62176 | J10: =IFERROR(INDEX(Motor!$F$61:$CP$301,$A10+1,($D$5-1)*15+13),0) -> 151083.7 | K10: =IFERROR(INDEX(Motor!$F$61:$CP$301,$A10+1,($D$5-1)*15+14),0) -> 150590.7 | M10: Linha âmbar: mês em que houve come-cotas (maio e novembro).
A11: 2 | B11: =EDATE(DATA_INICIO,$A11) -> 46318 | C11: =IFERROR(INDEX(Motor!$F$61:$CP$301,$A11+1,($D$5-1)*15+1),0) -> 151398.32 | D11: =IFERROR(INDEX(Motor!$F$61:$CP$301,$A11+1,($D$5-1)*15+4),0) -> 1436.5873 | E11: =IFERROR(INDEX(Motor!$F$61:$CP$301,$A11+1,($D$5-1)*15+2),0) -> 0 | F11: =IFERROR(INDEX(Motor!$F$61:$CP$301,$A11+1,($D$5-1)*15+3)+INDEX(Motor!$F$61:$CP$301,$A11+1,($D$5-1)*15+5)+INDEX(Motor!$F$61:$CP$301,$A11+1,($D$5-1)*15+6),0) -> 25.233053 | G11: =IFERROR(INDEX(Motor!$F$61:$CP$301,$A11+1,($D$5-1)*15+7),0) -> 0 | H11: =IFERROR(INDEX(Motor!$F$61:$CP$301,$A11+1,($D$5-1)*15+8),0) -> 152809.67 | I11: =IFERROR(INDEX(Motor!$F$61:$CP$301,$A11+1,($D$5-1)*15+12),0) -> 632.17647 | J11: =IFERROR(INDEX(Motor!$F$61:$CP$301,$A11+1,($D$5-1)*15+13),0) -> 152177.5 | K11: =IFERROR(INDEX(Motor!$F$61:$CP$301,$A11+1,($D$5-1)*15+14),0) -> 151185.99 | M11: Linha cinza: já passou do prazo escolhido.
A12: 3 | B12: =EDATE(DATA_INICIO,$A12) -> 46349 | C12: =IFERROR(INDEX(Motor!$F$61:$CP$301,$A12+1,($D$5-1)*15+1),0) -> 152809.67 | D12: =IFERROR(INDEX(Motor!$F$61:$CP$301,$A12+1,($D$5-1)*15+4),0) -> 1449.9793 | E12: =IFERROR(INDEX(Motor!$F$61:$CP$301,$A12+1,($D$5-1)*15+2),0) -> 0 | F12: =IFERROR(INDEX(Motor!$F$61:$CP$301,$A12+1,($D$5-1)*15+3)+INDEX(Motor!$F$61:$CP$301,$A12+1,($D$5-1)*15+5)+INDEX(Motor!$F$61:$CP$301,$A12+1,($D$5-1)*15+6),0) -> 25.468279 | G12: =IFERROR(INDEX(Motor!$F$61:$CP$301,$A12+1,($D$5-1)*15+7),0) -> 0 | H12: =IFERROR(INDEX(Motor!$F$61:$CP$301,$A12+1,($D$5-1)*15+8),0) -> 154234.18 | I12: =IFERROR(INDEX(Motor!$F$61:$CP$301,$A12+1,($D$5-1)*15+12),0) -> 952.69146 | J12: =IFERROR(INDEX(Motor!$F$61:$CP$301,$A12+1,($D$5-1)*15+13),0) -> 153281.49 | K12: =IFERROR(INDEX(Motor!$F$61:$CP$301,$A12+1,($D$5-1)*15+14),0) -> 151785.88
A13: 4 | B13: =EDATE(DATA_INICIO,$A13) -> 46379 | C13: =IFERROR(INDEX(Motor!$F$61:$CP$301,$A13+1,($D$5-1)*15+1),0) -> 154234.18 | D13: =IFERROR(INDEX(Motor!$F$61:$CP$301,$A13+1,($D$5-1)*15+4),0) -> 1463.4962 | E13: =IFERROR(INDEX(Motor!$F$61:$CP$301,$A13+1,($D$5-1)*15+2),0) -> 0 | F13: =IFERROR(INDEX(Motor!$F$61:$CP$301,$A13+1,($D$5-1)*15+3)+INDEX(Motor!$F$61:$CP$301,$A13+1,($D$5-1)*15+5)+INDEX(Motor!$F$61:$CP$301,$A13+1,($D$5-1)*15+6),0) -> 25.705697 | G13: =IFERROR(INDEX(Motor!$F$61:$CP$301,$A13+1,($D$5-1)*15+7),0) -> 0 | H13: =IFERROR(INDEX(Motor!$F$61:$CP$301,$A13+1,($D$5-1)*15+8),0) -> 155671.97 | I13: =IFERROR(INDEX(Motor!$F$61:$CP$301,$A13+1,($D$5-1)*15+12),0) -> 1276.1943 | J13: =IFERROR(INDEX(Motor!$F$61:$CP$301,$A13+1,($D$5-1)*15+13),0) -> 154395.78 | K13: =IFERROR(INDEX(Motor!$F$61:$CP$301,$A13+1,($D$5-1)*15+14),0) -> 152390.41
A14: 5 | B14: =EDATE(DATA_INICIO,$A14) -> 46410 | C14: =IFERROR(INDEX(Motor!$F$61:$CP$301,$A14+1,($D$5-1)*15+1),0) -> 155671.97 | D14: =IFERROR(INDEX(Motor!$F$61:$CP$301,$A14+1,($D$5-1)*15+4),0) -> 1477.1391 | E14: =IFERROR(INDEX(Motor!$F$61:$CP$301,$A14+1,($D$5-1)*15+2),0) -> 0 | F14: =IFERROR(INDEX(Motor!$F$61:$CP$301,$A14+1,($D$5-1)*15+3)+INDEX(Motor!$F$61:$CP$301,$A14+1,($D$5-1)*15+5)+INDEX(Motor!$F$61:$CP$301,$A14+1,($D$5-1)*15+6),0) -> 25.945329 | G14: =IFERROR(INDEX(Motor!$F$61:$CP$301,$A14+1,($D$5-1)*15+7),0) -> 0 | H14: =IFERROR(INDEX(Motor!$F$61:$CP$301,$A14+1,($D$5-1)*15+8),0) -> 157123.17 | I14: =IFERROR(INDEX(Motor!$F$61:$CP$301,$A14+1,($D$5-1)*15+12),0) -> 1602.7129 | J14: =IFERROR(INDEX(Motor!$F$61:$CP$301,$A14+1,($D$5-1)*15+13),0) -> 155520.46 | K14: =IFERROR(INDEX(Motor!$F$61:$CP$301,$A14+1,($D$5-1)*15+14),0) -> 152999.6
A15: 6 | B15: =EDATE(DATA_INICIO,$A15) -> 46441 | C15: =IFERROR(INDEX(Motor!$F$61:$CP$301,$A15+1,($D$5-1)*15+1),0) -> 157123.17 | D15: =IFERROR(INDEX(Motor!$F$61:$CP$301,$A15+1,($D$5-1)*15+4),0) -> 1490.9092 | E15: =IFERROR(INDEX(Motor!$F$61:$CP$301,$A15+1,($D$5-1)*15+2),0) -> 0 | F15: =IFERROR(INDEX(Motor!$F$61:$CP$301,$A15+1,($D$5-1)*15+3)+INDEX(Motor!$F$61:$CP$301,$A15+1,($D$5-1)*15+5)+INDEX(Motor!$F$61:$CP$301,$A15+1,($D$5-1)*15+6),0) -> 26.187195 | G15: =IFERROR(INDEX(Motor!$F$61:$CP$301,$A15+1,($D$5-1)*15+7),0) -> 0 | H15: =IFERROR(INDEX(Motor!$F$61:$CP$301,$A15+1,($D$5-1)*15+8),0) -> 158587.89 | I15: =IFERROR(INDEX(Motor!$F$61:$CP$301,$A15+1,($D$5-1)*15+12),0) -> 1932.2754 | J15: =IFERROR(INDEX(Motor!$F$61:$CP$301,$A15+1,($D$5-1)*15+13),0) -> 156655.62 | K15: =IFERROR(INDEX(Motor!$F$61:$CP$301,$A15+1,($D$5-1)*15+14),0) -> 153613.47
A16: 7 | B16: =EDATE(DATA_INICIO,$A16) -> 46469 | C16: =IFERROR(INDEX(Motor!$F$61:$CP$301,$A16+1,($D$5-1)*15+1),0) -> 158587.89 | D16: =IFERROR(INDEX(Motor!$F$61:$CP$301,$A16+1,($D$5-1)*15+4),0) -> 1504.8077 | E16: =IFERROR(INDEX(Motor!$F$61:$CP$301,$A16+1,($D$5-1)*15+2),0) -> 0 | F16: =IFERROR(INDEX(Motor!$F$61:$CP$301,$A16+1,($D$5-1)*15+3)+INDEX(Motor!$F$61:$CP$301,$A16+1,($D$5-1)*15+5)+INDEX(Motor!$F$61:$CP$301,$A16+1,($D$5-1)*15+6),0) -> 26.431315 | G16: =IFERROR(INDEX(Motor!$F$61:$CP$301,$A16+1,($D$5-1)*15+7),0) -> 0 | H16: =IFERROR(INDEX(Motor!$F$61:$CP$301,$A16+1,($D$5-1)*15+8),0) -> 160066.27 | I16: =IFERROR(INDEX(Motor!$F$61:$CP$301,$A16+1,($D$5-1)*15+12),0) -> 2013.2534 | J16: =IFERROR(INDEX(Motor!$F$61:$CP$301,$A16+1,($D$5-1)*15+13),0) -> 158053.01 | K16: =IFERROR(INDEX(Motor!$F$61:$CP$301,$A16+1,($D$5-1)*15+14),0) -> 154478.01
A17: 8 | B17: =EDATE(DATA_INICIO,$A17) -> 46500 | C17: =IFERROR(INDEX(Motor!$F$61:$CP$301,$A17+1,($D$5-1)*15+1),0) -> 160066.27 | D17: =IFERROR(INDEX(Motor!$F$61:$CP$301,$A17+1,($D$5-1)*15+4),0) -> 1518.8357 | E17: =IFERROR(INDEX(Motor!$F$61:$CP$301,$A17+1,($D$5-1)*15+2),0) -> 0 | F17: =IFERROR(INDEX(Motor!$F$61:$CP$301,$A17+1,($D$5-1)*15+3)+INDEX(Motor!$F$61:$CP$301,$A17+1,($D$5-1)*15+5)+INDEX(Motor!$F$61:$CP$301,$A17+1,($D$5-1)*15+6),0) -> 26.677711 | G17: =IFERROR(INDEX(Motor!$F$61:$CP$301,$A17+1,($D$5-1)*15+7),0) -> 0 | H17: =IFERROR(INDEX(Motor!$F$61:$CP$301,$A17+1,($D$5-1)*15+8),0) -> 161558.42 | I17: =IFERROR(INDEX(Motor!$F$61:$CP$301,$A17+1,($D$5-1)*15+12),0) -> 2311.685 | J17: =IFERROR(INDEX(Motor!$F$61:$CP$301,$A17+1,($D$5-1)*15+13),0) -> 159246.74 | K17: =IFERROR(INDEX(Motor!$F$61:$CP$301,$A17+1,($D$5-1)*15+14),0) -> 155136.86
A18: 9 | B18: =EDATE(DATA_INICIO,$A18) -> 46530 | C18: =IFERROR(INDEX(Motor!$F$61:$CP$301,$A18+1,($D$5-1)*15+1),0) -> 161558.42 | D18: =IFERROR(INDEX(Motor!$F$61:$CP$301,$A18+1,($D$5-1)*15+4),0) -> 1532.9944 | E18: =IFERROR(INDEX(Motor!$F$61:$CP$301,$A18+1,($D$5-1)*15+2),0) -> 0 | F18: =IFERROR(INDEX(Motor!$F$61:$CP$301,$A18+1,($D$5-1)*15+3)+INDEX(Motor!$F$61:$CP$301,$A18+1,($D$5-1)*15+5)+INDEX(Motor!$F$61:$CP$301,$A18+1,($D$5-1)*15+6),0) -> 26.926404 | G18: =IFERROR(INDEX(Motor!$F$61:$CP$301,$A18+1,($D$5-1)*15+7),0) -> 0 | H18: =IFERROR(INDEX(Motor!$F$61:$CP$301,$A18+1,($D$5-1)*15+8),0) -> 163064.49 | I18: =IFERROR(INDEX(Motor!$F$61:$CP$301,$A18+1,($D$5-1)*15+12),0) -> 2612.8986 | J18: =IFERROR(INDEX(Motor!$F$61:$CP$301,$A18+1,($D$5-1)*15+13),0) -> 160451.59 | K18: =IFERROR(INDEX(Motor!$F$61:$CP$301,$A18+1,($D$5-1)*15+14),0) -> 155800.57
A19: 10 | B19: =EDATE(DATA_INICIO,$A19) -> 46561 | C19: =IFERROR(INDEX(Motor!$F$61:$CP$301,$A19+1,($D$5-1)*15+1),0) -> 163064.49 | D19: =IFERROR(INDEX(Motor!$F$61:$CP$301,$A19+1,($D$5-1)*15+4),0) -> 1547.2852 | E19: =IFERROR(INDEX(Motor!$F$61:$CP$301,$A19+1,($D$5-1)*15+2),0) -> 0 | F19: =IFERROR(INDEX(Motor!$F$61:$CP$301,$A19+1,($D$5-1)*15+3)+INDEX(Motor!$F$61:$CP$301,$A19+1,($D$5-1)*15+5)+INDEX(Motor!$F$61:$CP$301,$A19+1,($D$5-1)*15+6),0) -> 27.177415 | G19: =IFERROR(INDEX(Motor!$F$61:$CP$301,$A19+1,($D$5-1)*15+7),0) -> 0 | H19: =IFERROR(INDEX(Motor!$F$61:$CP$301,$A19+1,($D$5-1)*15+8),0) -> 164584.6 | I19: =IFERROR(INDEX(Motor!$F$61:$CP$301,$A19+1,($D$5-1)*15+12),0) -> 2916.9201 | J19: =IFERROR(INDEX(Motor!$F$61:$CP$301,$A19+1,($D$5-1)*15+13),0) -> 161667.68 | K19: =IFERROR(INDEX(Motor!$F$61:$CP$301,$A19+1,($D$5-1)*15+14),0) -> 156469.16
A20: 11 | B20: =EDATE(DATA_INICIO,$A20) -> 46591 | C20: =IFERROR(INDEX(Motor!$F$61:$CP$301,$A20+1,($D$5-1)*15+1),0) -> 164584.6 | D20: =IFERROR(INDEX(Motor!$F$61:$CP$301,$A20+1,($D$5-1)*15+4),0) -> 1561.7092 | E20: =IFERROR(INDEX(Motor!$F$61:$CP$301,$A20+1,($D$5-1)*15+2),0) -> 0 | F20: =IFERROR(INDEX(Motor!$F$61:$CP$301,$A20+1,($D$5-1)*15+3)+INDEX(Motor!$F$61:$CP$301,$A20+1,($D$5-1)*15+5)+INDEX(Motor!$F$61:$CP$301,$A20+1,($D$5-1)*15+6),0) -> 27.430767 | G20: =IFERROR(INDEX(Motor!$F$61:$CP$301,$A20+1,($D$5-1)*15+7),0) -> 0 | H20: =IFERROR(INDEX(Motor!$F$61:$CP$301,$A20+1,($D$5-1)*15+8),0) -> 166118.88 | I20: =IFERROR(INDEX(Motor!$F$61:$CP$301,$A20+1,($D$5-1)*15+12),0) -> 3223.7758 | J20: =IFERROR(INDEX(Motor!$F$61:$CP$301,$A20+1,($D$5-1)*15+13),0) -> 162895.1 | K20: =IFERROR(INDEX(Motor!$F$61:$CP$301,$A20+1,($D$5-1)*15+14),0) -> 157142.67
A21: 12 | B21: =EDATE(DATA_INICIO,$A21) -> 46622 | C21: =IFERROR(INDEX(Motor!$F$61:$CP$301,$A21+1,($D$5-1)*15+1),0) -> 166118.88 | D21: =IFERROR(INDEX(Motor!$F$61:$CP$301,$A21+1,($D$5-1)*15+4),0) -> 1576.2676 | E21: =IFERROR(INDEX(Motor!$F$61:$CP$301,$A21+1,($D$5-1)*15+2),0) -> 0 | F21: =IFERROR(INDEX(Motor!$F$61:$CP$301,$A21+1,($D$5-1)*15+3)+INDEX(Motor!$F$61:$CP$301,$A21+1,($D$5-1)*15+5)+INDEX(Motor!$F$61:$CP$301,$A21+1,($D$5-1)*15+6),0) -> 27.68648 | G21: =IFERROR(INDEX(Motor!$F$61:$CP$301,$A21+1,($D$5-1)*15+7),0) -> 0 | H21: =IFERROR(INDEX(Motor!$F$61:$CP$301,$A21+1,($D$5-1)*15+8),0) -> 167667.46 | I21: =IFERROR(INDEX(Motor!$F$61:$CP$301,$A21+1,($D$5-1)*15+12),0) -> 3533.4921 | J21: =IFERROR(INDEX(Motor!$F$61:$CP$301,$A21+1,($D$5-1)*15+13),0) -> 164133.97 | K21: =IFERROR(INDEX(Motor!$F$61:$CP$301,$A21+1,($D$5-1)*15+14),0) -> 157821.12
A22: 13 | B22: =EDATE(DATA_INICIO,$A22) -> 46653 | C22: =IFERROR(INDEX(Motor!$F$61:$CP$301,$A22+1,($D$5-1)*15+1),0) -> 167667.46 | D22: =IFERROR(INDEX(Motor!$F$61:$CP$301,$A22+1,($D$5-1)*15+4),0) -> 1590.9618 | E22: =IFERROR(INDEX(Motor!$F$61:$CP$301,$A22+1,($D$5-1)*15+2),0) -> 0 | F22: =IFERROR(INDEX(Motor!$F$61:$CP$301,$A22+1,($D$5-1)*15+3)+INDEX(Motor!$F$61:$CP$301,$A22+1,($D$5-1)*15+5)+INDEX(Motor!$F$61:$CP$301,$A22+1,($D$5-1)*15+6),0) -> 27.944577 | G22: =IFERROR(INDEX(Motor!$F$61:$CP$301,$A22+1,($D$5-1)*15+7),0) -> 0 | H22: =IFERROR(INDEX(Motor!$F$61:$CP$301,$A22+1,($D$5-1)*15+8),0) -> 169230.48 | I22: =IFERROR(INDEX(Motor!$F$61:$CP$301,$A22+1,($D$5-1)*15+12),0) -> 3365.3336 | J22: =IFERROR(INDEX(Motor!$F$61:$CP$301,$A22+1,($D$5-1)*15+13),0) -> 165865.14 | K22: =IFERROR(INDEX(Motor!$F$61:$CP$301,$A22+1,($D$5-1)*15+14),0) -> 158965.3
A23: 14 | B23: =EDATE(DATA_INICIO,$A23) -> 46683 | C23: =IFERROR(INDEX(Motor!$F$61:$CP$301,$A23+1,($D$5-1)*15+1),0) -> 169230.48 | D23: =IFERROR(INDEX(Motor!$F$61:$CP$301,$A23+1,($D$5-1)*15+4),0) -> 1605.793 | E23: =IFERROR(INDEX(Motor!$F$61:$CP$301,$A23+1,($D$5-1)*15+2),0) -> 0 | F23: =IFERROR(INDEX(Motor!$F$61:$CP$301,$A23+1,($D$5-1)*15+3)+INDEX(Motor!$F$61:$CP$301,$A23+1,($D$5-1)*15+5)+INDEX(Motor!$F$61:$CP$301,$A23+1,($D$5-1)*15+6),0) -> 28.20508 | G23: =IFERROR(INDEX(Motor!$F$61:$CP$301,$A23+1,($D$5-1)*15+7),0) -> 0 | H23: =IFERROR(INDEX(Motor!$F$61:$CP$301,$A23+1,($D$5-1)*15+8),0) -> 170808.07 | I23: =IFERROR(INDEX(Motor!$F$61:$CP$301,$A23+1,($D$5-1)*15+12),0) -> 3641.4115 | J23: =IFERROR(INDEX(Motor!$F$61:$CP$301,$A23+1,($D$5-1)*15+13),0) -> 167166.65 | K23: =IFERROR(INDEX(Motor!$F$61:$CP$301,$A23+1,($D$5-1)*15+14),0) -> 159689.89
... A249: 240 | B249: =EDATE(DATA_INICIO,$A249) -> 53562 | C249: =IFERROR(INDEX(Motor!$F$61:$CP$301,$A249+1,($D$5-1)*15+1),0) -> 1377881.9 | D249: =IFERROR(INDEX(Motor!$F$61:$CP$301,$A249+1,($D$5-1)*15+4),0) -> 13074.436 | E249: =IFERROR(INDEX(Motor!$F$61:$CP$301,$A249+1,($D$5-1)*15+2),0) -> 0 | F249: =IFERROR(INDEX(Motor!$F$61:$CP$301,$A249+1,($D$5-1)*15+3)+INDEX(Motor!$F$61:$CP$301,$A249+1,($D$5-1)*15+5)+INDEX(Motor!$F$61:$CP$301,$A249+1,($D$5-1)*15+6),0) -> 229.64699 | G249: =IFERROR(INDEX(Motor!$F$61:$CP$301,$A249+1,($D$5-1)*15+7),0) -> 0 | H249: =IFERROR(INDEX(Motor!$F$61:$CP$301,$A249+1,($D$5-1)*15+8),0) -> 1390726.7 | I249: =IFERROR(INDEX(Motor!$F$61:$CP$301,$A249+1,($D$5-1)*15+12),0) -> 186109.01 | J249: =IFERROR(INDEX(Motor!$F$61:$CP$301,$A249+1,($D$5-1)*15+13),0) -> 1204617.7 | K249: =IFERROR(INDEX(Motor!$F$61:$CP$301,$A249+1,($D$5-1)*15+14),0) -> 549771.8

Sheet Imovel
A1: COMPRAR UM IMÓVEL PARA ALUGAR
A2: A estratégia do Seu João: comparar aplicação financeira com casa para alugar
A4: 1 · A COMPRA
B5: Incluir o imóvel na comparação? | F5: Sim
B6: Valor do imóvel | F6: 150000
B7: ITBI (% do valor) | F7: 0.02
B8: Escritura e registro (% do valor) | F8: 0.015
B9: ➜ Desembolso total para fechar a compra | F9: =IMOV_VALOR*(1+IMOV_ITBI+IMOV_CARTORIO) -> 155250
B10: =IF(MotorImovel!$B$12<0,"⚠ O cliente tem "&TEXT(IN_CAPITAL,"R$ #,##0")&" e a compra exige "&TEXT(IMOV_DESEMBOLSO,"R$ #,##0")&". Faltam "&TEXT(-MotorImovel!$B$12,"R$ #,##0")&" — quase ninguém lembra dos custos de aquisição, e eles mudam a conta.","✓ O capital disponível cobre o imóvel e os custos de aquisição. A sobra de "&TEXT(MotorImovel!$B$12,"R$ #,##0")&" entra na simulação como caixa aplicado.") -> ⚠ O cliente tem R$ 150,000 e a compra exige R$ 155,250. Faltam R$ 5,250 — quase ninguém lembra dos custos de aquisição, e eles mudam a conta.
A11: 2 · O ALUGUEL
B12: Como definir o aluguel? | F12: Informar o valor do aluguel
B13: Aluguel mensal, se você informar o valor | F13: 900
B14: ➜ Aluguel usado na simulação | F14: =MotorImovel!$B$13 -> 900
B15: Vacância — quanto do ano o imóvel fica sem inquilino | F15: 0.08 | H15: 8% equivale a cerca de um mês por ano vazio. Ignorar a vacância é o erro mais comum.
B16: Reajuste anual do aluguel | F16: =IPCA_CENARIO -> 0.04 | H16: ="Padrão: o IPCA do cenário ("&TEXT(IPCA_CENARIO,"0.0%")&" a.a.)." -> Padrão: o IPCA do cenário (4.0% a.a.).
A18: 3 · O CUSTO DE MANTER
B19: IPTU (% do valor do imóvel por ano) | F19: 0.006 | H19: IPTU e taxa de administração são dedutíveis no carnê-leão; manutenção não é. A planilha já trata os três de forma diferente.
B20: Manutenção e seguro (% do valor por ano) | F20: 0.01
B21: Administração imobiliária (% do aluguel) | F21: 0.08
A23: 4 · A VENDA NO FIM DO PRAZO
B24: Valorização anual do imóvel | F24: =IFERROR(INDEX(TAB_MACRO_VAL,MATCH("IMOB_VAL",TAB_MACRO_COD,0)),0.04) -> 0.04 | H24: Há regras específicas de isenção — imóvel único de menor valor vendido a cada cinco anos, e compra de outro imóvel residencial em até 180 dias. Confirme o enquadramento antes de marcar Sim: essa escolha muda bastante o resultado final.
B25: Corretagem na venda (%) | F25: 0.06
B26: Tem isenção de imposto sobre o ganho na venda? | F26: Não
A28: 5 · O QUE O CLIENTE FAZ COM O ALUGUEL
B29: O aluguel vai ser reinvestido ou gasto? | F29: Reinvestir | H29: =IF(IMOV_DESTINO="Reinvestir","O aluguel líquido é aplicado todo mês e volta a render. O patrimônio final fica maior, mas o cliente não usa esse dinheiro no dia a dia.","O aluguel é gasto: hoje isso vira cerca de "&TEXT(MotorImovel!$B$45,"R$ #,##0")&" por mês no bolso, e o patrimônio cresce só pela valorização do imóvel.") -> O aluguel líquido é aplicado todo mês e volta a render. O patrimônio final fica maior, mas o cliente não usa esse dinheiro no dia a dia.
B30: Se reinvestir, a que taxa ao ano? | F30: =CDI_CENARIO*0.98 -> 0.10682
A32: RESULTADO DA ESTRATÉGIA IMOBILIÁRIA
B33: Patrimônio líquido no fim do prazo (vendendo o imóvel) | F33: =MotorImovel!$B$34 -> 329895.57 | H33: ="Comparando com a melhor alternativa financeira em uso: "&TEXT(MAX(Motor!$B$40:$G$40),"R$ #,##0")&". "&IF(MotorImovel!$B$34>MAX(Motor!$B$40:$G$40),"Nestas premissas o imóvel termina à frente — mas lembre que ele não tem liquidez, depende de inquilino e concentra todo o patrimônio em um único bem.","Nestas premissas a aplicação financeira termina à frente. Ainda assim, o imóvel pode fazer sentido por outros motivos: uso próprio, herança, segurança percebida.") -> Comparando com a melhor alternativa financeira em uso: R$ 410,727. Nestas premissas a aplicação financeira termina à frente. Ainda assim, o imóvel pode fazer sentido por outros motivos: uso próprio, herança, segurança percebida.
B34: Em poder de compra de hoje | F34: =MotorImovel!$B$36 -> 222865.63
B35: Total investido pelo cliente | F35: =MotorImovel!$B$37 -> 155250
B36: Ganho líquido | F36: =MotorImovel!$B$38 -> 174645.57
B37: Impostos pagos (aluguel + caixa + ganho de capital) | F37: =MotorImovel!$B$39 -> 16294.186
B38: Custos pagos (aquisição, IPTU, manutenção, administração, vacância, corretagem) | F38: =MotorImovel!$B$40 -> 68286.677
B39: Rentabilidade líquida acumulada | F39: =MotorImovel!$B$41 -> 1.1249312
B40: Taxa líquida equivalente a.a. | F40: =MotorImovel!$B$42 -> 0.078287294
B41: Ganho real a.a. (acima da inflação) | F41: =MotorImovel!$B$43 -> 0.036814706
B42: Aluguel líquido no último mês do prazo | F42: =MotorImovel!$B$45 -> 827.86264
A44: ⚠ O imóvel é o único item da comparação que não é dinheiro. Ele não se divide, não se resgata em parte e depende de achar comprador. Isso não aparece em nenhum número — mas precisa aparecer na conversa.
B46: ◀ INÍCIO | D46: ◀ CLIENTE | F46: COMPARAR | H46: VER MÊS A MÊS DO IMÓVEL | J46: PREMISSAS

Sheet Previdencia
A1: PREVIDÊNCIA PRIVADA
A2: PGBL ou VGBL, progressivo ou regressivo — e quanto vale, em reais, o benefício fiscal
A4: 1 · ESTE CLIENTE PODE APROVEITAR O PGBL?
B5: Declara o Imposto de Renda no modelo completo? | E5: =PGBL_COMPLETA -> Não | F5: =IF(PGBL_COMPLETA<>"Sim","VEREDITO: o PGBL não faz sentido aqui. Ele só entrega vantagem para quem declara no modelo completo e tem imposto a deduzir. Para quem declara simplificado ou é isento, o VGBL é o caminho, porque cobra imposto apenas sobre o rendimento.",IF(PGBL_RENDA<=0,"VEREDITO: informe a renda bruta anual tributável na aba Consultor para calcular o benefício.","VEREDITO: o PGBL faz sentido. O cliente pode deduzir "&TEXT(MIN(IN_APORTE*12,PGBL_RENDA*LIMITE_PGBL),"R$ #,##0")&" por ano, o que devolve cerca de "&TEXT(PGBL_BENEFICIO,"R$ #,##0")&" na declaração. Atenção: na saída o imposto incide sobre o VALOR TOTAL resgatado, não só sobre o rendimento — o benefício é um adiantamento, não um perdão.")) -> VEREDITO: o PGBL não faz sentido aqui. Ele só entrega vantagem para quem declara no modelo completo e tem imposto a deduzir. Para quem declara simplificado ou é isento, o VGBL é o caminho, porque cobra imposto apenas sobre o rendimento.
B6: Tem renda bruta anual tributável informada? | E6: =IF(PGBL_RENDA>0,"Sim","Não informada") -> Não informada
B7: Limite de dedução (12% da renda bruta anual) | E7: =PGBL_RENDA*LIMITE_PGBL -> 0
B8: Aporte anual previsto em previdência | E8: =IN_APORTE*12 -> 0
B9: Parcela do aporte que pode ser deduzida | E9: =MIN(IN_APORTE*12,PGBL_RENDA*LIMITE_PGBL) -> 0
A11: 2 · QUANTO VALE O BENEFÍCIO FISCAL AO LONGO DO TEMPO
B12: Benefício fiscal por ano | E12: =PGBL_BENEFICIO -> 0 | F12: A maior parte das simulações de previdência ignora o benefício fiscal ou finge que ele some. Aqui ele tem dois caminhos, escolhidos na aba Consultor: consumido (aparece como dinheiro no bolso) ou reinvestido (volta como aporte extra em maio de cada ano e passa a compor). A diferença entre os dois caminhos costuma ser a parte mais convincente da conversa.
B13: Benefício ao longo de todo o prazo | E13: =PGBL_BENEFICIO*IN_PRAZO/12 -> 0
B14: Se reinvestido a cada ano, vira aproximadamente | E14: =IF(PGBL_REINVESTE<>"Sim",0,IF(CDI_CENARIO=0,PGBL_BENEFICIO*IN_PRAZO/12,PGBL_BENEFICIO*((1+CDI_CENARIO)^(IN_PRAZO/12)-1)/CDI_CENARIO)) -> 0
B15: O benefício está sendo reinvestido na simulação? | E15: =PGBL_REINVESTE -> Sim
A17: 3 · REGIME PROGRESSIVO OU REGRESSIVO?
B18: Tempo de aplicação | C18: Regressivo | D18: Progressivo (retido na fonte) | E18: Qual tende a ser melhor | F18: Observação
B19: Até 2 anos | C19: =INDEX(TAB_IR,MATCH(0,TAB_IR_DIAS,1),MATCH("PREV_REGR",TAB_IR_REGIMES,0)) -> 0.35 | D19: =INDEX(TAB_IR,MATCH(0,TAB_IR_DIAS,1),MATCH("PREV_PROG",TAB_IR_REGIMES,0)) -> 0.15 | E19: =IF($C19<$D19,"Regressivo",IF($C19=$D19,"Empate","Progressivo")) -> Progressivo | F19: Resgate cedo no regressivo é caro: 35%.
B20: De 2 a 4 anos | C20: =INDEX(TAB_IR,MATCH(721,TAB_IR_DIAS,1),MATCH("PREV_REGR",TAB_IR_REGIMES,0)) -> 0.3 | D20: =INDEX(TAB_IR,MATCH(721,TAB_IR_DIAS,1),MATCH("PREV_PROG",TAB_IR_REGIMES,0)) -> 0.15 | E20: =IF($C20<$D20,"Regressivo",IF($C20=$D20,"Empate","Progressivo")) -> Progressivo | F20: O progressivo faz o acerto na declaração: pode sobrar ou faltar imposto.
B21: De 4 a 6 anos | C21: =INDEX(TAB_IR,MATCH(1441,TAB_IR_DIAS,1),MATCH("PREV_REGR",TAB_IR_REGIMES,0)) -> 0.25 | D21: =INDEX(TAB_IR,MATCH(1441,TAB_IR_DIAS,1),MATCH("PREV_PROG",TAB_IR_REGIMES,0)) -> 0.15 | E21: =IF($C21<$D21,"Regressivo",IF($C21=$D21,"Empate","Progressivo")) -> Progressivo | F21: A partir daqui o regressivo vai ficando mais barato.
B22: De 6 a 8 anos | C22: =INDEX(TAB_IR,MATCH(2161,TAB_IR_DIAS,1),MATCH("PREV_REGR",TAB_IR_REGIMES,0)) -> 0.2 | D22: =INDEX(TAB_IR,MATCH(2161,TAB_IR_DIAS,1),MATCH("PREV_PROG",TAB_IR_REGIMES,0)) -> 0.15 | E22: =IF($C22<$D22,"Regressivo",IF($C22=$D22,"Empate","Progressivo")) -> Progressivo | F22: A partir daqui o regressivo vai ficando mais barato.
B23: De 8 a 10 anos | C23: =INDEX(TAB_IR,MATCH(2881,TAB_IR_DIAS,1),MATCH("PREV_REGR",TAB_IR_REGIMES,0)) -> 0.15 | D23: =INDEX(TAB_IR,MATCH(2881,TAB_IR_DIAS,1),MATCH("PREV_PROG",TAB_IR_REGIMES,0)) -> 0.15 | E23: =IF($C23<$D23,"Regressivo",IF($C23=$D23,"Empate","Progressivo")) -> Empate | F23: A partir daqui o regressivo vai ficando mais barato.
B24: Acima de 10 anos | C24: =INDEX(TAB_IR,MATCH(3601,TAB_IR_DIAS,1),MATCH("PREV_REGR",TAB_IR_REGIMES,0)) -> 0.1 | D24: =INDEX(TAB_IR,MATCH(3601,TAB_IR_DIAS,1),MATCH("PREV_PROG",TAB_IR_REGIMES,0)) -> 0.15 | E24: =IF($C24<$D24,"Regressivo",IF($C24=$D24,"Empate","Progressivo")) -> Regressivo | F24: Alíquota mínima de 10%: é aqui que a previdência de longo prazo brilha.
B26: ="No prazo escolhido ("&IN_PRAZO&" meses), o regime regressivo cobraria "&TEXT(INDEX(TAB_IR,MATCH(IN_PRAZO*30,TAB_IR_DIAS,1),MATCH("PREV_REGR",TAB_IR_REGIMES,0)),"0.0%")&" e o progressivo, "&TEXT(INDEX(TAB_IR,MATCH(IN_PRAZO*30,TAB_IR_DIAS,1),MATCH("PREV_PROG",TAB_IR_REGIMES,0)),"0.0%")&" na fonte. O progressivo só ganha quando a renda futura do cliente for baixa ou isenta — porque aí o acerto na declaração devolve imposto." -> No prazo escolhido (120 meses), o regime regressivo cobraria 15.0% e o progressivo, 15.0% na fonte. O progressivo só ganha quando a renda futura do cliente for baixa ou isenta — porque aí o acerto na declaração devolve imposto.
A28: 4 · OS PLANOS QUE ESTÃO NA COMPARAÇÃO
A29: Para comparar PGBL e VGBL lado a lado, coloque um em cada lugar na aba Consultor (com a sugestão automática desligada). As colunas abaixo mostram só os lugares ocupados por previdência.
B30: Plano | C30: Tipo | D30: Regime | E30: Taxa adm. | F30: Carregamento | G30: Patrimônio líquido | H30: IR no resgate | I30: Renda mensal
B31: =IF(ISNUMBER(SEARCH("PREV",Motor!$B$8)),Motor!$B$6,"—") -> — | C31: =IF(ISNUMBER(SEARCH("PREV",Motor!$B$8)),IF(Motor!$B$26=2,"PGBL (IR sobre o total)","VGBL (IR só sobre o rendimento)"),"") | D31: =IF(ISNUMBER(SEARCH("PREV",Motor!$B$8)),Motor!$B$8,"") | E31: =IF(ISNUMBER(SEARCH("PREV",Motor!$B$8)),Motor!$B$20,"") | F31: =IF(ISNUMBER(SEARCH("PREV",Motor!$B$8)),Motor!$B$24,"") | G31: =IF(ISNUMBER(SEARCH("PREV",Motor!$B$8)),Motor!$B$40,"") | H31: =IF(ISNUMBER(SEARCH("PREV",Motor!$B$8)),Motor!$B$45,"") | I31: =IF(ISNUMBER(SEARCH("PREV",Motor!$B$8)),Motor!$B$51,"")
B32: =IF(ISNUMBER(SEARCH("PREV",Motor!$C$8)),Motor!$C$6,"—") -> — | C32: =IF(ISNUMBER(SEARCH("PREV",Motor!$C$8)),IF(Motor!$C$26=2,"PGBL (IR sobre o total)","VGBL (IR só sobre o rendimento)"),"") | D32: =IF(ISNUMBER(SEARCH("PREV",Motor!$C$8)),Motor!$C$8,"") | E32: =IF(ISNUMBER(SEARCH("PREV",Motor!$C$8)),Motor!$C$20,"") | F32: =IF(ISNUMBER(SEARCH("PREV",Motor!$C$8)),Motor!$C$24,"") | G32: =IF(ISNUMBER(SEARCH("PREV",Motor!$C$8)),Motor!$C$40,"") | H32: =IF(ISNUMBER(SEARCH("PREV",Motor!$C$8)),Motor!$C$45,"") | I32: =IF(ISNUMBER(SEARCH("PREV",Motor!$C$8)),Motor!$C$51,"")
B33: =IF(ISNUMBER(SEARCH("PREV",Motor!$D$8)),Motor!$D$6,"—") -> — | C33: =IF(ISNUMBER(SEARCH("PREV",Motor!$D$8)),IF(Motor!$D$26=2,"PGBL (IR sobre o total)","VGBL (IR só sobre o rendimento)"),"") | D33: =IF(ISNUMBER(SEARCH("PREV",Motor!$D$8)),Motor!$D$8,"") | E33: =IF(ISNUMBER(SEARCH("PREV",Motor!$D$8)),Motor!$D$20,"") | F33: =IF(ISNUMBER(SEARCH("PREV",Motor!$D$8)),Motor!$D$24,"") | G33: =IF(ISNUMBER(SEARCH("PREV",Motor!$D$8)),Motor!$D$40,"") | H33: =IF(ISNUMBER(SEARCH("PREV",Motor!$D$8)),Motor!$D$45,"") | I33: =IF(ISNUMBER(SEARCH("PREV",Motor!$D$8)),Motor!$D$51,"")
B34: =IF(ISNUMBER(SEARCH("PREV",Motor!$E$8)),Motor!$E$6,"—") -> VGBL CAIXA Composto 30 — Regressivo | C34: =IF(ISNUMBER(SEARCH("PREV",Motor!$E$8)),IF(Motor!$E$26=2,"PGBL (IR sobre o total)","VGBL (IR só sobre o rendimento)"),"") -> VGBL (IR só sobre o rendimento) | D34: =IF(ISNUMBER(SEARCH("PREV",Motor!$E$8)),Motor!$E$8,"") -> PREV_REGR | E34: =IF(ISNUMBER(SEARCH("PREV",Motor!$E$8)),Motor!$E$20,"") -> 0.015 | F34: =IF(ISNUMBER(SEARCH("PREV",Motor!$E$8)),Motor!$E$24,"") -> 0 | G34: =IF(ISNUMBER(SEARCH("PREV",Motor!$E$8)),Motor!$E$40,"") -> 376188.27 | H34: =IF(ISNUMBER(SEARCH("PREV",Motor!$E$8)),Motor!$E$45,"") -> 39915.578 | I34: =IF(ISNUMBER(SEARCH("PREV",Motor!$E$8)),Motor!$E$51,"") -> 2730.3495
B35: =IF(ISNUMBER(SEARCH("PREV",Motor!$F$8)),Motor!$F$6,"—") -> PGBL CAIXA Composto 30 — Regressivo | C35: =IF(ISNUMBER(SEARCH("PREV",Motor!$F$8)),IF(Motor!$F$26=2,"PGBL (IR sobre o total)","VGBL (IR só sobre o rendimento)"),"") -> PGBL (IR sobre o total) | D35: =IF(ISNUMBER(SEARCH("PREV",Motor!$F$8)),Motor!$F$8,"") -> PREV_REGR | E35: =IF(ISNUMBER(SEARCH("PREV",Motor!$F$8)),Motor!$F$20,"") -> 0.015 | F35: =IF(ISNUMBER(SEARCH("PREV",Motor!$F$8)),Motor!$F$24,"") -> 0 | G35: =IF(ISNUMBER(SEARCH("PREV",Motor!$F$8)),Motor!$F$40,"") -> 353688.27 | H35: =IF(ISNUMBER(SEARCH("PREV",Motor!$F$8)),Motor!$F$45,"") -> 62415.578 | I35: =IF(ISNUMBER(SEARCH("PREV",Motor!$F$8)),Motor!$F$51,"") -> 2567.046
B36: =IF(ISNUMBER(SEARCH("PREV",Motor!$G$8)),Motor!$G$6,"—") -> — | C36: =IF(ISNUMBER(SEARCH("PREV",Motor!$G$8)),IF(Motor!$G$26=2,"PGBL (IR sobre o total)","VGBL (IR só sobre o rendimento)"),"") | D36: =IF(ISNUMBER(SEARCH("PREV",Motor!$G$8)),Motor!$G$8,"") | E36: =IF(ISNUMBER(SEARCH("PREV",Motor!$G$8)),Motor!$G$20,"") | F36: =IF(ISNUMBER(SEARCH("PREV",Motor!$G$8)),Motor!$G$24,"") | G36: =IF(ISNUMBER(SEARCH("PREV",Motor!$G$8)),Motor!$G$40,"") | H36: =IF(ISNUMBER(SEARCH("PREV",Motor!$G$8)),Motor!$G$45,"") | I36: =IF(ISNUMBER(SEARCH("PREV",Motor!$G$8)),Motor!$G$51,"")
A38: 5 · A RENDA QUE ESSE PATRIMÔNIO PODE GERAR
A39: Renda mensal estimada mantendo o patrimônio de pé — ou seja, vivendo do rendimento, sem consumir o principal. A segunda linha desconta a inflação: é o que o cliente realmente conseguirá comprar.
B40: Renda mensal em reais do futuro | D40: =IF(Motor!$B$9=0,"",Motor!$B$51) -> 3254.5196 | E40: =IF(Motor!$C$9=0,"",Motor!$C$51) -> 2403.3348 | F40: =IF(Motor!$D$9=0,"",Motor!$D$51) -> 2387.9368 | G40: =IF(Motor!$E$9=0,"",Motor!$E$51) -> 2730.3495 | H40: =IF(Motor!$F$9=0,"",Motor!$F$51) -> 2567.046 | I40: =IF(Motor!$G$9=0,"",Motor!$G$51) -> 1970.2821
B41: Renda mensal em poder de compra de hoje | D41: =IF(Motor!$B$9=0,"",Motor!$B$52) -> 1903.675 | E41: =IF(Motor!$C$9=0,"",Motor!$C$52) -> 1240.8624 | F41: =IF(Motor!$D$9=0,"",Motor!$D$52) -> 1256.0957 | G41: =IF(Motor!$E$9=0,"",Motor!$E$52) -> 1493.9163 | H41: =IF(Motor!$F$9=0,"",Motor!$F$52) -> 1404.5644 | I41: =IF(Motor!$G$9=0,"",Motor!$G$52) -> 931.10997
A43: ⚠ Previdência não tem cobertura do FGC: quem responde é a seguradora. Em compensação, o saldo não entra em inventário e vai direto para os beneficiários indicados — para muita gente esse é o motivo principal, e não a rentabilidade.
B45: ◀ INÍCIO | D45: ◀ CONSULTOR | F45: COMPARAR | H45: GLOSSÁRIO

Sheet Relatorio
A1: RESUMO DA SUA SIMULAÇÃO
A3: =" Cliente: "&IN_NOME&" Simulação feita em: "&TEXT(IN_DATA_SIM,"dd/mm/yyyy")&" Dados de: "&DATA_DADOS -> Cliente: (preencher) Simulação feita em: 23/08/2026 Dados de: 2026-08-23
A5: O QUE FOI CONSIDERADO
B6: Valor investido hoje | C6: =IN_CAPITAL -> 150000 | E6: Aporte mensal | G6: =IN_APORTE -> 0
B7: Prazo | C7: =IN_PRAZO&" meses ("&ROUND(IN_PRAZO/12,1)&" anos)" -> 120 meses (10 anos) | E7: Pode precisar retirar antes | G7: =IN_RESGATE -> Talvez
B8: O que é mais importante | C8: =IN_PRIORIDADE -> Equilíbrio entre segurança e rentabilidade | E8: Perfil de investidor | G8: =IN_PERFIL -> Moderado
B9: Cenário de premissas | C9: =CENARIO -> Base | E9: Inflação considerada (a.a.) | G9: =IPCA_CENARIO -> 0.04
A11: AS ALTERNATIVAS ANALISADAS
B12: Alternativa | C12: Você teria cerca de | D12: Em R$ de hoje | E12: Ganho estimado | F12: Renda mensal | G12: Para retirar | H12: Oscilação
B13: =IF(Motor!$B$9=0,"",Motor!$B$6) -> Tesouro Prefixado 2031 | C13: =IF(Motor!$B$9=0,"",Motor!$B$40) -> 410726.75 | D13: =IF(Motor!$B$9=0,"",Motor!$B$42) -> 277472.27 | E13: =IF(Motor!$B$9=0,"",Motor!$B$44) -> 260726.75 | F13: =IF(Motor!$B$9=0,"",Motor!$B$51) -> 3254.5196 | G13: =IF(Motor!$B$9=0,"",Motor!$B$56) -> Em 1 dia útil | H13: =IF(Motor!$B$9=0,"",Motor!$B$57) -> Baixa
B14: =IF(Motor!$C$9=0,"",Motor!$C$6) -> Tesouro IPCA+ 2035 | C14: =IF(Motor!$C$9=0,"",Motor!$C$40) -> 353849.19 | D14: =IF(Motor!$C$9=0,"",Motor!$C$42) -> 239047.83 | E14: =IF(Motor!$C$9=0,"",Motor!$C$44) -> 203849.19 | F14: =IF(Motor!$C$9=0,"",Motor!$C$51) -> 2403.3348 | G14: =IF(Motor!$C$9=0,"",Motor!$C$56) -> Em 1 dia útil | H14: =IF(Motor!$C$9=0,"",Motor!$C$57) -> Baixa
B15: =IF(Motor!$D$9=0,"",Motor!$D$6) -> Fundo CAIXA RF Crédito Privado LP | C15: =IF(Motor!$D$9=0,"",Motor!$D$40) -> 344477.27 | D15: =IF(Motor!$D$9=0,"",Motor!$D$42) -> 232716.5 | E15: =IF(Motor!$D$9=0,"",Motor!$D$44) -> 194477.27 | F15: =IF(Motor!$D$9=0,"",Motor!$D$51) -> 2387.9368 | G15: =IF(Motor!$D$9=0,"",Motor!$D$56) -> Em até 30 dias | H15: =IF(Motor!$D$9=0,"",Motor!$D$57) -> Baixa
B16: =IF(Motor!$E$9=0,"",Motor!$E$6) -> VGBL CAIXA Composto 30 — Regressivo | C16: =IF(Motor!$E$9=0,"",Motor!$E$40) -> 376188.27 | D16: =IF(Motor!$E$9=0,"",Motor!$E$42) -> 254139.32 | E16: =IF(Motor!$E$9=0,"",Motor!$E$44) -> 226188.27 | F16: =IF(Motor!$E$9=0,"",Motor!$E$51) -> 2730.3495 | G16: =IF(Motor!$E$9=0,"",Motor!$E$56) -> Em até 5 dias | H16: =IF(Motor!$E$9=0,"",Motor!$E$57) -> Média
B17: =IF(Motor!$F$9=0,"",Motor!$F$6) -> PGBL CAIXA Composto 30 — Regressivo | C17: =IF(Motor!$F$9=0,"",Motor!$F$40) -> 353688.27 | D17: =IF(Motor!$F$9=0,"",Motor!$F$42) -> 238939.12 | E17: =IF(Motor!$F$9=0,"",Motor!$F$44) -> 203688.27 | F17: =IF(Motor!$F$9=0,"",Motor!$F$51) -> 2567.046 | G17: =IF(Motor!$F$9=0,"",Motor!$F$56) -> Em até 5 dias | H17: =IF(Motor!$F$9=0,"",Motor!$F$57) -> Média
B18: =IF(Motor!$G$9=0,"",Motor!$G$6) -> Fundo CAIXA RF IPCA Longo Prazo | C18: =IF(Motor!$G$9=0,"",Motor!$G$40) -> 316495.51 | D18: =IF(Motor!$G$9=0,"",Motor!$G$42) -> 213813.03 | E18: =IF(Motor!$G$9=0,"",Motor!$G$44) -> 166495.51 | F18: =IF(Motor!$G$9=0,"",Motor!$G$51) -> 1970.2821 | G18: =IF(Motor!$G$9=0,"",Motor!$G$56) -> Em até 5 dias | H18: =IF(Motor!$G$9=0,"",Motor!$G$57) -> Média
B19: =IF(MotorImovel!$B$5=0,"","Imóvel para aluguel") -> Imóvel para aluguel | C19: =IF(MotorImovel!$B$5=0,"",MotorImovel!$B$34) -> 329895.57 | D19: =IF(MotorImovel!$B$5=0,"",MotorImovel!$B$36) -> 222865.63 | E19: =IF(MotorImovel!$B$5=0,"",MotorImovel!$B$38) -> 174645.57 | F19: =IF(MotorImovel!$B$5=0,"",MotorImovel!$B$45) -> 827.86264 | G19: =IF(MotorImovel!$B$5=0,"",MotorImovel!$B$50) -> Depende de encontrar comprador — normalmente meses | H19: =IF(MotorImovel!$B$5=0,"",MotorImovel!$B$51) -> Média
A21: O QUE MUDA DE UMA PARA A OUTRA
B22: =IF(COUNT(Comparar!$Q$7:$Q$13)<2,"Há apenas uma alternativa na comparação. Coloque outras na aba Consultor para o cliente enxergar a diferença entre os caminhos possíveis.","Entre a alternativa que termina com mais patrimônio e a que termina com menos há uma diferença de "&TEXT(MAX(Comparar!$Q$7:$Q$13)-MIN(Comparar!$Q$7:$Q$13),"R$ #,##0")&". Esse número, sozinho, não decide nada: uma alternativa que rende um pouco menos, mas permite retirar o dinheiro quando for preciso, pode ser a escolha certa. O contrário também vale — travar o dinheiro por mais tempo costuma vir junto com uma taxa melhor e menos imposto.") -> Entre a alternativa que termina com mais patrimônio e a que termina com menos há uma diferença de R$ 94,231. Esse número, sozinho, não decide nada: uma alternativa que rende um pouco menos, mas permite retirar o dinheiro quando for preciso, pode ser a escolha certa. O contrário também vale — travar o dinheiro por mais tempo costuma vir junto com uma taxa melhor e menos imposto.
A26: COMO O PATRIMÔNIO PODE EVOLUIR
A46: AVISOS IMPORTANTES
B47: • Simulação baseada nas informações e premissas registradas nesta planilha. Os resultados reais podem ser diferentes. Rentabilidade passada não é garantia de rentabilidade futura e nenhum número aqui representa promessa de retorno.
B48: • Ferramenta de apoio à conversa, de uso do profissional. Não é peça oficial de oferta e não substitui a lâmina, o regulamento, o prospecto do produto nem o questionário oficial de perfil (suitability).
B49: • Rentabilidade passada não é garantia de rentabilidade futura. Os cenários são premissas escolhidas pelo profissional para mostrar uma faixa de resultados possíveis — não são previsão nem promessa.
B50: • Os valores de imposto e de custos são estimativas calculadas com as regras registradas na planilha na data indicada. Mudanças de legislação alteram o resultado.
B51: • Produtos de renda variável e fundos podem apresentar rentabilidade negativa. A oscilação indicada descreve o comportamento esperado, não um limite de perda.
B53: ="Documento gerado em "&TEXT(TODAY(),"dd/mm/yyyy")&" a partir das premissas registradas nesta planilha. Fontes e datas de atualização de cada dado estão registradas na aba Fontes." -> Documento gerado em 23/08/2026 a partir das premissas registradas nesta planilha. Fontes e datas de atualização de cada dado estão registradas na aba Fontes.
B56: ◀ INÍCIO | D56: ◀ CLIENTE | F56: COMPARAR
A57: Para entregar ao cliente: Arquivo ▸ Exportar / Salvar como PDF. A área de impressão já está configurada em uma página A4.

Sheet Adequacao
A1: ADERÊNCIA AO OBJETIVO DO CLIENTE
A2: Camada de cálculo — mede ENCAIXE, não rentabilidade
A4: O QUE ESTA ABA FAZ (E O QUE ELA NÃO FAZ) | X4: ◀ INÍCIO
A5: Esta aba NÃO responde 'qual investimento rende mais'. Ela responde 'quais alternativas conversam com o objetivo, o prazo, a necessidade de liquidez, o perfil e a prioridade DESTE cliente'. O retorno estimado aparece só na última coluna, como informação — ele não entra na nota. Dois produtos com a mesma nota podem render muito diferente, e isso é proposital: a escolha final é do cliente com o consultor.
A6: Pesos em uso (vêm da prioridade escolhida) | B6: Prazo | C6: Liquidez | D6: Prioridade | E6: Custo/imposto
B7: =IFERROR(INDEX($B$91:$B$94,MATCH(IN_PRIORIDADE,$A$91:$A$94,0)),25) -> 25 | C7: =IFERROR(INDEX($C$91:$C$94,MATCH(IN_PRIORIDADE,$A$91:$A$94,0)),25) -> 25 | D7: =IFERROR(INDEX($D$91:$D$94,MATCH(IN_PRIORIDADE,$A$91:$A$94,0)),25) -> 35 | E7: =IFERROR(INDEX($E$91:$E$94,MATCH(IN_PRIORIDADE,$A$91:$A$94,0)),25) -> 15
A8: ID | B8: Produto | C8: Categoria | D8: Risco | E8: Carência (dias) | F8: Liquidez (dias) | G8: Aplicação mínima | H8: Regime | I8: Taxa adm. | J8: Ativo | K8: Passa no valor mínimo | L8: Passa no perfil | M8: Nota de prazo | N8: Nota de liquidez | O8: Nota de prioridade | P8: Nota de custo e imposto | Q8: ADERÊNCIA (0-100) | R8: Chave de ordenação | S8: Classificação | T8: Por que pode fazer sentido | U8: Ponto de atenção | V8: Retorno bruto a.a. estimado | W8: Indexador | X8: Volatilidade
A9: =IF(Produtos!$B9="","",Produtos!$A9) -> RF01 | B9: =IF(Produtos!$B9="","",Produtos!$B9) -> Poupança | C9: =IF(Produtos!$B9="","",Produtos!$C9) -> Renda Fixa | D9: =IF(Produtos!$B9="",0,Produtos!$T9) -> 1 | E9: =IF(Produtos!$B9="",0,Produtos!$P9) -> 0 | F9: =IF(Produtos!$B9="",0,Produtos!$Q9) -> 0 | G9: =IF(Produtos!$B9="",0,Produtos!$R9) -> 0.01 | H9: =IF(Produtos!$B9="","",Produtos!$N9) -> ISENTO | I9: =IF(Produtos!$B9="",0,Produtos!$I9) -> 0 | J9: =IF(Produtos!$B9="","NÃO",Produtos!$AD9) -> SIM | K9: =IF(AND($B9<>"",IN_CAPITAL>=$G9),1,0) -> 1 | L9: =IF(AND($B9<>"",$D9<=IFERROR(INDEX(Premissas!$B$102:$B$104,MATCH(IN_PERFIL,Premissas!$A$102:$A$104,0)),5)),1,0) -> 1 | M9: =IF(IN_PRAZO*30<$E9,0,IF($D9>=4,IF(IN_PRAZO>=60,100,IF(IN_PRAZO>=36,60,IF(IN_PRAZO>=24,30,0))),IF($D9=3,IF(IN_PRAZO>=24,100,IF(IN_PRAZO>=12,70,40)),100))) -> 100 | N9: =IF(IN_RESGATE="Sim",IF($E9+$F9<=3,100,IF($E9+$F9<=31,50,0)),IF(IN_RESGATE="Talvez",IF($E9+$F9<=90,100,IF($E9+$F9<=360,50,20)),100)) -> 100 | O9: =IF($D9=0,0,IFERROR(INDEX($B$98:$F$101,MATCH(IN_PRIORIDADE,$A$98:$A$101,0),$D9),0)) -> 60 | P9: =MAX(0,MIN(100,60+IF($H9="ISENTO",25,0)+IF($I9<=0.005,15,IF($I9>=0.015,-15,0))+IF(AND($H9="PREV_REGR",IN_PRAZO>=120),20,0)+IF(AND($H9="FUNDO_LP",IN_PRAZO<=12),-10,0)+IF(AND($H9="FUNDO_CP",IN_PRAZO>=24),-15,0))) -> 100 | Q9: =IF(OR($B9="",$J9<>"SIM",$K9=0,$L9=0),0,ROUND(($M9*$B$7+$N9*$C$7+$O9*$D$7+$P9*$E$7)/MAX(1,$B$7+$C$7+$D$7+$E$7),1)) -> 86 | R9: =IF($H9="IMOVEL",0,$Q9+ROW()/1000000) -> 86.000009 | S9: =IF($B9="","",IF($Q9=0,"Não indicado agora",IF($Q9>=75,"Pode fazer sentido",IF($Q9>=50,"Talvez faça sentido","Provavelmente não é o mais indicado")))) -> Pode fazer sentido | T9: =IF($B9="","",IF($Q9=0,IF($K9=0,"O valor disponível é menor que a aplicação mínima deste produto.",IF($L9=0,"O risco deste produto está acima do perfil declarado pelo cliente.","Produto não está ativo na base.")),IF($Q9<50,"Encaixa pouco no que foi pedido — veja o ponto de atenção ao lado.",IF($H9="ISENTO","Não paga Imposto de Renda para pessoa física.",IF($W9="PRE","A taxa fica travada na contratação: não cai se os juros da economia caírem.",IF($W9="IPCA","Protege o poder de compra: rende a inflação mais uma taxa fixa por cima.",IF(AND($E9=0,$F9<=1),"O dinheiro pode ser retirado praticamente a qualquer momento.",IF(AND($H9="PREV_REGR",IN_PRAZO>=120),"No prazo escolhido a previdência alcança a menor alíquota de imposto (10%).",IF($D9>=4,"Pode render mais no prazo longo, aceitando oscilação pelo caminho.","Combina com o prazo, a liquidez e a prioridade informados."))))))))) -> Não paga Imposto de Renda para pessoa física. | U9: =IF($B9="","",IF($E9>0,"Carência de "&$E9&" dias: não dá para resgatar antes.",IF($F9>60,"Não é dinheiro rápido: leva meses para virar caixa.",IF(LEFT($H9,4)="PREV",IF(IN_PRAZO<24,"Resgate antes de 2 anos paga 35% de imposto.","Não tem cobertura do FGC: quem responde pelo dinheiro é a seguradora."),IF($D9>=4,"Pode cair no caminho e demorar a se recuperar.",IF(AND($H9="RF_REGR",$X9>=0.03),"Se vender antes do vencimento, o preço pode estar abaixo do que você pagou.",IF($X9>=0.03,"O valor oscila mês a mês: em prazo curto pode estar abaixo do que você aplicou.",IF($H9="FUNDO_LP","Tem come-cotas em maio e novembro, que antecipam parte do imposto.",IF($F9>7,"Para o dinheiro cair na conta leva cerca de "&$F9&" dias.",IF($I9>=0.015,"Taxa de administração alta em relação ao retorno esperado.","Confirme prazo, liquidez e tributação antes de contratar.")))))))))) -> Confirme prazo, liquidez e tributação antes de contratar. | V9: =IF($B9="","",IFERROR(IF(Produtos!$H9="MULT",(1+INDEX(TAB_MACRO_VAL,MATCH(Produtos!$E9,TAB_MACRO_COD,0))*Produtos!$F9)*(1+Produtos!$G9)-1,INDEX(TAB_MACRO_VAL,MATCH(Produtos!$E9,TAB_MACRO_COD,0))*Produtos!$F9+Produtos!$G9),"")) -> 0.071677812 | W9: =IF(Produtos!$B9="","",Produtos!$E9) -> POUP | X9: =IF(Produtos!$B9="",0,Produtos!$U9) -> 0.001
A10: =IF(Produtos!$B10="","",Produtos!$A10) -> RF02 | B10: =IF(Produtos!$B10="","",Produtos!$B10) -> CDB CAIXA Liquidez Diária | C10: =IF(Produtos!$B10="","",Produtos!$C10) -> Renda Fixa | D10: =IF(Produtos!$B10="",0,Produtos!$T10) -> 1 | E10: =IF(Produtos!$B10="",0,Produtos!$P10) -> 0 | F10: =IF(Produtos!$B10="",0,Produtos!$Q10) -> 0 | G10: =IF(Produtos!$B10="",0,Produtos!$R10) -> 100 | H10: =IF(Produtos!$B10="","",Produtos!$N10) -> RF_REGR | I10: =IF(Produtos!$B10="",0,Produtos!$I10) -> 0 | J10: =IF(Produtos!$B10="","NÃO",Produtos!$AD10) -> SIM | K10: =IF(AND($B10<>"",IN_CAPITAL>=$G10),1,0) -> 1 | L10: =IF(AND($B10<>"",$D10<=IFERROR(INDEX(Premissas!$B$102:$B$104,MATCH(IN_PERFIL,Premissas!$A$102:$A$104,0)),5)),1,0) -> 1 | M10: =IF(IN_PRAZO*30<$E10,0,IF($D10>=4,IF(IN_PRAZO>=60,100,IF(IN_PRAZO>=36,60,IF(IN_PRAZO>=24,30,0))),IF($D10=3,IF(IN_PRAZO>=24,100,IF(IN_PRAZO>=12,70,40)),100))) -> 100 | N10: =IF(IN_RESGATE="Sim",IF($E10+$F10<=3,100,IF($E10+$F10<=31,50,0)),IF(IN_RESGATE="Talvez",IF($E10+$F10<=90,100,IF($E10+$F10<=360,50,20)),100)) -> 100 | O10: =IF($D10=0,0,IFERROR(INDEX($B$98:$F$101,MATCH(IN_PRIORIDADE,$A$98:$A$101,0),$D10),0)) -> 60 | P10: =MAX(0,MIN(100,60+IF($H10="ISENTO",25,0)+IF($I10<=0.005,15,IF($I10>=0.015,-15,0))+IF(AND($H10="PREV_REGR",IN_PRAZO>=120),20,0)+IF(AND($H10="FUNDO_LP",IN_PRAZO<=12),-10,0)+IF(AND($H10="FUNDO_CP",IN_PRAZO>=24),-15,0))) -> 75 | Q10: =IF(OR($B10="",$J10<>"SIM",$K10=0,$L10=0),0,ROUND(($M10*$B$7+$N10*$C$7+$O10*$D$7+$P10*$E$7)/MAX(1,$B$7+$C$7+$D$7+$E$7),1)) -> 82.3 | R10: =IF($H10="IMOVEL",0,$Q10+ROW()/1000000) -> 82.30001 | S10: =IF($B10="","",IF($Q10=0,"Não indicado agora",IF($Q10>=75,"Pode fazer sentido",IF($Q10>=50,"Talvez faça sentido","Provavelmente não é o mais indicado")))) -> Pode fazer sentido | T10: =IF($B10="","",IF($Q10=0,IF($K10=0,"O valor disponível é menor que a aplicação mínima deste produto.",IF($L10=0,"O risco deste produto está acima do perfil declarado pelo cliente.","Produto não está ativo na base.")),IF($Q10<50,"Encaixa pouco no que foi pedido — veja o ponto de atenção ao lado.",IF($H10="ISENTO","Não paga Imposto de Renda para pessoa física.",IF($W10="PRE","A taxa fica travada na contratação: não cai se os juros da economia caírem.",IF($W10="IPCA","Protege o poder de compra: rende a inflação mais uma taxa fixa por cima.",IF(AND($E10=0,$F10<=1),"O dinheiro pode ser retirado praticamente a qualquer momento.",IF(AND($H10="PREV_REGR",IN_PRAZO>=120),"No prazo escolhido a previdência alcança a menor alíquota de imposto (10%).",IF($D10>=4,"Pode render mais no prazo longo, aceitando oscilação pelo caminho.","Combina com o prazo, a liquidez e a prioridade informados."))))))))) -> O dinheiro pode ser retirado praticamente a qualquer momento. | U10: =IF($B10="","",IF($E10>0,"Carência de "&$E10&" dias: não dá para resgatar antes.",IF($F10>60,"Não é dinheiro rápido: leva meses para virar caixa.",IF(LEFT($H10,4)="PREV",IF(IN_PRAZO<24,"Resgate antes de 2 anos paga 35% de imposto.","Não tem cobertura do FGC: quem responde pelo dinheiro é a seguradora."),IF($D10>=4,"Pode cair no caminho e demorar a se recuperar.",IF(AND($H10="RF_REGR",$X10>=0.03),"Se vender antes do vencimento, o preço pode estar abaixo do que você pagou.",IF($X10>=0.03,"O valor oscila mês a mês: em prazo curto pode estar abaixo do que você aplicou.",IF($H10="FUNDO_LP","Tem come-cotas em maio e novembro, que antecipam parte do imposto.",IF($F10>7,"Para o dinheiro cair na conta leva cerca de "&$F10&" dias.",IF($I10>=0.015,"Taxa de administração alta em relação ao retorno esperado.","Confirme prazo, liquidez e tributação antes de contratar.")))))))))) -> Confirme prazo, liquidez e tributação antes de contratar. | V10: =IF($B10="","",IFERROR(IF(Produtos!$H10="MULT",(1+INDEX(TAB_MACRO_VAL,MATCH(Produtos!$E10,TAB_MACRO_COD,0))*Produtos!$F10)*(1+Produtos!$G10)-1,INDEX(TAB_MACRO_VAL,MATCH(Produtos!$E10,TAB_MACRO_COD,0))*Produtos!$F10+Produtos!$G10),"")) -> 0.10682 | W10: =IF(Produtos!$B10="","",Produtos!$E10) -> CDI | X10: =IF(Produtos!$B10="",0,Produtos!$U10) -> 0.001
A11: =IF(Produtos!$B11="","",Produtos!$A11) -> RF03 | B11: =IF(Produtos!$B11="","",Produtos!$B11) -> CDB CAIXA 12 meses | C11: =IF(Produtos!$B11="","",Produtos!$C11) -> Renda Fixa | D11: =IF(Produtos!$B11="",0,Produtos!$T11) -> 1 | E11: =IF(Produtos!$B11="",0,Produtos!$P11) -> 360 | F11: =IF(Produtos!$B11="",0,Produtos!$Q11) -> 0 | G11: =IF(Produtos!$B11="",0,Produtos!$R11) -> 1000 | H11: =IF(Produtos!$B11="","",Produtos!$N11) -> RF_REGR | I11: =IF(Produtos!$B11="",0,Produtos!$I11) -> 0 | J11: =IF(Produtos!$B11="","NÃO",Produtos!$AD11) -> SIM | K11: =IF(AND($B11<>"",IN_CAPITAL>=$G11),1,0) -> 1 | L11: =IF(AND($B11<>"",$D11<=IFERROR(INDEX(Premissas!$B$102:$B$104,MATCH(IN_PERFIL,Premissas!$A$102:$A$104,0)),5)),1,0) -> 1 | M11: =IF(IN_PRAZO*30<$E11,0,IF($D11>=4,IF(IN_PRAZO>=60,100,IF(IN_PRAZO>=36,60,IF(IN_PRAZO>=24,30,0))),IF($D11=3,IF(IN_PRAZO>=24,100,IF(IN_PRAZO>=12,70,40)),100))) -> 100 | N11: =IF(IN_RESGATE="Sim",IF($E11+$F11<=3,100,IF($E11+$F11<=31,50,0)),IF(IN_RESGATE="Talvez",IF($E11+$F11<=90,100,IF($E11+$F11<=360,50,20)),100)) -> 50 | O11: =IF($D11=0,0,IFERROR(INDEX($B$98:$F$101,MATCH(IN_PRIORIDADE,$A$98:$A$101,0),$D11),0)) -> 60 | P11: =MAX(0,MIN(100,60+IF($H11="ISENTO",25,0)+IF($I11<=0.005,15,IF($I11>=0.015,-15,0))+IF(AND($H11="PREV_REGR",IN_PRAZO>=120),20,0)+IF(AND($H11="FUNDO_LP",IN_PRAZO<=12),-10,0)+IF(AND($H11="FUNDO_CP",IN_PRAZO>=24),-15,0))) -> 75 | Q11: =IF(OR($B11="",$J11<>"SIM",$K11=0,$L11=0),0,ROUND(($M11*$B$7+$N11*$C$7+$O11*$D$7+$P11*$E$7)/MAX(1,$B$7+$C$7+$D$7+$E$7),1)) -> 69.8 | R11: =IF($H11="IMOVEL",0,$Q11+ROW()/1000000) -> 69.800011 | S11: =IF($B11="","",IF($Q11=0,"Não indicado agora",IF($Q11>=75,"Pode fazer sentido",IF($Q11>=50,"Talvez faça sentido","Provavelmente não é o mais indicado")))) -> Talvez faça sentido | T11: =IF($B11="","",IF($Q11=0,IF($K11=0,"O valor disponível é menor que a aplicação mínima deste produto.",IF($L11=0,"O risco deste produto está acima do perfil declarado pelo cliente.","Produto não está ativo na base.")),IF($Q11<50,"Encaixa pouco no que foi pedido — veja o ponto de atenção ao lado.",IF($H11="ISENTO","Não paga Imposto de Renda para pessoa física.",IF($W11="PRE","A taxa fica travada na contratação: não cai se os juros da economia caírem.",IF($W11="IPCA","Protege o poder de compra: rende a inflação mais uma taxa fixa por cima.",IF(AND($E11=0,$F11<=1),"O dinheiro pode ser retirado praticamente a qualquer momento.",IF(AND($H11="PREV_REGR",IN_PRAZO>=120),"No prazo escolhido a previdência alcança a menor alíquota de imposto (10%).",IF($D11>=4,"Pode render mais no prazo longo, aceitando oscilação pelo caminho.","Combina com o prazo, a liquidez e a prioridade informados."))))))))) -> Combina com o prazo, a liquidez e a prioridade informados. | U11: =IF($B11="","",IF($E11>0,"Carência de "&$E11&" dias: não dá para resgatar antes.",IF($F11>60,"Não é dinheiro rápido: leva meses para virar caixa.",IF(LEFT($H11,4)="PREV",IF(IN_PRAZO<24,"Resgate antes de 2 anos paga 35% de imposto.","Não tem cobertura do FGC: quem responde pelo dinheiro é a seguradora."),IF($D11>=4,"Pode cair no caminho e demorar a se recuperar.",IF(AND($H11="RF_REGR",$X11>=0.03),"Se vender antes do vencimento, o preço pode estar abaixo do que você pagou.",IF($X11>=0.03,"O valor oscila mês a mês: em prazo curto pode estar abaixo do que você aplicou.",IF($H11="FUNDO_LP","Tem come-cotas em maio e novembro, que antecipam parte do imposto.",IF($F11>7,"Para o dinheiro cair na conta leva cerca de "&$F11&" dias.",IF($I11>=0.015,"Taxa de administração alta em relação ao retorno esperado.","Confirme prazo, liquidez e tributação antes de contratar.")))))))))) -> Carência de 360 dias: não dá para resgatar antes. | V11: =IF($B11="","",IFERROR(IF(Produtos!$H11="MULT",(1+INDEX(TAB_MACRO_VAL,MATCH(Produtos!$E11,TAB_MACRO_COD,0))*Produtos!$F11)*(1+Produtos!$G11)-1,INDEX(TAB_MACRO_VAL,MATCH(Produtos!$E11,TAB_MACRO_COD,0))*Produtos!$F11+Produtos!$G11),"")) -> 0.11118 | W11: =IF(Produtos!$B11="","",Produtos!$E11) -> CDI | X11: =IF(Produtos!$B11="",0,Produtos!$U11) -> 0.001
A12: =IF(Produtos!$B12="","",Produtos!$A12) -> RF04 | B12: =IF(Produtos!$B12="","",Produtos!$B12) -> CDB CAIXA 24 meses | C12: =IF(Produtos!$B12="","",Produtos!$C12) -> Renda Fixa | D12: =IF(Produtos!$B12="",0,Produtos!$T12) -> 1 | E12: =IF(Produtos!$B12="",0,Produtos!$P12) -> 720 | F12: =IF(Produtos!$B12="",0,Produtos!$Q12) -> 0 | G12: =IF(Produtos!$B12="",0,Produtos!$R12) -> 5000 | H12: =IF(Produtos!$B12="","",Produtos!$N12) -> RF_REGR | I12: =IF(Produtos!$B12="",0,Produtos!$I12) -> 0 | J12: =IF(Produtos!$B12="","NÃO",Produtos!$AD12) -> SIM | K12: =IF(AND($B12<>"",IN_CAPITAL>=$G12),1,0) -> 1 | L12: =IF(AND($B12<>"",$D12<=IFERROR(INDEX(Premissas!$B$102:$B$104,MATCH(IN_PERFIL,Premissas!$A$102:$A$104,0)),5)),1,0) -> 1 | M12: =IF(IN_PRAZO*30<$E12,0,IF($D12>=4,IF(IN_PRAZO>=60,100,IF(IN_PRAZO>=36,60,IF(IN_PRAZO>=24,30,0))),IF($D12=3,IF(IN_PRAZO>=24,100,IF(IN_PRAZO>=12,70,40)),100))) -> 100 | N12: =IF(IN_RESGATE="Sim",IF($E12+$F12<=3,100,IF($E12+$F12<=31,50,0)),IF(IN_RESGATE="Talvez",IF($E12+$F12<=90,100,IF($E12+$F12<=360,50,20)),100)) -> 20 | O12: =IF($D12=0,0,IFERROR(INDEX($B$98:$F$101,MATCH(IN_PRIORIDADE,$A$98:$A$101,0),$D12),0)) -> 60 | P12: =MAX(0,MIN(100,60+IF($H12="ISENTO",25,0)+IF($I12<=0.005,15,IF($I12>=0.015,-15,0))+IF(AND($H12="PREV_REGR",IN_PRAZO>=120),20,0)+IF(AND($H12="FUNDO_LP",IN_PRAZO<=12),-10,0)+IF(AND($H12="FUNDO_CP",IN_PRAZO>=24),-15,0))) -> 75 | Q12: =IF(OR($B12="",$J12<>"SIM",$K12=0,$L12=0),0,ROUND(($M12*$B$7+$N12*$C$7+$O12*$D$7+$P12*$E$7)/MAX(1,$B$7+$C$7+$D$7+$E$7),1)) -> 62.3 | R12: =IF($H12="IMOVEL",0,$Q12+ROW()/1000000) -> 62.300012 | S12: =IF($B12="","",IF($Q12=0,"Não indicado agora",IF($Q12>=75,"Pode fazer sentido",IF($Q12>=50,"Talvez faça sentido","Provavelmente não é o mais indicado")))) -> Talvez faça sentido | T12: =IF($B12="","",IF($Q12=0,IF($K12=0,"O valor disponível é menor que a aplicação mínima deste produto.",IF($L12=0,"O risco deste produto está acima do perfil declarado pelo cliente.","Produto não está ativo na base.")),IF($Q12<50,"Encaixa pouco no que foi pedido — veja o ponto de atenção ao lado.",IF($H12="ISENTO","Não paga Imposto de Renda para pessoa física.",IF($W12="PRE","A taxa fica travada na contratação: não cai se os juros da economia caírem.",IF($W12="IPCA","Protege o poder de compra: rende a inflação mais uma taxa fixa por cima.",IF(AND($E12=0,$F12<=1),"O dinheiro pode ser retirado praticamente a qualquer momento.",IF(AND($H12="PREV_REGR",IN_PRAZO>=120),"No prazo escolhido a previdência alcança a menor alíquota de imposto (10%).",IF($D12>=4,"Pode render mais no prazo longo, aceitando oscilação pelo caminho.","Combina com o prazo, a liquidez e a prioridade informados."))))))))) -> Combina com o prazo, a liquidez e a prioridade informados. | U12: =IF($B12="","",IF($E12>0,"Carência de "&$E12&" dias: não dá para resgatar antes.",IF($F12>60,"Não é dinheiro rápido: leva meses para virar caixa.",IF(LEFT($H12,4)="PREV",IF(IN_PRAZO<24,"Resgate antes de 2 anos paga 35% de imposto.","Não tem cobertura do FGC: quem responde pelo dinheiro é a seguradora."),IF($D12>=4,"Pode cair no caminho e demorar a se recuperar.",IF(AND($H12="RF_REGR",$X12>=0.03),"Se vender antes do vencimento, o preço pode estar abaixo do que você pagou.",IF($X12>=0.03,"O valor oscila mês a mês: em prazo curto pode estar abaixo do que você aplicou.",IF($H12="FUNDO_LP","Tem come-cotas em maio e novembro, que antecipam parte do imposto.",IF($F12>7,"Para o dinheiro cair na conta leva cerca de "&$F12&" dias.",IF($I12>=0.015,"Taxa de administração alta em relação ao retorno esperado.","Confirme prazo, liquidez e tributação antes de contratar.")))))))))) -> Carência de 720 dias: não dá para resgatar antes. | V12: =IF($B12="","",IFERROR(IF(Produtos!$H12="MULT",(1+INDEX(TAB_MACRO_VAL,MATCH(Produtos!$E12,TAB_MACRO_COD,0))*Produtos!$F12)*(1+Produtos!$G12)-1,INDEX(TAB_MACRO_VAL,MATCH(Produtos!$E12,TAB_MACRO_COD,0))*Produtos!$F12+Produtos!$G12),"")) -> 0.11445 | W12: =IF(Produtos!$B12="","",Produtos!$E12) -> CDI | X12: =IF(Produtos!$B12="",0,Produtos!$U12) -> 0.001
A13: =IF(Produtos!$B13="","",Produtos!$A13) -> RF05 | B13: =IF(Produtos!$B13="","",Produtos!$B13) -> CDB CAIXA 60 meses | C13: =IF(Produtos!$B13="","",Produtos!$C13) -> Renda Fixa | D13: =IF(Produtos!$B13="",0,Produtos!$T13) -> 1 | E13: =IF(Produtos!$B13="",0,Produtos!$P13) -> 1800 | F13: =IF(Produtos!$B13="",0,Produtos!$Q13) -> 0 | G13: =IF(Produtos!$B13="",0,Produtos!$R13) -> 10000 | H13: =IF(Produtos!$B13="","",Produtos!$N13) -> RF_REGR | I13: =IF(Produtos!$B13="",0,Produtos!$I13) -> 0 | J13: =IF(Produtos!$B13="","NÃO",Produtos!$AD13) -> SIM | K13: =IF(AND($B13<>"",IN_CAPITAL>=$G13),1,0) -> 1 | L13: =IF(AND($B13<>"",$D13<=IFERROR(INDEX(Premissas!$B$102:$B$104,MATCH(IN_PERFIL,Premissas!$A$102:$A$104,0)),5)),1,0) -> 1 | M13: =IF(IN_PRAZO*30<$E13,0,IF($D13>=4,IF(IN_PRAZO>=60,100,IF(IN_PRAZO>=36,60,IF(IN_PRAZO>=24,30,0))),IF($D13=3,IF(IN_PRAZO>=24,100,IF(IN_PRAZO>=12,70,40)),100))) -> 100 | N13: =IF(IN_RESGATE="Sim",IF($E13+$F13<=3,100,IF($E13+$F13<=31,50,0)),IF(IN_RESGATE="Talvez",IF($E13+$F13<=90,100,IF($E13+$F13<=360,50,20)),100)) -> 20 | O13: =IF($D13=0,0,IFERROR(INDEX($B$98:$F$101,MATCH(IN_PRIORIDADE,$A$98:$A$101,0),$D13),0)) -> 60 | P13: =MAX(0,MIN(100,60+IF($H13="ISENTO",25,0)+IF($I13<=0.005,15,IF($I13>=0.015,-15,0))+IF(AND($H13="PREV_REGR",IN_PRAZO>=120),20,0)+IF(AND($H13="FUNDO_LP",IN_PRAZO<=12),-10,0)+IF(AND($H13="FUNDO_CP",IN_PRAZO>=24),-15,0))) -> 75 | Q13: =IF(OR($B13="",$J13<>"SIM",$K13=0,$L13=0),0,ROUND(($M13*$B$7+$N13*$C$7+$O13*$D$7+$P13*$E$7)/MAX(1,$B$7+$C$7+$D$7+$E$7),1)) -> 62.3 | R13: =IF($H13="IMOVEL",0,$Q13+ROW()/1000000) -> 62.300013 | S13: =IF($B13="","",IF($Q13=0,"Não indicado agora",IF($Q13>=75,"Pode fazer sentido",IF($Q13>=50,"Talvez faça sentido","Provavelmente não é o mais indicado")))) -> Talvez faça sentido | T13: =IF($B13="","",IF($Q13=0,IF($K13=0,"O valor disponível é menor que a aplicação mínima deste produto.",IF($L13=0,"O risco deste produto está acima do perfil declarado pelo cliente.","Produto não está ativo na base.")),IF($Q13<50,"Encaixa pouco no que foi pedido — veja o ponto de atenção ao lado.",IF($H13="ISENTO","Não paga Imposto de Renda para pessoa física.",IF($W13="PRE","A taxa fica travada na contratação: não cai se os juros da economia caírem.",IF($W13="IPCA","Protege o poder de compra: rende a inflação mais uma taxa fixa por cima.",IF(AND($E13=0,$F13<=1),"O dinheiro pode ser retirado praticamente a qualquer momento.",IF(AND($H13="PREV_REGR",IN_PRAZO>=120),"No prazo escolhido a previdência alcança a menor alíquota de imposto (10%).",IF($D13>=4,"Pode render mais no prazo longo, aceitando oscilação pelo caminho.","Combina com o prazo, a liquidez e a prioridade informados."))))))))) -> Combina com o prazo, a liquidez e a prioridade informados. | U13: =IF($B13="","",IF($E13>0,"Carência de "&$E13&" dias: não dá para resgatar antes.",IF($F13>60,"Não é dinheiro rápido: leva meses para virar caixa.",IF(LEFT($H13,4)="PREV",IF(IN_PRAZO<24,"Resgate antes de 2 anos paga 35% de imposto.","Não tem cobertura do FGC: quem responde pelo dinheiro é a seguradora."),IF($D13>=4,"Pode cair no caminho e demorar a se recuperar.",IF(AND($H13="RF_REGR",$X13>=0.03),"Se vender antes do vencimento, o preço pode estar abaixo do que você pagou.",IF($X13>=0.03,"O valor oscila mês a mês: em prazo curto pode estar abaixo do que você aplicou.",IF($H13="FUNDO_LP","Tem come-cotas em maio e novembro, que antecipam parte do imposto.",IF($F13>7,"Para o dinheiro cair na conta leva cerca de "&$F13&" dias.",IF($I13>=0.015,"Taxa de administração alta em relação ao retorno esperado.","Confirme prazo, liquidez e tributação antes de contratar.")))))))))) -> Carência de 1800 dias: não dá para resgatar antes. | V13: =IF($B13="","",IFERROR(IF(Produtos!$H13="MULT",(1+INDEX(TAB_MACRO_VAL,MATCH(Produtos!$E13,TAB_MACRO_COD,0))*Produtos!$F13)*(1+Produtos!$G13)-1,INDEX(TAB_MACRO_VAL,MATCH(Produtos!$E13,TAB_MACRO_COD,0))*Produtos!$F13+Produtos!$G13),"")) -> 0.1199 | W13: =IF(Produtos!$B13="","",Produtos!$E13) -> CDI | X13: =IF(Produtos!$B13="",0,Produtos!$U13) -> 0.001
A14: =IF(Produtos!$B14="","",Produtos!$A14) -> RF06 | B14: =IF(Produtos!$B14="","",Produtos!$B14) -> LCI CAIXA 12 meses | C14: =IF(Produtos!$B14="","",Produtos!$C14) -> Renda Fixa | D14: =IF(Produtos!$B14="",0,Produtos!$T14) -> 1 | E14: =IF(Produtos!$B14="",0,Produtos!$P14) -> 360 | F14: =IF(Produtos!$B14="",0,Produtos!$Q14) -> 0 | G14: =IF(Produtos!$B14="",0,Produtos!$R14) -> 5000 | H14: =IF(Produtos!$B14="","",Produtos!$N14) -> ISENTO | I14: =IF(Produtos!$B14="",0,Produtos!$I14) -> 0 | J14: =IF(Produtos!$B14="","NÃO",Produtos!$AD14) -> SIM | K14: =IF(AND($B14<>"",IN_CAPITAL>=$G14),1,0) -> 1 | L14: =IF(AND($B14<>"",$D14<=IFERROR(INDEX(Premissas!$B$102:$B$104,MATCH(IN_PERFIL,Premissas!$A$102:$A$104,0)),5)),1,0) -> 1 | M14: =IF(IN_PRAZO*30<$E14,0,IF($D14>=4,IF(IN_PRAZO>=60,100,IF(IN_PRAZO>=36,60,IF(IN_PRAZO>=24,30,0))),IF($D14=3,IF(IN_PRAZO>=24,100,IF(IN_PRAZO>=12,70,40)),100))) -> 100 | N14: =IF(IN_RESGATE="Sim",IF($E14+$F14<=3,100,IF($E14+$F14<=31,50,0)),IF(IN_RESGATE="Talvez",IF($E14+$F14<=90,100,IF($E14+$F14<=360,50,20)),100)) -> 50 | O14: =IF($D14=0,0,IFERROR(INDEX($B$98:$F$101,MATCH(IN_PRIORIDADE,$A$98:$A$101,0),$D14),0)) -> 60 | P14: =MAX(0,MIN(100,60+IF($H14="ISENTO",25,0)+IF($I14<=0.005,15,IF($I14>=0.015,-15,0))+IF(AND($H14="PREV_REGR",IN_PRAZO>=120),20,0)+IF(AND($H14="FUNDO_LP",IN_PRAZO<=12),-10,0)+IF(AND($H14="FUNDO_CP",IN_PRAZO>=24),-15,0))) -> 100 | Q14: =IF(OR($B14="",$J14<>"SIM",$K14=0,$L14=0),0,ROUND(($M14*$B$7+$N14*$C$7+$O14*$D$7+$P14*$E$7)/MAX(1,$B$7+$C$7+$D$7+$E$7),1)) -> 73.5 | R14: =IF($H14="IMOVEL",0,$Q14+ROW()/1000000) -> 73.500014 | S14: =IF($B14="","",IF($Q14=0,"Não indicado agora",IF($Q14>=75,"Pode fazer sentido",IF($Q14>=50,"Talvez faça sentido","Provavelmente não é o mais indicado")))) -> Talvez faça sentido | T14: =IF($B14="","",IF($Q14=0,IF($K14=0,"O valor disponível é menor que a aplicação mínima deste produto.",IF($L14=0,"O risco deste produto está acima do perfil declarado pelo cliente.","Produto não está ativo na base.")),IF($Q14<50,"Encaixa pouco no que foi pedido — veja o ponto de atenção ao lado.",IF($H14="ISENTO","Não paga Imposto de Renda para pessoa física.",IF($W14="PRE","A taxa fica travada na contratação: não cai se os juros da economia caírem.",IF($W14="IPCA","Protege o poder de compra: rende a inflação mais uma taxa fixa por cima.",IF(AND($E14=0,$F14<=1),"O dinheiro pode ser retirado praticamente a qualquer momento.",IF(AND($H14="PREV_REGR",IN_PRAZO>=120),"No prazo escolhido a previdência alcança a menor alíquota de imposto (10%).",IF($D14>=4,"Pode render mais no prazo longo, aceitando oscilação pelo caminho.","Combina com o prazo, a liquidez e a prioridade informados."))))))))) -> Não paga Imposto de Renda para pessoa física. | U14: =IF($B14="","",IF($E14>0,"Carência de "&$E14&" dias: não dá para resgatar antes.",IF($F14>60,"Não é dinheiro rápido: leva meses para virar caixa.",IF(LEFT($H14,4)="PREV",IF(IN_PRAZO<24,"Resgate antes de 2 anos paga 35% de imposto.","Não tem cobertura do FGC: quem responde pelo dinheiro é a seguradora."),IF($D14>=4,"Pode cair no caminho e demorar a se recuperar.",IF(AND($H14="RF_REGR",$X14>=0.03),"Se vender antes do vencimento, o preço pode estar abaixo do que você pagou.",IF($X14>=0.03,"O valor oscila mês a mês: em prazo curto pode estar abaixo do que você aplicou.",IF($H14="FUNDO_LP","Tem come-cotas em maio e novembro, que antecipam parte do imposto.",IF($F14>7,"Para o dinheiro cair na conta leva cerca de "&$F14&" dias.",IF($I14>=0.015,"Taxa de administração alta em relação ao retorno esperado.","Confirme prazo, liquidez e tributação antes de contratar.")))))))))) -> Carência de 360 dias: não dá para resgatar antes. | V14: =IF($B14="","",IFERROR(IF(Produtos!$H14="MULT",(1+INDEX(TAB_MACRO_VAL,MATCH(Produtos!$E14,TAB_MACRO_COD,0))*Produtos!$F14)*(1+Produtos!$G14)-1,INDEX(TAB_MACRO_VAL,MATCH(Produtos!$E14,TAB_MACRO_COD,0))*Produtos!$F14+Produtos!$G14),"")) -> 0.10028 | W14: =IF(Produtos!$B14="","",Produtos!$E14) -> CDI | X14: =IF(Produtos!$B14="",0,Produtos!$U14) -> 0.001
A15: =IF(Produtos!$B15="","",Produtos!$A15) -> RF07 | B15: =IF(Produtos!$B15="","",Produtos!$B15) -> LCA CAIXA 12 meses | C15: =IF(Produtos!$B15="","",Produtos!$C15) -> Renda Fixa | D15: =IF(Produtos!$B15="",0,Produtos!$T15) -> 1 | E15: =IF(Produtos!$B15="",0,Produtos!$P15) -> 270 | F15: =IF(Produtos!$B15="",0,Produtos!$Q15) -> 0 | G15: =IF(Produtos!$B15="",0,Produtos!$R15) -> 5000 | H15: =IF(Produtos!$B15="","",Produtos!$N15) -> ISENTO | I15: =IF(Produtos!$B15="",0,Produtos!$I15) -> 0 | J15: =IF(Produtos!$B15="","NÃO",Produtos!$AD15) -> SIM | K15: =IF(AND($B15<>"",IN_CAPITAL>=$G15),1,0) -> 1 | L15: =IF(AND($B15<>"",$D15<=IFERROR(INDEX(Premissas!$B$102:$B$104,MATCH(IN_PERFIL,Premissas!$A$102:$A$104,0)),5)),1,0) -> 1 | M15: =IF(IN_PRAZO*30<$E15,0,IF($D15>=4,IF(IN_PRAZO>=60,100,IF(IN_PRAZO>=36,60,IF(IN_PRAZO>=24,30,0))),IF($D15=3,IF(IN_PRAZO>=24,100,IF(IN_PRAZO>=12,70,40)),100))) -> 100 | N15: =IF(IN_RESGATE="Sim",IF($E15+$F15<=3,100,IF($E15+$F15<=31,50,0)),IF(IN_RESGATE="Talvez",IF($E15+$F15<=90,100,IF($E15+$F15<=360,50,20)),100)) -> 50 | O15: =IF($D15=0,0,IFERROR(INDEX($B$98:$F$101,MATCH(IN_PRIORIDADE,$A$98:$A$101,0),$D15),0)) -> 60 | P15: =MAX(0,MIN(100,60+IF($H15="ISENTO",25,0)+IF($I15<=0.005,15,IF($I15>=0.015,-15,0))+IF(AND($H15="PREV_REGR",IN_PRAZO>=120),20,0)+IF(AND($H15="FUNDO_LP",IN_PRAZO<=12),-10,0)+IF(AND($H15="FUNDO_CP",IN_PRAZO>=24),-15,0))) -> 100 | Q15: =IF(OR($B15="",$J15<>"SIM",$K15=0,$L15=0),0,ROUND(($M15*$B$7+$N15*$C$7+$O15*$D$7+$P15*$E$7)/MAX(1,$B$7+$C$7+$D$7+$E$7),1)) -> 73.5 | R15: =IF($H15="IMOVEL",0,$Q15+ROW()/1000000) -> 73.500015 | S15: =IF($B15="","",IF($Q15=0,"Não indicado agora",IF($Q15>=75,"Pode fazer sentido",IF($Q15>=50,"Talvez faça sentido","Provavelmente não é o mais indicado")))) -> Talvez faça sentido | T15: =IF($B15="","",IF($Q15=0,IF($K15=0,"O valor disponível é menor que a aplicação mínima deste produto.",IF($L15=0,"O risco deste produto está acima do perfil declarado pelo cliente.","Produto não está ativo na base.")),IF($Q15<50,"Encaixa pouco no que foi pedido — veja o ponto de atenção ao lado.",IF($H15="ISENTO","Não paga Imposto de Renda para pessoa física.",IF($W15="PRE","A taxa fica travada na contratação: não cai se os juros da economia caírem.",IF($W15="IPCA","Protege o poder de compra: rende a inflação mais uma taxa fixa por cima.",IF(AND($E15=0,$F15<=1),"O dinheiro pode ser retirado praticamente a qualquer momento.",IF(AND($H15="PREV_REGR",IN_PRAZO>=120),"No prazo escolhido a previdência alcança a menor alíquota de imposto (10%).",IF($D15>=4,"Pode render mais no prazo longo, aceitando oscilação pelo caminho.","Combina com o prazo, a liquidez e a prioridade informados."))))))))) -> Não paga Imposto de Renda para pessoa física. | U15: =IF($B15="","",IF($E15>0,"Carência de "&$E15&" dias: não dá para resgatar antes.",IF($F15>60,"Não é dinheiro rápido: leva meses para virar caixa.",IF(LEFT($H15,4)="PREV",IF(IN_PRAZO<24,"Resgate antes de 2 anos paga 35% de imposto.","Não tem cobertura do FGC: quem responde pelo dinheiro é a seguradora."),IF($D15>=4,"Pode cair no caminho e demorar a se recuperar.",IF(AND($H15="RF_REGR",$X15>=0.03),"Se vender antes do vencimento, o preço pode estar abaixo do que você pagou.",IF($X15>=0.03,"O valor oscila mês a mês: em prazo curto pode estar abaixo do que você aplicou.",IF($H15="FUNDO_LP","Tem come-cotas em maio e novembro, que antecipam parte do imposto.",IF($F15>7,"Para o dinheiro cair na conta leva cerca de "&$F15&" dias.",IF($I15>=0.015,"Taxa de administração alta em relação ao retorno esperado.","Confirme prazo, liquidez e tributação antes de contratar.")))))))))) -> Carência de 270 dias: não dá para resgatar antes. | V15: =IF($B15="","",IFERROR(IF(Produtos!$H15="MULT",(1+INDEX(TAB_MACRO_VAL,MATCH(Produtos!$E15,TAB_MACRO_COD,0))*Produtos!$F15)*(1+Produtos!$G15)-1,INDEX(TAB_MACRO_VAL,MATCH(Produtos!$E15,TAB_MACRO_COD,0))*Produtos!$F15+Produtos!$G15),"")) -> 0.09919 | W15: =IF(Produtos!$B15="","",Produtos!$E15) -> CDI | X15: =IF(Produtos!$B15="",0,Produtos!$U15) -> 0.001
A16: =IF(Produtos!$B16="","",Produtos!$A16) -> RF08 | B16: =IF(Produtos!$B16="","",Produtos!$B16) -> Tesouro Selic 2031 | C16: =IF(Produtos!$B16="","",Produtos!$C16) -> Renda Fixa | D16: =IF(Produtos!$B16="",0,Produtos!$T16) -> 1 | E16: =IF(Produtos!$B16="",0,Produtos!$P16) -> 0 | F16: =IF(Produtos!$B16="",0,Produtos!$Q16) -> 1 | G16: =IF(Produtos!$B16="",0,Produtos!$R16) -> 100 | H16: =IF(Produtos!$B16="","",Produtos!$N16) -> RF_REGR | I16: =IF(Produtos!$B16="",0,Produtos!$I16) -> 0 | J16: =IF(Produtos!$B16="","NÃO",Produtos!$AD16) -> SIM | K16: =IF(AND($B16<>"",IN_CAPITAL>=$G16),1,0) -> 1 | L16: =IF(AND($B16<>"",$D16<=IFERROR(INDEX(Premissas!$B$102:$B$104,MATCH(IN_PERFIL,Premissas!$A$102:$A$104,0)),5)),1,0) -> 1 | M16: =IF(IN_PRAZO*30<$E16,0,IF($D16>=4,IF(IN_PRAZO>=60,100,IF(IN_PRAZO>=36,60,IF(IN_PRAZO>=24,30,0))),IF($D16=3,IF(IN_PRAZO>=24,100,IF(IN_PRAZO>=12,70,40)),100))) -> 100 | N16: =IF(IN_RESGATE="Sim",IF($E16+$F16<=3,100,IF($E16+$F16<=31,50,0)),IF(IN_RESGATE="Talvez",IF($E16+$F16<=90,100,IF($E16+$F16<=360,50,20)),100)) -> 100 | O16: =IF($D16=0,0,IFERROR(INDEX($B$98:$F$101,MATCH(IN_PRIORIDADE,$A$98:$A$101,0),$D16),0)) -> 60 | P16: =MAX(0,MIN(100,60+IF($H16="ISENTO",25,0)+IF($I16<=0.005,15,IF($I16>=0.015,-15,0))+IF(AND($H16="PREV_REGR",IN_PRAZO>=120),20,0)+IF(AND($H16="FUNDO_LP",IN_PRAZO<=12),-10,0)+IF(AND($H16="FUNDO_CP",IN_PRAZO>=24),-15,0))) -> 75 | Q16: =IF(OR($B16="",$J16<>"SIM",$K16=0,$L16=0),0,ROUND(($M16*$B$7+$N16*$C$7+$O16*$D$7+$P16*$E$7)/MAX(1,$B$7+$C$7+$D$7+$E$7),1)) -> 82.3 | R16: =IF($H16="IMOVEL",0,$Q16+ROW()/1000000) -> 82.300016 | S16: =IF($B16="","",IF($Q16=0,"Não indicado agora",IF($Q16>=75,"Pode fazer sentido",IF($Q16>=50,"Talvez faça sentido","Provavelmente não é o mais indicado")))) -> Pode fazer sentido | T16: =IF($B16="","",IF($Q16=0,IF($K16=0,"O valor disponível é menor que a aplicação mínima deste produto.",IF($L16=0,"O risco deste produto está acima do perfil declarado pelo cliente.","Produto não está ativo na base.")),IF($Q16<50,"Encaixa pouco no que foi pedido — veja o ponto de atenção ao lado.",IF($H16="ISENTO","Não paga Imposto de Renda para pessoa física.",IF($W16="PRE","A taxa fica travada na contratação: não cai se os juros da economia caírem.",IF($W16="IPCA","Protege o poder de compra: rende a inflação mais uma taxa fixa por cima.",IF(AND($E16=0,$F16<=1),"O dinheiro pode ser retirado praticamente a qualquer momento.",IF(AND($H16="PREV_REGR",IN_PRAZO>=120),"No prazo escolhido a previdência alcança a menor alíquota de imposto (10%).",IF($D16>=4,"Pode render mais no prazo longo, aceitando oscilação pelo caminho.","Combina com o prazo, a liquidez e a prioridade informados."))))))))) -> O dinheiro pode ser retirado praticamente a qualquer momento. | U16: =IF($B16="","",IF($E16>0,"Carência de "&$E16&" dias: não dá para resgatar antes.",IF($F16>60,"Não é dinheiro rápido: leva meses para virar caixa.",IF(LEFT($H16,4)="PREV",IF(IN_PRAZO<24,"Resgate antes de 2 anos paga 35% de imposto.","Não tem cobertura do FGC: quem responde pelo dinheiro é a seguradora."),IF($D16>=4,"Pode cair no caminho e demorar a se recuperar.",IF(AND($H16="RF_REGR",$X16>=0.03),"Se vender antes do vencimento, o preço pode estar abaixo do que você pagou.",IF($X16>=0.03,"O valor oscila mês a mês: em prazo curto pode estar abaixo do que você aplicou.",IF($H16="FUNDO_LP","Tem come-cotas em maio e novembro, que antecipam parte do imposto.",IF($F16>7,"Para o dinheiro cair na conta leva cerca de "&$F16&" dias.",IF($I16>=0.015,"Taxa de administração alta em relação ao retorno esperado.","Confirme prazo, liquidez e tributação antes de contratar.")))))))))) -> Confirme prazo, liquidez e tributação antes de contratar. | V16: =IF($B16="","",IFERROR(IF(Produtos!$H16="MULT",(1+INDEX(TAB_MACRO_VAL,MATCH(Produtos!$E16,TAB_MACRO_COD,0))*Produtos!$F16)*(1+Produtos!$G16)-1,INDEX(TAB_MACRO_VAL,MATCH(Produtos!$E16,TAB_MACRO_COD,0))*Produtos!$F16+Produtos!$G16),"")) -> 0.1102 | W16: =IF(Produtos!$B16="","",Produtos!$E16) -> SELIC | X16: =IF(Produtos!$B16="",0,Produtos!$U16) -> 0.002
A17: =IF(Produtos!$B17="","",Produtos!$A17) -> RF09 | B17: =IF(Produtos!$B17="","",Produtos!$B17) -> Tesouro IPCA+ 2035 | C17: =IF(Produtos!$B17="","",Produtos!$C17) -> Renda Fixa | D17: =IF(Produtos!$B17="",0,Produtos!$T17) -> 2 | E17: =IF(Produtos!$B17="",0,Produtos!$P17) -> 0 | F17: =IF(Produtos!$B17="",0,Produtos!$Q17) -> 1 | G17: =IF(Produtos!$B17="",0,Produtos!$R17) -> 100 | H17: =IF(Produtos!$B17="","",Produtos!$N17) -> RF_REGR | I17: =IF(Produtos!$B17="",0,Produtos!$I17) -> 0 | J17: =IF(Produtos!$B17="","NÃO",Produtos!$AD17) -> SIM | K17: =IF(AND($B17<>"",IN_CAPITAL>=$G17),1,0) -> 1 | L17: =IF(AND($B17<>"",$D17<=IFERROR(INDEX(Premissas!$B$102:$B$104,MATCH(IN_PERFIL,Premissas!$A$102:$A$104,0)),5)),1,0) -> 1 | M17: =IF(IN_PRAZO*30<$E17,0,IF($D17>=4,IF(IN_PRAZO>=60,100,IF(IN_PRAZO>=36,60,IF(IN_PRAZO>=24,30,0))),IF($D17=3,IF(IN_PRAZO>=24,100,IF(IN_PRAZO>=12,70,40)),100))) -> 100 | N17: =IF(IN_RESGATE="Sim",IF($E17+$F17<=3,100,IF($E17+$F17<=31,50,0)),IF(IN_RESGATE="Talvez",IF($E17+$F17<=90,100,IF($E17+$F17<=360,50,20)),100)) -> 100 | O17: =IF($D17=0,0,IFERROR(INDEX($B$98:$F$101,MATCH(IN_PRIORIDADE,$A$98:$A$101,0),$D17),0)) -> 100 | P17: =MAX(0,MIN(100,60+IF($H17="ISENTO",25,0)+IF($I17<=0.005,15,IF($I17>=0.015,-15,0))+IF(AND($H17="PREV_REGR",IN_PRAZO>=120),20,0)+IF(AND($H17="FUNDO_LP",IN_PRAZO<=12),-10,0)+IF(AND($H17="FUNDO_CP",IN_PRAZO>=24),-15,0))) -> 75 | Q17: =IF(OR($B17="",$J17<>"SIM",$K17=0,$L17=0),0,ROUND(($M17*$B$7+$N17*$C$7+$O17*$D$7+$P17*$E$7)/MAX(1,$B$7+$C$7+$D$7+$E$7),1)) -> 96.3 | R17: =IF($H17="IMOVEL",0,$Q17+ROW()/1000000) -> 96.300017 | S17: =IF($B17="","",IF($Q17=0,"Não indicado agora",IF($Q17>=75,"Pode fazer sentido",IF($Q17>=50,"Talvez faça sentido","Provavelmente não é o mais indicado")))) -> Pode fazer sentido | T17: =IF($B17="","",IF($Q17=0,IF($K17=0,"O valor disponível é menor que a aplicação mínima deste produto.",IF($L17=0,"O risco deste produto está acima do perfil declarado pelo cliente.","Produto não está ativo na base.")),IF($Q17<50,"Encaixa pouco no que foi pedido — veja o ponto de atenção ao lado.",IF($H17="ISENTO","Não paga Imposto de Renda para pessoa física.",IF($W17="PRE","A taxa fica travada na contratação: não cai se os juros da economia caírem.",IF($W17="IPCA","Protege o poder de compra: rende a inflação mais uma taxa fixa por cima.",IF(AND($E17=0,$F17<=1),"O dinheiro pode ser retirado praticamente a qualquer momento.",IF(AND($H17="PREV_REGR",IN_PRAZO>=120),"No prazo escolhido a previdência alcança a menor alíquota de imposto (10%).",IF($D17>=4,"Pode render mais no prazo longo, aceitando oscilação pelo caminho.","Combina com o prazo, a liquidez e a prioridade informados."))))))))) -> Protege o poder de compra: rende a inflação mais uma taxa fixa por cima. | U17: =IF($B17="","",IF($E17>0,"Carência de "&$E17&" dias: não dá para resgatar antes.",IF($F17>60,"Não é dinheiro rápido: leva meses para virar caixa.",IF(LEFT($H17,4)="PREV",IF(IN_PRAZO<24,"Resgate antes de 2 anos paga 35% de imposto.","Não tem cobertura do FGC: quem responde pelo dinheiro é a seguradora."),IF($D17>=4,"Pode cair no caminho e demorar a se recuperar.",IF(AND($H17="RF_REGR",$X17>=0.03),"Se vender antes do vencimento, o preço pode estar abaixo do que você pagou.",IF($X17>=0.03,"O valor oscila mês a mês: em prazo curto pode estar abaixo do que você aplicou.",IF($H17="FUNDO_LP","Tem come-cotas em maio e novembro, que antecipam parte do imposto.",IF($F17>7,"Para o dinheiro cair na conta leva cerca de "&$F17&" dias.",IF($I17>=0.015,"Taxa de administração alta em relação ao retorno esperado.","Confirme prazo, liquidez e tributação antes de contratar.")))))))))) -> Se vender antes do vencimento, o preço pode estar abaixo do que você pagou. | V17: =IF($B17="","",IFERROR(IF(Produtos!$H17="MULT",(1+INDEX(TAB_MACRO_VAL,MATCH(Produtos!$E17,TAB_MACRO_COD,0))*Produtos!$F17)*(1+Produtos!$G17)-1,INDEX(TAB_MACRO_VAL,MATCH(Produtos!$E17,TAB_MACRO_COD,0))*Produtos!$F17+Produtos!$G17),"")) -> 0.1024 | W17: =IF(Produtos!$B17="","",Produtos!$E17) -> IPCA | X17: =IF(Produtos!$B17="",0,Produtos!$U17) -> 0.08
A18: =IF(Produtos!$B18="","",Produtos!$A18) -> RF10 | B18: =IF(Produtos!$B18="","",Produtos!$B18) -> Tesouro Prefixado 2031 | C18: =IF(Produtos!$B18="","",Produtos!$C18) -> Renda Fixa | D18: =IF(Produtos!$B18="",0,Produtos!$T18) -> 2 | E18: =IF(Produtos!$B18="",0,Produtos!$P18) -> 0 | F18: =IF(Produtos!$B18="",0,Produtos!$Q18) -> 1 | G18: =IF(Produtos!$B18="",0,Produtos!$R18) -> 100 | H18: =IF(Produtos!$B18="","",Produtos!$N18) -> RF_REGR | I18: =IF(Produtos!$B18="",0,Produtos!$I18) -> 0 | J18: =IF(Produtos!$B18="","NÃO",Produtos!$AD18) -> SIM | K18: =IF(AND($B18<>"",IN_CAPITAL>=$G18),1,0) -> 1 | L18: =IF(AND($B18<>"",$D18<=IFERROR(INDEX(Premissas!$B$102:$B$104,MATCH(IN_PERFIL,Premissas!$A$102:$A$104,0)),5)),1,0) -> 1 | M18: =IF(IN_PRAZO*30<$E18,0,IF($D18>=4,IF(IN_PRAZO>=60,100,IF(IN_PRAZO>=36,60,IF(IN_PRAZO>=24,30,0))),IF($D18=3,IF(IN_PRAZO>=24,100,IF(IN_PRAZO>=12,70,40)),100))) -> 100 | N18: =IF(IN_RESGATE="Sim",IF($E18+$F18<=3,100,IF($E18+$F18<=31,50,0)),IF(IN_RESGATE="Talvez",IF($E18+$F18<=90,100,IF($E18+$F18<=360,50,20)),100)) -> 100 | O18: =IF($D18=0,0,IFERROR(INDEX($B$98:$F$101,MATCH(IN_PRIORIDADE,$A$98:$A$101,0),$D18),0)) -> 100 | P18: =MAX(0,MIN(100,60+IF($H18="ISENTO",25,0)+IF($I18<=0.005,15,IF($I18>=0.015,-15,0))+IF(AND($H18="PREV_REGR",IN_PRAZO>=120),20,0)+IF(AND($H18="FUNDO_LP",IN_PRAZO<=12),-10,0)+IF(AND($H18="FUNDO_CP",IN_PRAZO>=24),-15,0))) -> 75 | Q18: =IF(OR($B18="",$J18<>"SIM",$K18=0,$L18=0),0,ROUND(($M18*$B$7+$N18*$C$7+$O18*$D$7+$P18*$E$7)/MAX(1,$B$7+$C$7+$D$7+$E$7),1)) -> 96.3 | R18: =IF($H18="IMOVEL",0,$Q18+ROW()/1000000) -> 96.300018 | S18: =IF($B18="","",IF($Q18=0,"Não indicado agora",IF($Q18>=75,"Pode fazer sentido",IF($Q18>=50,"Talvez faça sentido","Provavelmente não é o mais indicado")))) -> Pode fazer sentido | T18: =IF($B18="","",IF($Q18=0,IF($K18=0,"O valor disponível é menor que a aplicação mínima deste produto.",IF($L18=0,"O risco deste produto está acima do perfil declarado pelo cliente.","Produto não está ativo na base.")),IF($Q18<50,"Encaixa pouco no que foi pedido — veja o ponto de atenção ao lado.",IF($H18="ISENTO","Não paga Imposto de Renda para pessoa física.",IF($W18="PRE","A taxa fica travada na contratação: não cai se os juros da economia caírem.",IF($W18="IPCA","Protege o poder de compra: rende a inflação mais uma taxa fixa por cima.",IF(AND($E18=0,$F18<=1),"O dinheiro pode ser retirado praticamente a qualquer momento.",IF(AND($H18="PREV_REGR",IN_PRAZO>=120),"No prazo escolhido a previdência alcança a menor alíquota de imposto (10%).",IF($D18>=4,"Pode render mais no prazo longo, aceitando oscilação pelo caminho.","Combina com o prazo, a liquidez e a prioridade informados."))))))))) -> A taxa fica travada na contratação: não cai se os juros da economia caírem. | U18: =IF($B18="","",IF($E18>0,"Carência de "&$E18&" dias: não dá para resgatar antes.",IF($F18>60,"Não é dinheiro rápido: leva meses para virar caixa.",IF(LEFT($H18,4)="PREV",IF(IN_PRAZO<24,"Resgate antes de 2 anos paga 35% de imposto.","Não tem cobertura do FGC: quem responde pelo dinheiro é a seguradora."),IF($D18>=4,"Pode cair no caminho e demorar a se recuperar.",IF(AND($H18="RF_REGR",$X18>=0.03),"Se vender antes do vencimento, o preço pode estar abaixo do que você pagou.",IF($X18>=0.03,"O valor oscila mês a mês: em prazo curto pode estar abaixo do que você aplicou.",IF($H18="FUNDO_LP","Tem come-cotas em maio e novembro, que antecipam parte do imposto.",IF($F18>7,"Para o dinheiro cair na conta leva cerca de "&$F18&" dias.",IF($I18>=0.015,"Taxa de administração alta em relação ao retorno esperado.","Confirme prazo, liquidez e tributação antes de contratar.")))))))))) -> Se vender antes do vencimento, o preço pode estar abaixo do que você pagou. | V18: =IF($B18="","",IFERROR(IF(Produtos!$H18="MULT",(1+INDEX(TAB_MACRO_VAL,MATCH(Produtos!$E18,TAB_MACRO_COD,0))*Produtos!$F18)*(1+Produtos!$G18)-1,INDEX(TAB_MACRO_VAL,MATCH(Produtos!$E18,TAB_MACRO_COD,0))*Produtos!$F18+Produtos!$G18),"")) -> 0.12 | W18: =IF(Produtos!$B18="","",Produtos!$E18) -> PRE | X18: =IF(Produtos!$B18="",0,Produtos!$U18) -> 0.06
A19: =IF(Produtos!$B19="","",Produtos!$A19) -> FU01 | B19: =IF(Produtos!$B19="","",Produtos!$B19) -> Fundo CAIXA RF Simples | C19: =IF(Produtos!$B19="","",Produtos!$C19) -> Fundo | D19: =IF(Produtos!$B19="",0,Produtos!$T19) -> 1 | E19: =IF(Produtos!$B19="",0,Produtos!$P19) -> 0 | F19: =IF(Produtos!$B19="",0,Produtos!$Q19) -> 0 | G19: =IF(Produtos!$B19="",0,Produtos!$R19) -> 100 | H19: =IF(Produtos!$B19="","",Produtos!$N19) -> FUNDO_LP | I19: =IF(Produtos!$B19="",0,Produtos!$I19) -> 0.004 | J19: =IF(Produtos!$B19="","NÃO",Produtos!$AD19) -> SIM | K19: =IF(AND($B19<>"",IN_CAPITAL>=$G19),1,0) -> 1 | L19: =IF(AND($B19<>"",$D19<=IFERROR(INDEX(Premissas!$B$102:$B$104,MATCH(IN_PERFIL,Premissas!$A$102:$A$104,0)),5)),1,0) -> 1 | M19: =IF(IN_PRAZO*30<$E19,0,IF($D19>=4,IF(IN_PRAZO>=60,100,IF(IN_PRAZO>=36,60,IF(IN_PRAZO>=24,30,0))),IF($D19=3,IF(IN_PRAZO>=24,100,IF(IN_PRAZO>=12,70,40)),100))) -> 100 | N19: =IF(IN_RESGATE="Sim",IF($E19+$F19<=3,100,IF($E19+$F19<=31,50,0)),IF(IN_RESGATE="Talvez",IF($E19+$F19<=90,100,IF($E19+$F19<=360,50,20)),100)) -> 100 | O19: =IF($D19=0,0,IFERROR(INDEX($B$98:$F$101,MATCH(IN_PRIORIDADE,$A$98:$A$101,0),$D19),0)) -> 60 | P19: =MAX(0,MIN(100,60+IF($H19="ISENTO",25,0)+IF($I19<=0.005,15,IF($I19>=0.015,-15,0))+IF(AND($H19="PREV_REGR",IN_PRAZO>=120),20,0)+IF(AND($H19="FUNDO_LP",IN_PRAZO<=12),-10,0)+IF(AND($H19="FUNDO_CP",IN_PRAZO>=24),-15,0))) -> 75 | Q19: =IF(OR($B19="",$J19<>"SIM",$K19=0,$L19=0),0,ROUND(($M19*$B$7+$N19*$C$7+$O19*$D$7+$P19*$E$7)/MAX(1,$B$7+$C$7+$D$7+$E$7),1)) -> 82.3 | R19: =IF($H19="IMOVEL",0,$Q19+ROW()/1000000) -> 82.300019 | S19: =IF($B19="","",IF($Q19=0,"Não indicado agora",IF($Q19>=75,"Pode fazer sentido",IF($Q19>=50,"Talvez faça sentido","Provavelmente não é o mais indicado")))) -> Pode fazer sentido | T19: =IF($B19="","",IF($Q19=0,IF($K19=0,"O valor disponível é menor que a aplicação mínima deste produto.",IF($L19=0,"O risco deste produto está acima do perfil declarado pelo cliente.","Produto não está ativo na base.")),IF($Q19<50,"Encaixa pouco no que foi pedido — veja o ponto de atenção ao lado.",IF($H19="ISENTO","Não paga Imposto de Renda para pessoa física.",IF($W19="PRE","A taxa fica travada na contratação: não cai se os juros da economia caírem.",IF($W19="IPCA","Protege o poder de compra: rende a inflação mais uma taxa fixa por cima.",IF(AND($E19=0,$F19<=1),"O dinheiro pode ser retirado praticamente a qualquer momento.",IF(AND($H19="PREV_REGR",IN_PRAZO>=120),"No prazo escolhido a previdência alcança a menor alíquota de imposto (10%).",IF($D19>=4,"Pode render mais no prazo longo, aceitando oscilação pelo caminho.","Combina com o prazo, a liquidez e a prioridade informados."))))))))) -> O dinheiro pode ser retirado praticamente a qualquer momento. | U19: =IF($B19="","",IF($E19>0,"Carência de "&$E19&" dias: não dá para resgatar antes.",IF($F19>60,"Não é dinheiro rápido: leva meses para virar caixa.",IF(LEFT($H19,4)="PREV",IF(IN_PRAZO<24,"Resgate antes de 2 anos paga 35% de imposto.","Não tem cobertura do FGC: quem responde pelo dinheiro é a seguradora."),IF($D19>=4,"Pode cair no caminho e demorar a se recuperar.",IF(AND($H19="RF_REGR",$X19>=0.03),"Se vender antes do vencimento, o preço pode estar abaixo do que você pagou.",IF($X19>=0.03,"O valor oscila mês a mês: em prazo curto pode estar abaixo do que você aplicou.",IF($H19="FUNDO_LP","Tem come-cotas em maio e novembro, que antecipam parte do imposto.",IF($F19>7,"Para o dinheiro cair na conta leva cerca de "&$F19&" dias.",IF($I19>=0.015,"Taxa de administração alta em relação ao retorno esperado.","Confirme prazo, liquidez e tributação antes de contratar.")))))))))) -> Tem come-cotas em maio e novembro, que antecipam parte do imposto. | V19: =IF($B19="","",IFERROR(IF(Produtos!$H19="MULT",(1+INDEX(TAB_MACRO_VAL,MATCH(Produtos!$E19,TAB_MACRO_COD,0))*Produtos!$F19)*(1+Produtos!$G19)-1,INDEX(TAB_MACRO_VAL,MATCH(Produtos!$E19,TAB_MACRO_COD,0))*Produtos!$F19+Produtos!$G19),"")) -> 0.109 | W19: =IF(Produtos!$B19="","",Produtos!$E19) -> CDI | X19: =IF(Produtos!$B19="",0,Produtos!$U19) -> 0.002
A20: =IF(Produtos!$B20="","",Produtos!$A20) -> FU02 | B20: =IF(Produtos!$B20="","",Produtos!$B20) -> Fundo CAIXA RF Referenciado DI LP | C20: =IF(Produtos!$B20="","",Produtos!$C20) -> Fundo | D20: =IF(Produtos!$B20="",0,Produtos!$T20) -> 1 | E20: =IF(Produtos!$B20="",0,Produtos!$P20) -> 0 | F20: =IF(Produtos!$B20="",0,Produtos!$Q20) -> 0 | G20: =IF(Produtos!$B20="",0,Produtos!$R20) -> 1000 | H20: =IF(Produtos!$B20="","",Produtos!$N20) -> FUNDO_LP | I20: =IF(Produtos!$B20="",0,Produtos!$I20) -> 0.008 | J20: =IF(Produtos!$B20="","NÃO",Produtos!$AD20) -> SIM | K20: =IF(AND($B20<>"",IN_CAPITAL>=$G20),1,0) -> 1 | L20: =IF(AND($B20<>"",$D20<=IFERROR(INDEX(Premissas!$B$102:$B$104,MATCH(IN_PERFIL,Premissas!$A$102:$A$104,0)),5)),1,0) -> 1 | M20: =IF(IN_PRAZO*30<$E20,0,IF($D20>=4,IF(IN_PRAZO>=60,100,IF(IN_PRAZO>=36,60,IF(IN_PRAZO>=24,30,0))),IF($D20=3,IF(IN_PRAZO>=24,100,IF(IN_PRAZO>=12,70,40)),100))) -> 100 | N20: =IF(IN_RESGATE="Sim",IF($E20+$F20<=3,100,IF($E20+$F20<=31,50,0)),IF(IN_RESGATE="Talvez",IF($E20+$F20<=90,100,IF($E20+$F20<=360,50,20)),100)) -> 100 | O20: =IF($D20=0,0,IFERROR(INDEX($B$98:$F$101,MATCH(IN_PRIORIDADE,$A$98:$A$101,0),$D20),0)) -> 60 | P20: =MAX(0,MIN(100,60+IF($H20="ISENTO",25,0)+IF($I20<=0.005,15,IF($I20>=0.015,-15,0))+IF(AND($H20="PREV_REGR",IN_PRAZO>=120),20,0)+IF(AND($H20="FUNDO_LP",IN_PRAZO<=12),-10,0)+IF(AND($H20="FUNDO_CP",IN_PRAZO>=24),-15,0))) -> 60 | Q20: =IF(OR($B20="",$J20<>"SIM",$K20=0,$L20=0),0,ROUND(($M20*$B$7+$N20*$C$7+$O20*$D$7+$P20*$E$7)/MAX(1,$B$7+$C$7+$D$7+$E$7),1)) -> 80 | R20: =IF($H20="IMOVEL",0,$Q20+ROW()/1000000) -> 80.00002 | S20: =IF($B20="","",IF($Q20=0,"Não indicado agora",IF($Q20>=75,"Pode fazer sentido",IF($Q20>=50,"Talvez faça sentido","Provavelmente não é o mais indicado")))) -> Pode fazer sentido | T20: =IF($B20="","",IF($Q20=0,IF($K20=0,"O valor disponível é menor que a aplicação mínima deste produto.",IF($L20=0,"O risco deste produto está acima do perfil declarado pelo cliente.","Produto não está ativo na base.")),IF($Q20<50,"Encaixa pouco no que foi pedido — veja o ponto de atenção ao lado.",IF($H20="ISENTO","Não paga Imposto de Renda para pessoa física.",IF($W20="PRE","A taxa fica travada na contratação: não cai se os juros da economia caírem.",IF($W20="IPCA","Protege o poder de compra: rende a inflação mais uma taxa fixa por cima.",IF(AND($E20=0,$F20<=1),"O dinheiro pode ser retirado praticamente a qualquer momento.",IF(AND($H20="PREV_REGR",IN_PRAZO>=120),"No prazo escolhido a previdência alcança a menor alíquota de imposto (10%).",IF($D20>=4,"Pode render mais no prazo longo, aceitando oscilação pelo caminho.","Combina com o prazo, a liquidez e a prioridade informados."))))))))) -> O dinheiro pode ser retirado praticamente a qualquer momento. | U20: =IF($B20="","",IF($E20>0,"Carência de "&$E20&" dias: não dá para resgatar antes.",IF($F20>60,"Não é dinheiro rápido: leva meses para virar caixa.",IF(LEFT($H20,4)="PREV",IF(IN_PRAZO<24,"Resgate antes de 2 anos paga 35% de imposto.","Não tem cobertura do FGC: quem responde pelo dinheiro é a seguradora."),IF($D20>=4,"Pode cair no caminho e demorar a se recuperar.",IF(AND($H20="RF_REGR",$X20>=0.03),"Se vender antes do vencimento, o preço pode estar abaixo do que você pagou.",IF($X20>=0.03,"O valor oscila mês a mês: em prazo curto pode estar abaixo do que você aplicou.",IF($H20="FUNDO_LP","Tem come-cotas em maio e novembro, que antecipam parte do imposto.",IF($F20>7,"Para o dinheiro cair na conta leva cerca de "&$F20&" dias.",IF($I20>=0.015,"Taxa de administração alta em relação ao retorno esperado.","Confirme prazo, liquidez e tributação antes de contratar.")))))))))) -> Tem come-cotas em maio e novembro, que antecipam parte do imposto. | V20: =IF($B20="","",IFERROR(IF(Produtos!$H20="MULT",(1+INDEX(TAB_MACRO_VAL,MATCH(Produtos!$E20,TAB_MACRO_COD,0))*Produtos!$F20)*(1+Produtos!$G20)-1,INDEX(TAB_MACRO_VAL,MATCH(Produtos!$E20,TAB_MACRO_COD,0))*Produtos!$F20+Produtos!$G20),"")) -> 0.109 | W20: =IF(Produtos!$B20="","",Produtos!$E20) -> CDI | X20: =IF(Produtos!$B20="",0,Produtos!$U20) -> 0.002
... A78: =IF(Produtos!$B78="","",Produtos!$A78) | B78: =IF(Produtos!$B78="","",Produtos!$B78) | C78: =IF(Produtos!$B78="","",Produtos!$C78) | D78: =IF(Produtos!$B78="",0,Produtos!$T78) -> 0 | E78: =IF(Produtos!$B78="",0,Produtos!$P78) -> 0 | F78: =IF(Produtos!$B78="",0,Produtos!$Q78) -> 0 | G78: =IF(Produtos!$B78="",0,Produtos!$R78) -> 0 | H78: =IF(Produtos!$B78="","",Produtos!$N78) | I78: =IF(Produtos!$B78="",0,Produtos!$I78) -> 0 | J78: =IF(Produtos!$B78="","NÃO",Produtos!$AD78) -> NÃO | K78: =IF(AND($B78<>"",IN_CAPITAL>=$G78),1,0) -> 0 | L78: =IF(AND($B78<>"",$D78<=IFERROR(INDEX(Premissas!$B$102:$B$104,MATCH(IN_PERFIL,Premissas!$A$102:$A$104,0)),5)),1,0) -> 0 | M78: =IF(IN_PRAZO*30<$E78,0,IF($D78>=4,IF(IN_PRAZO>=60,100,IF(IN_PRAZO>=36,60,IF(IN_PRAZO>=24,30,0))),IF($D78=3,IF(IN_PRAZO>=24,100,IF(IN_PRAZO>=12,70,40)),100))) -> 100 | N78: =IF(IN_RESGATE="Sim",IF($E78+$F78<=3,100,IF($E78+$F78<=31,50,0)),IF(IN_RESGATE="Talvez",IF($E78+$F78<=90,100,IF($E78+$F78<=360,50,20)),100)) -> 100 | O78: =IF($D78=0,0,IFERROR(INDEX($B$98:$F$101,MATCH(IN_PRIORIDADE,$A$98:$A$101,0),$D78),0)) -> 0 | P78: =MAX(0,MIN(100,60+IF($H78="ISENTO",25,0)+IF($I78<=0.005,15,IF($I78>=0.015,-15,0))+IF(AND($H78="PREV_REGR",IN_PRAZO>=120),20,0)+IF(AND($H78="FUNDO_LP",IN_PRAZO<=12),-10,0)+IF(AND($H78="FUNDO_CP",IN_PRAZO>=24),-15,0))) -> 75 | Q78: =IF(OR($B78="",$J78<>"SIM",$K78=0,$L78=0),0,ROUND(($M78*$B$7+$N78*$C$7+$O78*$D$7+$P78*$E$7)/MAX(1,$B$7+$C$7+$D$7+$E$7),1)) -> 0 | R78: =IF($H78="IMOVEL",0,$Q78+ROW()/1000000) -> 7.8e-05 | S78: =IF($B78="","",IF($Q78=0,"Não indicado agora",IF($Q78>=75,"Pode fazer sentido",IF($Q78>=50,"Talvez faça sentido","Provavelmente não é o mais indicado")))) | T78: =IF($B78="","",IF($Q78=0,IF($K78=0,"O valor disponível é menor que a aplicação mínima deste produto.",IF($L78=0,"O risco deste produto está acima do perfil declarado pelo cliente.","Produto não está ativo na base.")),IF($Q78<50,"Encaixa pouco no que foi pedido — veja o ponto de atenção ao lado.",IF($H78="ISENTO","Não paga Imposto de Renda para pessoa física.",IF($W78="PRE","A taxa fica travada na contratação: não cai se os juros da economia caírem.",IF($W78="IPCA","Protege o poder de compra: rende a inflação mais uma taxa fixa por cima.",IF(AND($E78=0,$F78<=1),"O dinheiro pode ser retirado praticamente a qualquer momento.",IF(AND($H78="PREV_REGR",IN_PRAZO>=120),"No prazo escolhido a previdência alcança a menor alíquota de imposto (10%).",IF($D78>=4,"Pode render mais no prazo longo, aceitando oscilação pelo caminho.","Combina com o prazo, a liquidez e a prioridade informados."))))))))) | U78: =IF($B78="","",IF($E78>0,"Carência de "&$E78&" dias: não dá para resgatar antes.",IF($F78>60,"Não é dinheiro rápido: leva meses para virar caixa.",IF(LEFT($H78,4)="PREV",IF(IN_PRAZO<24,"Resgate antes de 2 anos paga 35% de imposto.","Não tem cobertura do FGC: quem responde pelo dinheiro é a seguradora."),IF($D78>=4,"Pode cair no caminho e demorar a se recuperar.",IF(AND($H78="RF_REGR",$X78>=0.03),"Se vender antes do vencimento, o preço pode estar abaixo do que você pagou.",IF($X78>=0.03,"O valor oscila mês a mês: em prazo curto pode estar abaixo do que você aplicou.",IF($H78="FUNDO_LP","Tem come-cotas em maio e novembro, que antecipam parte do imposto.",IF($F78>7,"Para o dinheiro cair na conta leva cerca de "&$F78&" dias.",IF($I78>=0.015,"Taxa de administração alta em relação ao retorno esperado.","Confirme prazo, liquidez e tributação antes de contratar.")))))))))) | V78: =IF($B78="","",IFERROR(IF(Produtos!$H78="MULT",(1+INDEX(TAB_MACRO_VAL,MATCH(Produtos!$E78,TAB_MACRO_COD,0))*Produtos!$F78)*(1+Produtos!$G78)-1,INDEX(TAB_MACRO_VAL,MATCH(Produtos!$E78,TAB_MACRO_COD,0))*Produtos!$F78+Produtos!$G78),"")) | W78: =IF(Produtos!$B78="","",Produtos!$E78) | X78: =IF(Produtos!$B78="",0,Produtos!$U78) -> 0
A80: ORDEM DE ADERÊNCIA — o que a planilha sugere colocar na comparação
A81: Posição | B81: Produto sugerido | C81: Aderência | D81: Classificação | E81: Por que | F81: Ponto de atenção
A82: 1 | B82: =IFERROR(IF(LARGE($R$9:$R$78,1)<1,"",INDEX($B$9:$B$78,MATCH(LARGE($R$9:$R$78,1),$R$9:$R$78,0))),"") -> Tesouro Prefixado 2031 | C82: =IFERROR(IF(LARGE($R$9:$R$78,1)<1,"",INDEX($Q$9:$Q$78,MATCH(LARGE($R$9:$R$78,1),$R$9:$R$78,0))),"") -> 96.3 | D82: =IFERROR(IF(LARGE($R$9:$R$78,1)<1,"",INDEX($S$9:$S$78,MATCH(LARGE($R$9:$R$78,1),$R$9:$R$78,0))),"") -> Pode fazer sentido | E82: =IFERROR(IF(LARGE($R$9:$R$78,1)<1,"",INDEX($T$9:$T$78,MATCH(LARGE($R$9:$R$78,1),$R$9:$R$78,0))),"") -> A taxa fica travada na contratação: não cai se os juros da economia caírem. | F82: =IFERROR(IF(LARGE($R$9:$R$78,1)<1,"",INDEX($U$9:$U$78,MATCH(LARGE($R$9:$R$78,1),$R$9:$R$78,0))),"") -> Se vender antes do vencimento, o preço pode estar abaixo do que você pagou.
A83: 2 | B83: =IFERROR(IF(LARGE($R$9:$R$78,2)<1,"",INDEX($B$9:$B$78,MATCH(LARGE($R$9:$R$78,2),$R$9:$R$78,0))),"") -> Tesouro IPCA+ 2035 | C83: =IFERROR(IF(LARGE($R$9:$R$78,2)<1,"",INDEX($Q$9:$Q$78,MATCH(LARGE($R$9:$R$78,2),$R$9:$R$78,0))),"") -> 96.3 | D83: =IFERROR(IF(LARGE($R$9:$R$78,2)<1,"",INDEX($S$9:$S$78,MATCH(LARGE($R$9:$R$78,2),$R$9:$R$78,0))),"") -> Pode fazer sentido | E83: =IFERROR(IF(LARGE($R$9:$R$78,2)<1,"",INDEX($T$9:$T$78,MATCH(LARGE($R$9:$R$78,2),$R$9:$R$78,0))),"") -> Protege o poder de compra: rende a inflação mais uma taxa fixa por cima. | F83: =IFERROR(IF(LARGE($R$9:$R$78,2)<1,"",INDEX($U$9:$U$78,MATCH(LARGE($R$9:$R$78,2),$R$9:$R$78,0))),"") -> Se vender antes do vencimento, o preço pode estar abaixo do que você pagou.
A84: 3 | B84: =IFERROR(IF(LARGE($R$9:$R$78,3)<1,"",INDEX($B$9:$B$78,MATCH(LARGE($R$9:$R$78,3),$R$9:$R$78,0))),"") -> Fundo CAIXA RF Crédito Privado LP | C84: =IFERROR(IF(LARGE($R$9:$R$78,3)<1,"",INDEX($Q$9:$Q$78,MATCH(LARGE($R$9:$R$78,3),$R$9:$R$78,0))),"") -> 94 | D84: =IFERROR(IF(LARGE($R$9:$R$78,3)<1,"",INDEX($S$9:$S$78,MATCH(LARGE($R$9:$R$78,3),$R$9:$R$78,0))),"") -> Pode fazer sentido | E84: =IFERROR(IF(LARGE($R$9:$R$78,3)<1,"",INDEX($T$9:$T$78,MATCH(LARGE($R$9:$R$78,3),$R$9:$R$78,0))),"") -> Combina com o prazo, a liquidez e a prioridade informados. | F84: =IFERROR(IF(LARGE($R$9:$R$78,3)<1,"",INDEX($U$9:$U$78,MATCH(LARGE($R$9:$R$78,3),$R$9:$R$78,0))),"") -> Tem come-cotas em maio e novembro, que antecipam parte do imposto.
A85: 4 | B85: =IFERROR(IF(LARGE($R$9:$R$78,4)<1,"",INDEX($B$9:$B$78,MATCH(LARGE($R$9:$R$78,4),$R$9:$R$78,0))),"") -> VGBL CAIXA Composto 30 — Regressivo | C85: =IFERROR(IF(LARGE($R$9:$R$78,4)<1,"",INDEX($Q$9:$Q$78,MATCH(LARGE($R$9:$R$78,4),$R$9:$R$78,0))),"") -> 91.3 | D85: =IFERROR(IF(LARGE($R$9:$R$78,4)<1,"",INDEX($S$9:$S$78,MATCH(LARGE($R$9:$R$78,4),$R$9:$R$78,0))),"") -> Pode fazer sentido | E85: =IFERROR(IF(LARGE($R$9:$R$78,4)<1,"",INDEX($T$9:$T$78,MATCH(LARGE($R$9:$R$78,4),$R$9:$R$78,0))),"") -> No prazo escolhido a previdência alcança a menor alíquota de imposto (10%). | F85: =IFERROR(IF(LARGE($R$9:$R$78,4)<1,"",INDEX($U$9:$U$78,MATCH(LARGE($R$9:$R$78,4),$R$9:$R$78,0))),"") -> Não tem cobertura do FGC: quem responde pelo dinheiro é a seguradora.
A86: 5 | B86: =IFERROR(IF(LARGE($R$9:$R$78,5)<1,"",INDEX($B$9:$B$78,MATCH(LARGE($R$9:$R$78,5),$R$9:$R$78,0))),"") -> PGBL CAIXA Composto 30 — Regressivo | C86: =IFERROR(IF(LARGE($R$9:$R$78,5)<1,"",INDEX($Q$9:$Q$78,MATCH(LARGE($R$9:$R$78,5),$R$9:$R$78,0))),"") -> 91.3 | D86: =IFERROR(IF(LARGE($R$9:$R$78,5)<1,"",INDEX($S$9:$S$78,MATCH(LARGE($R$9:$R$78,5),$R$9:$R$78,0))),"") -> Pode fazer sentido | E86: =IFERROR(IF(LARGE($R$9:$R$78,5)<1,"",INDEX($T$9:$T$78,MATCH(LARGE($R$9:$R$78,5),$R$9:$R$78,0))),"") -> No prazo escolhido a previdência alcança a menor alíquota de imposto (10%). | F86: =IFERROR(IF(LARGE($R$9:$R$78,5)<1,"",INDEX($U$9:$U$78,MATCH(LARGE($R$9:$R$78,5),$R$9:$R$78,0))),"") -> Não tem cobertura do FGC: quem responde pelo dinheiro é a seguradora.
A87: 6 | B87: =IFERROR(IF(LARGE($R$9:$R$78,6)<1,"",INDEX($B$9:$B$78,MATCH(LARGE($R$9:$R$78,6),$R$9:$R$78,0))),"") -> Fundo CAIXA RF IPCA Longo Prazo | C87: =IFERROR(IF(LARGE($R$9:$R$78,6)<1,"",INDEX($Q$9:$Q$78,MATCH(LARGE($R$9:$R$78,6),$R$9:$R$78,0))),"") -> 90.5 | D87: =IFERROR(IF(LARGE($R$9:$R$78,6)<1,"",INDEX($S$9:$S$78,MATCH(LARGE($R$9:$R$78,6),$R$9:$R$78,0))),"") -> Pode fazer sentido | E87: =IFERROR(IF(LARGE($R$9:$R$78,6)<1,"",INDEX($T$9:$T$78,MATCH(LARGE($R$9:$R$78,6),$R$9:$R$78,0))),"") -> Protege o poder de compra: rende a inflação mais uma taxa fixa por cima. | F87: =IFERROR(IF(LARGE($R$9:$R$78,6)<1,"",INDEX($U$9:$U$78,MATCH(LARGE($R$9:$R$78,6),$R$9:$R$78,0))),"") -> O valor oscila mês a mês: em prazo curto pode estar abaixo do que você aplicou.
A89: PESOS POR PRIORIDADE DO CLIENTE (edite aqui para calibrar a sugestão)
A90: Prioridade declarada pelo cliente | B90: Peso do prazo | C90: Peso da liquidez | D90: Peso da prioridade | E90: Peso do custo/imposto
A91: Segurança acima de tudo | B91: 20 | C91: 20 | D91: 50 | E91: 10
A92: Equilíbrio entre segurança e rentabilidade | B92: 25 | C92: 25 | D92: 35 | E92: 15
A93: Rentabilidade, aceitando oscilação | B93: 30 | C93: 15 | D93: 40 | E93: 15
A94: Poder retirar a qualquer momento | B94: 15 | C94: 55 | D94: 20 | E94: 10
A96: NOTA DE PRIORIDADE POR NÍVEL DE RISCO (0 a 100)
A97: Prioridade declarada pelo cliente | B97: Risco 1 | C97: Risco 2 | D97: Risco 3 | E97: Risco 4 | F97: Risco 5
A98: Segurança acima de tudo | B98: 100 | C98: 70 | D98: 30 | E98: 5 | F98: 0
A99: Equilíbrio entre segurança e rentabilidade | B99: 60 | C99: 100 | D99: 90 | E99: 45 | F99: 15
A100: Rentabilidade, aceitando oscilação | B100: 30 | C100: 50 | D100: 80 | E100: 100 | F100: 95
A101: Poder retirar a qualquer momento | B101: 100 | C101: 85 | D101: 50 | E101: 20 | F101: 5

Sheet Motor
A1: MOTOR DE SIMULAÇÃO
A2: Camada de cálculo — nenhuma célula desta aba é digitada; tudo vem de Produtos, Premissas e das respostas do cliente
A4: BLOCO 1 · PARÂMETROS RESOLVIDOS DE CADA ALTERNATIVA | L4: ◀ INÍCIO
A5: Parâmetro | B5: ALTERNATIVA A | C5: ALTERNATIVA B | D5: ALTERNATIVA C | E5: ALTERNATIVA D | F5: ALTERNATIVA E | G5: ALTERNATIVA F | L5: ◀ CONSULTOR
A6: Produto selecionado | B6: =SLOT_A -> Tesouro Prefixado 2031 | C6: =SLOT_B -> Tesouro IPCA+ 2035 | D6: =SLOT_C -> Fundo CAIXA RF Crédito Privado LP | E6: =SLOT_D -> VGBL CAIXA Composto 30 — Regressivo | F6: =SLOT_E -> PGBL CAIXA Composto 30 — Regressivo | G6: =SLOT_F -> Fundo CAIXA RF IPCA Longo Prazo
A7: Linha na base de produtos | B7: =IFERROR(MATCH(B$6,BASE_PRODUTOS,0),0) -> 10 | C7: =IFERROR(MATCH(C$6,BASE_PRODUTOS,0),0) -> 9 | D7: =IFERROR(MATCH(D$6,BASE_PRODUTOS,0),0) -> 13 | E7: =IFERROR(MATCH(E$6,BASE_PRODUTOS,0),0) -> 23 | F7: =IFERROR(MATCH(F$6,BASE_PRODUTOS,0),0) -> 22 | G7: =IFERROR(MATCH(G$6,BASE_PRODUTOS,0),0) -> 14
A8: Regime tributário | B8: =IF($B$7=0,"",INDEX(Produtos!$N$9:$N$78,$B$7)) -> RF_REGR | C8: =IF($C$7=0,"",INDEX(Produtos!$N$9:$N$78,$C$7)) -> RF_REGR | D8: =IF($D$7=0,"",INDEX(Produtos!$N$9:$N$78,$D$7)) -> FUNDO_LP | E8: =IF($E$7=0,"",INDEX(Produtos!$N$9:$N$78,$E$7)) -> PREV_REGR | F8: =IF($F$7=0,"",INDEX(Produtos!$N$9:$N$78,$F$7)) -> PREV_REGR | G8: =IF($G$7=0,"",INDEX(Produtos!$N$9:$N$78,$G$7)) -> FUNDO_LP
A9: Alternativa em uso (1/0) | B9: =IF(OR($B$6="",$B$7=0,$B$8="IMOVEL"),0,1) -> 1 | C9: =IF(OR($C$6="",$C$7=0,$C$8="IMOVEL"),0,1) -> 1 | D9: =IF(OR($D$6="",$D$7=0,$D$8="IMOVEL"),0,1) -> 1 | E9: =IF(OR($E$6="",$E$7=0,$E$8="IMOVEL"),0,1) -> 1 | F9: =IF(OR($F$6="",$F$7=0,$F$8="IMOVEL"),0,1) -> 1 | G9: =IF(OR($G$6="",$G$7=0,$G$8="IMOVEL"),0,1) -> 1
A10: Categoria | B10: =IF($B$7=0,"",INDEX(Produtos!$C$9:$C$78,$B$7)) -> Renda Fixa | C10: =IF($C$7=0,"",INDEX(Produtos!$C$9:$C$78,$C$7)) -> Renda Fixa | D10: =IF($D$7=0,"",INDEX(Produtos!$C$9:$C$78,$D$7)) -> Fundo | E10: =IF($E$7=0,"",INDEX(Produtos!$C$9:$C$78,$E$7)) -> Previdência | F10: =IF($F$7=0,"",INDEX(Produtos!$C$9:$C$78,$F$7)) -> Previdência | G10: =IF($G$7=0,"",INDEX(Produtos!$C$9:$C$78,$G$7)) -> Fundo
A11: Emissor / Gestor | B11: =IF($B$7=0,"",INDEX(Produtos!$D$9:$D$78,$B$7)) -> Tesouro Nacional | C11: =IF($C$7=0,"",INDEX(Produtos!$D$9:$D$78,$C$7)) -> Tesouro Nacional | D11: =IF($D$7=0,"",INDEX(Produtos!$D$9:$D$78,$D$7)) -> CAIXA Asset | E11: =IF($E$7=0,"",INDEX(Produtos!$D$9:$D$78,$E$7)) -> CAIXA Vida e Previdência | F11: =IF($F$7=0,"",INDEX(Produtos!$D$9:$D$78,$F$7)) -> CAIXA Vida e Previdência | G11: =IF($G$7=0,"",INDEX(Produtos!$D$9:$D$78,$G$7)) -> CAIXA Asset
A12: Benchmark | B12: =IF($B$7=0,"",INDEX(Produtos!$E$9:$E$78,$B$7)) -> PRE | C12: =IF($C$7=0,"",INDEX(Produtos!$E$9:$E$78,$C$7)) -> IPCA | D12: =IF($D$7=0,"",INDEX(Produtos!$E$9:$E$78,$D$7)) -> CDI | E12: =IF($E$7=0,"",INDEX(Produtos!$E$9:$E$78,$E$7)) -> CDI | F12: =IF($F$7=0,"",INDEX(Produtos!$E$9:$E$78,$F$7)) -> CDI | G12: =IF($G$7=0,"",INDEX(Produtos!$E$9:$E$78,$G$7)) -> IPCA
A13: % do benchmark | B13: =IF($B$7=0,0,IFERROR(INDEX(Produtos!$F$9:$F$78,$B$7),0)) -> 1 | C13: =IF($C$7=0,0,IFERROR(INDEX(Produtos!$F$9:$F$78,$C$7),0)) -> 1 | D13: =IF($D$7=0,0,IFERROR(INDEX(Produtos!$F$9:$F$78,$D$7),0)) -> 1.04 | E13: =IF($E$7=0,0,IFERROR(INDEX(Produtos!$F$9:$F$78,$E$7),0)) -> 1 | F13: =IF($F$7=0,0,IFERROR(INDEX(Produtos!$F$9:$F$78,$F$7),0)) -> 1 | G13: =IF($G$7=0,0,IFERROR(INDEX(Produtos!$F$9:$F$78,$G$7),0)) -> 1
A14: Spread a.a. | B14: =IF($B$7=0,0,IFERROR(INDEX(Produtos!$G$9:$G$78,$B$7),0)) -> 0.12 | C14: =IF($C$7=0,0,IFERROR(INDEX(Produtos!$G$9:$G$78,$C$7),0)) -> 0.06 | D14: =IF($D$7=0,0,IFERROR(INDEX(Produtos!$G$9:$G$78,$D$7),0)) -> 0 | E14: =IF($E$7=0,0,IFERROR(INDEX(Produtos!$G$9:$G$78,$E$7),0)) -> 0.015 | F14: =IF($F$7=0,0,IFERROR(INDEX(Produtos!$G$9:$G$78,$F$7),0)) -> 0.015 | G14: =IF($G$7=0,0,IFERROR(INDEX(Produtos!$G$9:$G$78,$G$7),0)) -> 0.06
A15: Composição | B15: =IF($B$7=0,"",INDEX(Produtos!$H$9:$H$78,$B$7)) -> SOMA | C15: =IF($C$7=0,"",INDEX(Produtos!$H$9:$H$78,$C$7)) -> MULT | D15: =IF($D$7=0,"",INDEX(Produtos!$H$9:$H$78,$D$7)) -> SOMA | E15: =IF($E$7=0,"",INDEX(Produtos!$H$9:$H$78,$E$7)) -> SOMA | F15: =IF($F$7=0,"",INDEX(Produtos!$H$9:$H$78,$F$7)) -> SOMA | G15: =IF($G$7=0,"",INDEX(Produtos!$H$9:$H$78,$G$7)) -> MULT
A16: Retorno a.a. do benchmark puro | B16: =IFERROR(INDEX(TAB_MACRO_VAL,MATCH($B$12,TAB_MACRO_COD,0)),0) -> 0 | C16: =IFERROR(INDEX(TAB_MACRO_VAL,MATCH($C$12,TAB_MACRO_COD,0)),0) -> 0.04 | D16: =IFERROR(INDEX(TAB_MACRO_VAL,MATCH($D$12,TAB_MACRO_COD,0)),0) -> 0.109 | E16: =IFERROR(INDEX(TAB_MACRO_VAL,MATCH($E$12,TAB_MACRO_COD,0)),0) -> 0.109 | F16: =IFERROR(INDEX(TAB_MACRO_VAL,MATCH($F$12,TAB_MACRO_COD,0)),0) -> 0.109 | G16: =IFERROR(INDEX(TAB_MACRO_VAL,MATCH($G$12,TAB_MACRO_COD,0)),0) -> 0.04
A17: Retorno BRUTO a.a. (cenário) | B17: =IF($B$9=0,0,IF($B$15="MULT",(1+$B$16*$B$13)*(1+$B$14)-1,$B$16*$B$13+$B$14)) -> 0.12 | C17: =IF($C$9=0,0,IF($C$15="MULT",(1+$C$16*$C$13)*(1+$C$14)-1,$C$16*$C$13+$C$14)) -> 0.1024 | D17: =IF($D$9=0,0,IF($D$15="MULT",(1+$D$16*$D$13)*(1+$D$14)-1,$D$16*$D$13+$D$14)) -> 0.11336 | E17: =IF($E$9=0,0,IF($E$15="MULT",(1+$E$16*$E$13)*(1+$E$14)-1,$E$16*$E$13+$E$14)) -> 0.124 | F17: =IF($F$9=0,0,IF($F$15="MULT",(1+$F$16*$F$13)*(1+$F$14)-1,$F$16*$F$13+$F$14)) -> 0.124 | G17: =IF($G$9=0,0,IF($G$15="MULT",(1+$G$16*$G$13)*(1+$G$14)-1,$G$16*$G$13+$G$14)) -> 0.1024
A18: Taxa mensal do benchmark | B18: =IF($B$16<=-1,0,(1+$B$16)^(1/12)-1) -> 0 | C18: =IF($C$16<=-1,0,(1+$C$16)^(1/12)-1) -> 0.0032737398 | D18: =IF($D$16<=-1,0,(1+$D$16)^(1/12)-1) -> 0.0086588317 | E18: =IF($E$16<=-1,0,(1+$E$16)^(1/12)-1) -> 0.0086588317 | F18: =IF($F$16<=-1,0,(1+$F$16)^(1/12)-1) -> 0.0086588317 | G18: =IF($G$16<=-1,0,(1+$G$16)^(1/12)-1) -> 0.0032737398
A19: Taxa mensal bruta | B19: =IF($B$17<=-1,0,(1+$B$17)^(1/12)-1) -> 0.0094887929 | C19: =IF($C$17<=-1,0,(1+$C$17)^(1/12)-1) -> 0.0081572254 | D19: =IF($D$17<=-1,0,(1+$D$17)^(1/12)-1) -> 0.008988697 | E19: =IF($E$17<=-1,0,(1+$E$17)^(1/12)-1) -> 0.0097887454 | F19: =IF($F$17<=-1,0,(1+$F$17)^(1/12)-1) -> 0.0097887454 | G19: =IF($G$17<=-1,0,(1+$G$17)^(1/12)-1) -> 0.0081572254
A20: Taxa de administração a.a. | B20: =IF($B$7=0,0,IFERROR(INDEX(Produtos!$I$9:$I$78,$B$7),0)) -> 0 | C20: =IF($C$7=0,0,IFERROR(INDEX(Produtos!$I$9:$I$78,$C$7),0)) -> 0 | D20: =IF($D$7=0,0,IFERROR(INDEX(Produtos!$I$9:$I$78,$D$7),0)) -> 0.01 | E20: =IF($E$7=0,0,IFERROR(INDEX(Produtos!$I$9:$I$78,$E$7),0)) -> 0.015 | F20: =IF($F$7=0,0,IFERROR(INDEX(Produtos!$I$9:$I$78,$F$7),0)) -> 0.015 | G20: =IF($G$7=0,0,IFERROR(INDEX(Produtos!$I$9:$I$78,$G$7),0)) -> 0.01
A21: Custódia a.a. | B21: =IF($B$7=0,0,IFERROR(INDEX(Produtos!$M$9:$M$78,$B$7),0)) -> 0.002 | C21: =IF($C$7=0,0,IFERROR(INDEX(Produtos!$M$9:$M$78,$C$7),0)) -> 0.002 | D21: =IF($D$7=0,0,IFERROR(INDEX(Produtos!$M$9:$M$78,$D$7),0)) -> 0 | E21: =IF($E$7=0,0,IFERROR(INDEX(Produtos!$M$9:$M$78,$E$7),0)) -> 0 | F21: =IF($F$7=0,0,IFERROR(INDEX(Produtos!$M$9:$M$78,$F$7),0)) -> 0 | G21: =IF($G$7=0,0,IFERROR(INDEX(Produtos!$M$9:$M$78,$G$7),0)) -> 0
A22: Custos mensais (adm + custódia) | B22: =($B$20+$B$21)/12 -> 0.00016666667 | C22: =($C$20+$C$21)/12 -> 0.00016666667 | D22: =($D$20+$D$21)/12 -> 0.00083333333 | E22: =($E$20+$E$21)/12 -> 0.00125 | F22: =($F$20+$F$21)/12 -> 0.00125 | G22: =($G$20+$G$21)/12 -> 0.00083333333
A23: Taxa de performance | B23: =IF($B$7=0,0,IFERROR(INDEX(Produtos!$J$9:$J$78,$B$7),0)) -> 0 | C23: =IF($C$7=0,0,IFERROR(INDEX(Produtos!$J$9:$J$78,$C$7),0)) -> 0 | D23: =IF($D$7=0,0,IFERROR(INDEX(Produtos!$J$9:$J$78,$D$7),0)) -> 0 | E23: =IF($E$7=0,0,IFERROR(INDEX(Produtos!$J$9:$J$78,$E$7),0)) -> 0 | F23: =IF($F$7=0,0,IFERROR(INDEX(Produtos!$J$9:$J$78,$F$7),0)) -> 0 | G23: =IF($G$7=0,0,IFERROR(INDEX(Produtos!$J$9:$J$78,$G$7),0)) -> 0
A24: Carregamento de entrada | B24: =IF($B$7=0,0,IFERROR(INDEX(Produtos!$K$9:$K$78,$B$7),0)) -> 0 | C24: =IF($C$7=0,0,IFERROR(INDEX(Produtos!$K$9:$K$78,$C$7),0)) -> 0 | D24: =IF($D$7=0,0,IFERROR(INDEX(Produtos!$K$9:$K$78,$D$7),0)) -> 0 | E24: =IF($E$7=0,0,IFERROR(INDEX(Produtos!$K$9:$K$78,$E$7),0)) -> 0 | F24: =IF($F$7=0,0,IFERROR(INDEX(Produtos!$K$9:$K$78,$F$7),0)) -> 0 | G24: =IF($G$7=0,0,IFERROR(INDEX(Produtos!$K$9:$K$78,$G$7),0)) -> 0
A25: Carregamento de saída | B25: =IF($B$7=0,0,IFERROR(INDEX(Produtos!$L$9:$L$78,$B$7),0)) -> 0 | C25: =IF($C$7=0,0,IFERROR(INDEX(Produtos!$L$9:$L$78,$C$7),0)) -> 0 | D25: =IF($D$7=0,0,IFERROR(INDEX(Produtos!$L$9:$L$78,$D$7),0)) -> 0 | E25: =IF($E$7=0,0,IFERROR(INDEX(Produtos!$L$9:$L$78,$E$7),0)) -> 0 | F25: =IF($F$7=0,0,IFERROR(INDEX(Produtos!$L$9:$L$78,$F$7),0)) -> 0 | G25: =IF($G$7=0,0,IFERROR(INDEX(Produtos!$L$9:$L$78,$G$7),0)) -> 0
A26: Base tributável (1=rend. / 2=total) | B26: =IF($B$7=0,0,IFERROR(INDEX(Produtos!$O$9:$O$78,$B$7),0)) -> 1 | C26: =IF($C$7=0,0,IFERROR(INDEX(Produtos!$O$9:$O$78,$C$7),0)) -> 1 | D26: =IF($D$7=0,0,IFERROR(INDEX(Produtos!$O$9:$O$78,$D$7),0)) -> 1 | E26: =IF($E$7=0,0,IFERROR(INDEX(Produtos!$O$9:$O$78,$E$7),0)) -> 1 | F26: =IF($F$7=0,0,IFERROR(INDEX(Produtos!$O$9:$O$78,$F$7),0)) -> 2 | G26: =IF($G$7=0,0,IFERROR(INDEX(Produtos!$O$9:$O$78,$G$7),0)) -> 1
A27: Tem come-cotas (1/0) | B27: =IFERROR(INDEX(Premissas!$B$34:$B$40,MATCH($B$8,Premissas!$A$34:$A$40,0)),0) -> 0 | C27: =IFERROR(INDEX(Premissas!$B$34:$B$40,MATCH($C$8,Premissas!$A$34:$A$40,0)),0) -> 0 | D27: =IFERROR(INDEX(Premissas!$B$34:$B$40,MATCH($D$8,Premissas!$A$34:$A$40,0)),0) -> 1 | E27: =IFERROR(INDEX(Premissas!$B$34:$B$40,MATCH($E$8,Premissas!$A$34:$A$40,0)),0) -> 0 | F27: =IFERROR(INDEX(Premissas!$B$34:$B$40,MATCH($F$8,Premissas!$A$34:$A$40,0)),0) -> 0 | G27: =IFERROR(INDEX(Premissas!$B$34:$B$40,MATCH($G$8,Premissas!$A$34:$A$40,0)),0) -> 1
A28: Alíquota do come-cotas | B28: =IFERROR(INDEX(Premissas!$C$34:$C$40,MATCH($B$8,Premissas!$A$34:$A$40,0)),0) -> 0 | C28: =IFERROR(INDEX(Premissas!$C$34:$C$40,MATCH($C$8,Premissas!$A$34:$A$40,0)),0) -> 0 | D28: =IFERROR(INDEX(Premissas!$C$34:$C$40,MATCH($D$8,Premissas!$A$34:$A$40,0)),0) -> 0.15 | E28: =IFERROR(INDEX(Premissas!$C$34:$C$40,MATCH($E$8,Premissas!$A$34:$A$40,0)),0) -> 0 | F28: =IFERROR(INDEX(Premissas!$C$34:$C$40,MATCH($F$8,Premissas!$A$34:$A$40,0)),0) -> 0 | G28: =IFERROR(INDEX(Premissas!$C$34:$C$40,MATCH($G$8,Premissas!$A$34:$A$40,0)),0) -> 0.15
A29: Carência (dias) | B29: =IF($B$7=0,0,IFERROR(INDEX(Produtos!$P$9:$P$78,$B$7),0)) -> 0 | C29: =IF($C$7=0,0,IFERROR(INDEX(Produtos!$P$9:$P$78,$C$7),0)) -> 0 | D29: =IF($D$7=0,0,IFERROR(INDEX(Produtos!$P$9:$P$78,$D$7),0)) -> 0 | E29: =IF($E$7=0,0,IFERROR(INDEX(Produtos!$P$9:$P$78,$E$7),0)) -> 0 | F29: =IF($F$7=0,0,IFERROR(INDEX(Produtos!$P$9:$P$78,$F$7),0)) -> 0 | G29: =IF($G$7=0,0,IFERROR(INDEX(Produtos!$P$9:$P$78,$G$7),0)) -> 0
A30: Liquidez (dias) | B30: =IF($B$7=0,0,IFERROR(INDEX(Produtos!$Q$9:$Q$78,$B$7),0)) -> 1 | C30: =IF($C$7=0,0,IFERROR(INDEX(Produtos!$Q$9:$Q$78,$C$7),0)) -> 1 | D30: =IF($D$7=0,0,IFERROR(INDEX(Produtos!$Q$9:$Q$78,$D$7),0)) -> 30 | E30: =IF($E$7=0,0,IFERROR(INDEX(Produtos!$Q$9:$Q$78,$E$7),0)) -> 5 | F30: =IF($F$7=0,0,IFERROR(INDEX(Produtos!$Q$9:$Q$78,$F$7),0)) -> 5 | G30: =IF($G$7=0,0,IFERROR(INDEX(Produtos!$Q$9:$Q$78,$G$7),0)) -> 5
A31: Aplicação mínima | B31: =IF($B$7=0,0,IFERROR(INDEX(Produtos!$R$9:$R$78,$B$7),0)) -> 100 | C31: =IF($C$7=0,0,IFERROR(INDEX(Produtos!$R$9:$R$78,$C$7),0)) -> 100 | D31: =IF($D$7=0,0,IFERROR(INDEX(Produtos!$R$9:$R$78,$D$7),0)) -> 5000 | E31: =IF($E$7=0,0,IFERROR(INDEX(Produtos!$R$9:$R$78,$E$7),0)) -> 5000 | F31: =IF($F$7=0,0,IFERROR(INDEX(Produtos!$R$9:$R$78,$F$7),0)) -> 5000 | G31: =IF($G$7=0,0,IFERROR(INDEX(Produtos!$R$9:$R$78,$G$7),0)) -> 5000
A32: Risco (1-5) | B32: =IF($B$7=0,0,IFERROR(INDEX(Produtos!$T$9:$T$78,$B$7),0)) -> 2 | C32: =IF($C$7=0,0,IFERROR(INDEX(Produtos!$T$9:$T$78,$C$7),0)) -> 2 | D32: =IF($D$7=0,0,IFERROR(INDEX(Produtos!$T$9:$T$78,$D$7),0)) -> 2 | E32: =IF($E$7=0,0,IFERROR(INDEX(Produtos!$T$9:$T$78,$E$7),0)) -> 3 | F32: =IF($F$7=0,0,IFERROR(INDEX(Produtos!$T$9:$T$78,$F$7),0)) -> 3 | G32: =IF($G$7=0,0,IFERROR(INDEX(Produtos!$T$9:$T$78,$G$7),0)) -> 3
A33: Volatilidade a.a. | B33: =IF($B$7=0,0,IFERROR(INDEX(Produtos!$U$9:$U$78,$B$7),0)) -> 0.06 | C33: =IF($C$7=0,0,IFERROR(INDEX(Produtos!$U$9:$U$78,$C$7),0)) -> 0.08 | D33: =IF($D$7=0,0,IFERROR(INDEX(Produtos!$U$9:$U$78,$D$7),0)) -> 0.01 | E33: =IF($E$7=0,0,IFERROR(INDEX(Produtos!$U$9:$U$78,$E$7),0)) -> 0.06 | F33: =IF($F$7=0,0,IFERROR(INDEX(Produtos!$U$9:$U$78,$F$7),0)) -> 0.06 | G33: =IF($G$7=0,0,IFERROR(INDEX(Produtos!$U$9:$U$78,$G$7),0)) -> 0.08
A34: Garantia | B34: =IF($B$7=0,"",INDEX(Produtos!$V$9:$V$78,$B$7)) -> Tesouro Nacional | C34: =IF($C$7=0,"",INDEX(Produtos!$V$9:$V$78,$C$7)) -> Tesouro Nacional | D34: =IF($D$7=0,"",INDEX(Produtos!$V$9:$V$78,$D$7)) -> Sem garantia do FGC | E34: =IF($E$7=0,"",INDEX(Produtos!$V$9:$V$78,$E$7)) -> Seguradora (sem FGC) | F34: =IF($F$7=0,"",INDEX(Produtos!$V$9:$V$78,$F$7)) -> Seguradora (sem FGC) | G34: =IF($G$7=0,"",INDEX(Produtos!$V$9:$V$78,$G$7)) -> Sem garantia do FGC
A35: É PGBL (aporte dedutível) | B35: =IF($B$26=2,1,0) -> 0 | C35: =IF($C$26=2,1,0) -> 0 | D35: =IF($D$26=2,1,0) -> 0 | E35: =IF($E$26=2,1,0) -> 0 | F35: =IF($F$26=2,1,0) -> 1 | G35: =IF($G$26=2,1,0) -> 0
A36: Retorno LÍQUIDO a.a. estimado | B36: =IF($B$9=0,0,(1+$B$19-$B$22)^12-1) -> 0.11778307 | C36: =IF($C$9=0,0,(1+$C$19-$C$22)^12-1) -> 0.10021503 | D36: =IF($D$9=0,0,(1+$D$19-$D$22)^12-1) -> 0.10237557 | E36: =IF($E$9=0,0,(1+$E$19-$E$22)^12-1) -> 0.10741665 | F36: =IF($F$9=0,0,(1+$F$19-$F$22)^12-1) -> 0.10741665 | G36: =IF($G$9=0,0,(1+$G$19-$G$22)^12-1) -> 0.091514773
A37: BLOCO 2 · RESULTADOS NO PRAZO ESCOLHIDO PELO CLIENTE
A38: Resultado | B38: ALTERNATIVA A | C38: ALTERNATIVA B | D38: ALTERNATIVA C | E38: ALTERNATIVA D | F38: ALTERNATIVA E | G38: ALTERNATIVA F
A39: Patrimônio bruto no prazo | B39: =IF($B$9=0,0,INDEX($M$61:$M$301,IN_PRAZO+1)) -> 456737.35 | C39: =IF($C$9=0,0,INDEX($AB$61:$AB$301,IN_PRAZO+1)) -> 389822.57 | D39: =IF($D$9=0,0,INDEX($AQ$61:$AQ$301,IN_PRAZO+1)) -> 345725.63 | E39: =IF($E$9=0,0,INDEX($BF$61:$BF$301,IN_PRAZO+1)) -> 416103.85 | F39: =IF($F$9=0,0,INDEX($BU$61:$BU$301,IN_PRAZO+1)) -> 416103.85 | G39: =IF($G$9=0,0,INDEX($CJ$61:$CJ$301,IN_PRAZO+1)) -> 317526.86
A40: Patrimônio líquido no prazo | B40: =IF($B$9=0,0,INDEX($R$61:$R$301,IN_PRAZO+1)) -> 410726.75 | C40: =IF($C$9=0,0,INDEX($AG$61:$AG$301,IN_PRAZO+1)) -> 353849.19 | D40: =IF($D$9=0,0,INDEX($AV$61:$AV$301,IN_PRAZO+1)) -> 344477.27 | E40: =IF($E$9=0,0,INDEX($BK$61:$BK$301,IN_PRAZO+1)) -> 376188.27 | F40: =IF($F$9=0,0,INDEX($BZ$61:$BZ$301,IN_PRAZO+1)) -> 353688.27 | G40: =IF($G$9=0,0,INDEX($CO$61:$CO$301,IN_PRAZO+1)) -> 316495.51
A41: Patrimônio líquido na metade do prazo | B41: =IF($B$9=0,0,INDEX($R$61:$R$301,INT(IN_PRAZO/2)+1)) -> 244983.51 | C41: =IF($C$9=0,0,INDEX($AG$61:$AG$301,INT(IN_PRAZO/2)+1)) -> 228040.8 | D41: =IF($D$9=0,0,INDEX($AV$61:$AV$301,INT(IN_PRAZO/2)+1)) -> 227305.4 | E41: =IF($E$9=0,0,INDEX($BK$61:$BK$301,INT(IN_PRAZO/2)+1)) -> 224873.32 | F41: =IF($F$9=0,0,INDEX($BZ$61:$BZ$301,INT(IN_PRAZO/2)+1)) -> 187373.32 | G41: =IF($G$9=0,0,INDEX($CO$61:$CO$301,INT(IN_PRAZO/2)+1)) -> 217879.48
A42: Patrimônio líquido em R$ de hoje | B42: =IF($B$9=0,0,INDEX($S$61:$S$301,IN_PRAZO+1)) -> 277472.27 | C42: =IF($C$9=0,0,INDEX($AH$61:$AH$301,IN_PRAZO+1)) -> 239047.83 | D42: =IF($D$9=0,0,INDEX($AW$61:$AW$301,IN_PRAZO+1)) -> 232716.5 | E42: =IF($E$9=0,0,INDEX($BL$61:$BL$301,IN_PRAZO+1)) -> 254139.32 | F42: =IF($F$9=0,0,INDEX($CA$61:$CA$301,IN_PRAZO+1)) -> 238939.12 | G42: =IF($G$9=0,0,INDEX($CP$61:$CP$301,IN_PRAZO+1)) -> 213813.03
A43: Total investido (capital + aportes) | B43: =IF($B$9=0,0,SUMIF($A$61:$A$301,"<="&IN_PRAZO,$G$61:$G$301)) -> 150000 | C43: =IF($C$9=0,0,SUMIF($A$61:$A$301,"<="&IN_PRAZO,$V$61:$V$301)) -> 150000 | D43: =IF($D$9=0,0,SUMIF($A$61:$A$301,"<="&IN_PRAZO,$AK$61:$AK$301)) -> 150000 | E43: =IF($E$9=0,0,SUMIF($A$61:$A$301,"<="&IN_PRAZO,$AZ$61:$AZ$301)) -> 150000 | F43: =IF($F$9=0,0,SUMIF($A$61:$A$301,"<="&IN_PRAZO,$BO$61:$BO$301)) -> 150000 | G43: =IF($G$9=0,0,SUMIF($A$61:$A$301,"<="&IN_PRAZO,$CD$61:$CD$301)) -> 150000
A44: Ganho líquido | B44: =$B$40-$B$43 -> 260726.75 | C44: =$C$40-$C$43 -> 203849.19 | D44: =$D$40-$D$43 -> 194477.27 | E44: =$E$40-$E$43 -> 226188.27 | F44: =$F$40-$F$43 -> 203688.27 | G44: =$G$40-$G$43 -> 166495.51
A45: Imposto total pago | B45: =IF($B$9=0,0,SUMIF($A$61:$A$301,"<="&IN_PRAZO,$L$61:$L$301)+INDEX($Q$61:$Q$301,IN_PRAZO+1)) -> 46010.603 | C45: =IF($C$9=0,0,SUMIF($A$61:$A$301,"<="&IN_PRAZO,$AA$61:$AA$301)+INDEX($AF$61:$AF$301,IN_PRAZO+1)) -> 35973.386 | D45: =IF($D$9=0,0,SUMIF($A$61:$A$301,"<="&IN_PRAZO,$AP$61:$AP$301)+INDEX($AU$61:$AU$301,IN_PRAZO+1)) -> 34319.518 | E45: =IF($E$9=0,0,SUMIF($A$61:$A$301,"<="&IN_PRAZO,$BE$61:$BE$301)+INDEX($BJ$61:$BJ$301,IN_PRAZO+1)) -> 39915.578 | F45: =IF($F$9=0,0,SUMIF($A$61:$A$301,"<="&IN_PRAZO,$BT$61:$BT$301)+INDEX($BY$61:$BY$301,IN_PRAZO+1)) -> 62415.578 | G45: =IF($G$9=0,0,SUMIF($A$61:$A$301,"<="&IN_PRAZO,$CI$61:$CI$301)+INDEX($CN$61:$CN$301,IN_PRAZO+1)) -> 29381.56
A46: Custos totais pagos | B46: =IF($B$9=0,0,SUMIF($A$61:$A$301,"<="&IN_PRAZO,$H$61:$H$301)+SUMIF($A$61:$A$301,"<="&IN_PRAZO,$J$61:$J$301)+SUMIF($A$61:$A$301,"<="&IN_PRAZO,$K$61:$K$301)+INDEX($M$61:$M$301,IN_PRAZO+1)*$B$25) -> 5484.0377 | C46: =IF($C$9=0,0,SUMIF($A$61:$A$301,"<="&IN_PRAZO,$W$61:$W$301)+SUMIF($A$61:$A$301,"<="&IN_PRAZO,$Y$61:$Y$301)+SUMIF($A$61:$A$301,"<="&IN_PRAZO,$Z$61:$Z$301)+INDEX($AB$61:$AB$301,IN_PRAZO+1)*$C$25) -> 5002.2069 | D46: =IF($D$9=0,0,SUMIF($A$61:$A$301,"<="&IN_PRAZO,$AL$61:$AL$301)+SUMIF($A$61:$A$301,"<="&IN_PRAZO,$AN$61:$AN$301)+SUMIF($A$61:$A$301,"<="&IN_PRAZO,$AO$61:$AO$301)+INDEX($AQ$61:$AQ$301,IN_PRAZO+1)*$D$25) -> 23378.968 | E46: =IF($E$9=0,0,SUMIF($A$61:$A$301,"<="&IN_PRAZO,$BA$61:$BA$301)+SUMIF($A$61:$A$301,"<="&IN_PRAZO,$BC$61:$BC$301)+SUMIF($A$61:$A$301,"<="&IN_PRAZO,$BD$61:$BD$301)+INDEX($BF$61:$BF$301,IN_PRAZO+1)*$E$25) -> 38955.35 | F46: =IF($F$9=0,0,SUMIF($A$61:$A$301,"<="&IN_PRAZO,$BP$61:$BP$301)+SUMIF($A$61:$A$301,"<="&IN_PRAZO,$BR$61:$BR$301)+SUMIF($A$61:$A$301,"<="&IN_PRAZO,$BS$61:$BS$301)+INDEX($BU$61:$BU$301,IN_PRAZO+1)*$F$25) -> 38955.35 | G46: =IF($G$9=0,0,SUMIF($A$61:$A$301,"<="&IN_PRAZO,$CE$61:$CE$301)+SUMIF($A$61:$A$301,"<="&IN_PRAZO,$CG$61:$CG$301)+SUMIF($A$61:$A$301,"<="&IN_PRAZO,$CH$61:$CH$301)+INDEX($CJ$61:$CJ$301,IN_PRAZO+1)*$G$25) -> 22287.452
A47: Rentabilidade líquida acumulada | B47: =IF($B$43=0,0,$B$40/$B$43-1) -> 1.7381783 | C47: =IF($C$43=0,0,$C$40/$C$43-1) -> 1.3589946 | D47: =IF($D$43=0,0,$D$40/$D$43-1) -> 1.2965151 | E47: =IF($E$43=0,0,$E$40/$E$43-1) -> 1.5079218 | F47: =IF($F$43=0,0,$F$40/$F$43-1) -> 1.3579218 | G47: =IF($G$43=0,0,$G$40/$G$43-1) -> 1.1099701
A48: Taxa líquida equivalente a.a. | B48: =IF(OR($B$9=0,IN_PRAZO=0),0,IFERROR((1+RATE(IN_PRAZO,-($B$43-IN_CAPITAL)/IN_PRAZO,-IN_CAPITAL,$B$40))^12-1,(1+$B$47)^(12/IN_PRAZO)-1)) -> 0.1059772 | C48: =IF(OR($C$9=0,IN_PRAZO=0),0,IFERROR((1+RATE(IN_PRAZO,-($C$43-IN_CAPITAL)/IN_PRAZO,-IN_CAPITAL,$C$40))^12-1,(1+$C$47)^(12/IN_PRAZO)-1)) -> 0.089614049 | D48: =IF(OR($D$9=0,IN_PRAZO=0),0,IFERROR((1+RATE(IN_PRAZO,-($D$43-IN_CAPITAL)/IN_PRAZO,-IN_CAPITAL,$D$40))^12-1,(1+$D$47)^(12/IN_PRAZO)-1)) -> 0.086693154 | E48: =IF(OR($E$9=0,IN_PRAZO=0),0,IFERROR((1+RATE(IN_PRAZO,-($E$43-IN_CAPITAL)/IN_PRAZO,-IN_CAPITAL,$E$40))^12-1,(1+$E$47)^(12/IN_PRAZO)-1)) -> 0.096305012 | F48: =IF(OR($F$9=0,IN_PRAZO=0),0,IFERROR((1+RATE(IN_PRAZO,-($F$43-IN_CAPITAL)/IN_PRAZO,-IN_CAPITAL,$F$40))^12-1,(1+$F$47)^(12/IN_PRAZO)-1)) -> 0.089564489 | G48: =IF(OR($G$9=0,IN_PRAZO=0),0,IFERROR((1+RATE(IN_PRAZO,-($G$43-IN_CAPITAL)/IN_PRAZO,-IN_CAPITAL,$G$40))^12-1,(1+$G$47)^(12/IN_PRAZO)-1)) -> 0.07752568
A49: Ganho real a.a. (acima da inflação) | B49: =IF($B$9=0,0,(1+$B$48)/(1+IPCA_CENARIO)-1) -> 0.063439613 | C49: =IF($C$9=0,0,(1+$C$48)/(1+IPCA_CENARIO)-1) -> 0.047705816 | D49: =IF($D$9=0,0,(1+$D$48)/(1+IPCA_CENARIO)-1) -> 0.044897263 | E49: =IF($E$9=0,0,(1+$E$48)/(1+IPCA_CENARIO)-1) -> 0.054139434 | F49: =IF($F$9=0,0,(1+$F$48)/(1+IPCA_CENARIO)-1) -> 0.047658162 | G49: =IF($G$9=0,0,(1+$G$48)/(1+IPCA_CENARIO)-1) -> 0.036082385
A50: Alíquota de IR no prazo escolhido | B50: =IF($B$9=0,0,IFERROR(INDEX(TAB_IR,MATCH(IN_PRAZO*30,TAB_IR_DIAS,1),MATCH($B$8,TAB_IR_REGIMES,0)),0)) -> 0.15 | C50: =IF($C$9=0,0,IFERROR(INDEX(TAB_IR,MATCH(IN_PRAZO*30,TAB_IR_DIAS,1),MATCH($C$8,TAB_IR_REGIMES,0)),0)) -> 0.15 | D50: =IF($D$9=0,0,IFERROR(INDEX(TAB_IR,MATCH(IN_PRAZO*30,TAB_IR_DIAS,1),MATCH($D$8,TAB_IR_REGIMES,0)),0)) -> 0.15 | E50: =IF($E$9=0,0,IFERROR(INDEX(TAB_IR,MATCH(IN_PRAZO*30,TAB_IR_DIAS,1),MATCH($E$8,TAB_IR_REGIMES,0)),0)) -> 0.15 | F50: =IF($F$9=0,0,IFERROR(INDEX(TAB_IR,MATCH(IN_PRAZO*30,TAB_IR_DIAS,1),MATCH($F$8,TAB_IR_REGIMES,0)),0)) -> 0.15 | G50: =IF($G$9=0,0,IFERROR(INDEX(TAB_IR,MATCH(IN_PRAZO*30,TAB_IR_DIAS,1),MATCH($G$8,TAB_IR_REGIMES,0)),0)) -> 0.15
A51: Renda mensal potencial (nominal) | B51: =IF($B$9=0,0,MAX(0,$B$40*($B$19-$B$22)*(1-$B$50))) -> 3254.5196 | C51: =IF($C$9=0,0,MAX(0,$C$40*($C$19-$C$22)*(1-$C$50))) -> 2403.3348 | D51: =IF($D$9=0,0,MAX(0,$D$40*($D$19-$D$22)*(1-$D$50))) -> 2387.9368 | E51: =IF($E$9=0,0,MAX(0,$E$40*($E$19-$E$22)*(1-$E$50))) -> 2730.3495 | F51: =IF($F$9=0,0,MAX(0,$F$40*($F$19-$F$22)*(1-$F$50))) -> 2567.046 | G51: =IF($G$9=0,0,MAX(0,$G$40*($G$19-$G$22)*(1-$G$50))) -> 1970.2821
A52: Renda mensal potencial (poder de compra) | B52: =IF($B$9=0,0,MAX(0,$B$40*((1+($B$19-$B$22)*(1-$B$50))/((1+IPCA_CENARIO)^(1/12))-1))) -> 1903.675 | C52: =IF($C$9=0,0,MAX(0,$C$40*((1+($C$19-$C$22)*(1-$C$50))/((1+IPCA_CENARIO)^(1/12))-1))) -> 1240.8624 | D52: =IF($D$9=0,0,MAX(0,$D$40*((1+($D$19-$D$22)*(1-$D$50))/((1+IPCA_CENARIO)^(1/12))-1))) -> 1256.0957 | E52: =IF($E$9=0,0,MAX(0,$E$40*((1+($E$19-$E$22)*(1-$E$50))/((1+IPCA_CENARIO)^(1/12))-1))) -> 1493.9163 | F52: =IF($F$9=0,0,MAX(0,$F$40*((1+($F$19-$F$22)*(1-$F$50))/((1+IPCA_CENARIO)^(1/12))-1))) -> 1404.5644 | G52: =IF($G$9=0,0,MAX(0,$G$40*((1+($G$19-$G$22)*(1-$G$50))/((1+IPCA_CENARIO)^(1/12))-1))) -> 931.10997
A53: Pode retirar a partir de | B53: =IF($B$9=0,"",DATA_INICIO+$B$29+$B$30) -> 46258 | C53: =IF($C$9=0,"",DATA_INICIO+$C$29+$C$30) -> 46258 | D53: =IF($D$9=0,"",DATA_INICIO+$D$29+$D$30) -> 46287 | E53: =IF($E$9=0,"",DATA_INICIO+$E$29+$E$30) -> 46262 | F53: =IF($F$9=0,"",DATA_INICIO+$F$29+$F$30) -> 46262 | G53: =IF($G$9=0,"",DATA_INICIO+$G$29+$G$30) -> 46262
A54: Atende à aplicação mínima (1/0) | B54: =IF($B$9=0,0,IF(IN_CAPITAL>=$B$31,1,0)) -> 1 | C54: =IF($C$9=0,0,IF(IN_CAPITAL>=$C$31,1,0)) -> 1 | D54: =IF($D$9=0,0,IF(IN_CAPITAL>=$D$31,1,0)) -> 1 | E54: =IF($E$9=0,0,IF(IN_CAPITAL>=$E$31,1,0)) -> 1 | F54: =IF($F$9=0,0,IF(IN_CAPITAL>=$F$31,1,0)) -> 1 | G54: =IF($G$9=0,0,IF(IN_CAPITAL>=$G$31,1,0)) -> 1
A55: Cabe no perfil declarado (1/0) | B55: =IF($B$9=0,0,IF($B$32<=IFERROR(INDEX(Premissas!$B$102:$B$104,MATCH(IN_PERFIL,Premissas!$A$102:$A$104,0)),5),1,0)) -> 1 | C55: =IF($C$9=0,0,IF($C$32<=IFERROR(INDEX(Premissas!$B$102:$B$104,MATCH(IN_PERFIL,Premissas!$A$102:$A$104,0)),5),1,0)) -> 1 | D55: =IF($D$9=0,0,IF($D$32<=IFERROR(INDEX(Premissas!$B$102:$B$104,MATCH(IN_PERFIL,Premissas!$A$102:$A$104,0)),5),1,0)) -> 1 | E55: =IF($E$9=0,0,IF($E$32<=IFERROR(INDEX(Premissas!$B$102:$B$104,MATCH(IN_PERFIL,Premissas!$A$102:$A$104,0)),5),1,0)) -> 1 | F55: =IF($F$9=0,0,IF($F$32<=IFERROR(INDEX(Premissas!$B$102:$B$104,MATCH(IN_PERFIL,Premissas!$A$102:$A$104,0)),5),1,0)) -> 1 | G55: =IF($G$9=0,0,IF($G$32<=IFERROR(INDEX(Premissas!$B$102:$B$104,MATCH(IN_PERFIL,Premissas!$A$102:$A$104,0)),5),1,0)) -> 1
A56: Para retirar (linguagem de cliente) | B56: =IF($B$9=0,"",IF($B$29>0,"A partir de "&TEXT(DATA_INICIO+$B$29,"dd/mm/yyyy"),IF($B$30<=0,"No mesmo dia",IF($B$30=1,"Em 1 dia útil","Em até "&$B$30&" dias")))) -> Em 1 dia útil | C56: =IF($C$9=0,"",IF($C$29>0,"A partir de "&TEXT(DATA_INICIO+$C$29,"dd/mm/yyyy"),IF($C$30<=0,"No mesmo dia",IF($C$30=1,"Em 1 dia útil","Em até "&$C$30&" dias")))) -> Em 1 dia útil | D56: =IF($D$9=0,"",IF($D$29>0,"A partir de "&TEXT(DATA_INICIO+$D$29,"dd/mm/yyyy"),IF($D$30<=0,"No mesmo dia",IF($D$30=1,"Em 1 dia útil","Em até "&$D$30&" dias")))) -> Em até 30 dias | E56: =IF($E$9=0,"",IF($E$29>0,"A partir de "&TEXT(DATA_INICIO+$E$29,"dd/mm/yyyy"),IF($E$30<=0,"No mesmo dia",IF($E$30=1,"Em 1 dia útil","Em até "&$E$30&" dias")))) -> Em até 5 dias | F56: =IF($F$9=0,"",IF($F$29>0,"A partir de "&TEXT(DATA_INICIO+$F$29,"dd/mm/yyyy"),IF($F$30<=0,"No mesmo dia",IF($F$30=1,"Em 1 dia útil","Em até "&$F$30&" dias")))) -> Em até 5 dias | G56: =IF($G$9=0,"",IF($G$29>0,"A partir de "&TEXT(DATA_INICIO+$G$29,"dd/mm/yyyy"),IF($G$30<=0,"No mesmo dia",IF($G$30=1,"Em 1 dia útil","Em até "&$G$30&" dias")))) -> Em até 5 dias
A57: Oscilação (linguagem de cliente) | B57: =IF($B$9=0,"",IFERROR(INDEX(Premissas!$B$94:$B$98,$B$32),"")) -> Baixa | C57: =IF($C$9=0,"",IFERROR(INDEX(Premissas!$B$94:$B$98,$C$32),"")) -> Baixa | D57: =IF($D$9=0,"",IFERROR(INDEX(Premissas!$B$94:$B$98,$D$32),"")) -> Baixa | E57: =IF($E$9=0,"",IFERROR(INDEX(Premissas!$B$94:$B$98,$E$32),"")) -> Média | F57: =IF($F$9=0,"",IFERROR(INDEX(Premissas!$B$94:$B$98,$F$32),"")) -> Média | G57: =IF($G$9=0,"",IFERROR(INDEX(Premissas!$B$94:$B$98,$G$32),"")) -> Média
A58: BLOCO 3 · PROJEÇÃO MÊS A MÊS
F59: =IF($B$9=0,"ALTERNATIVA A — não utilizada","ALTERNATIVA A — "&$B$6) -> ALTERNATIVA A — Tesouro Prefixado 2031 | U59: =IF($C$9=0,"ALTERNATIVA B — não utilizada","ALTERNATIVA B — "&$C$6) -> ALTERNATIVA B — Tesouro IPCA+ 2035 | AJ59: =IF($D$9=0,"ALTERNATIVA C — não utilizada","ALTERNATIVA C — "&$D$6) -> ALTERNATIVA C — Fundo CAIXA RF Crédito Privado LP | AY59: =IF($E$9=0,"ALTERNATIVA D — não utilizada","ALTERNATIVA D — "&$E$6) -> ALTERNATIVA D — VGBL CAIXA Composto 30 — Regressivo | BN59: =IF($F$9=0,"ALTERNATIVA E — não utilizada","ALTERNATIVA E — "&$F$6) -> ALTERNATIVA E — PGBL CAIXA Composto 30 — Regressivo | CC59: =IF($G$9=0,"ALTERNATIVA F — não utilizada","ALTERNATIVA F — "&$G$6) -> ALTERNATIVA F — Fundo CAIXA RF IPCA Longo Prazo
A60: Mês | B60: Data | C60: Dias | D60: Fator inflação | F60: Saldo inicial | G60: Aporte do mês | H60: Custo de entrada | I60: Rendimento bruto | J60: Taxa de administração | K60: Taxa de performance | L60: Come-cotas (IR) | M60: Saldo final | N60: Total aportado (base fiscal) | O60: Come-cotas acumulado | P60: Ganho tributável | Q60: IR no resgate | R60: Valor líquido se resgatar | S60: Valor líquido em R$ de hoje | U60: Saldo inicial | V60: Aporte do mês | W60: Custo de entrada | X60: Rendimento bruto | Y60: Taxa de administração | Z60: Taxa de performance | AA60: Come-cotas (IR) | AB60: Saldo final | AC60: Total aportado (base fiscal) | AD60: Come-cotas acumulado | AE60: Ganho tributável | AF60: IR no resgate | AG60: Valor líquido se resgatar | AH60: Valor líquido em R$ de hoje | AJ60: Saldo inicial | AK60: Aporte do mês | AL60: Custo de entrada | AM60: Rendimento bruto | AN60: Taxa de administração | AO60: Taxa de performance | AP60: Come-cotas (IR) | AQ60: Saldo final | AR60: Total aportado (base fiscal) | AS60: Come-cotas acumulado | AT60: Ganho tributável | AU60: IR no resgate | AV60: Valor líquido se resgatar | AW60: Valor líquido em R$ de hoje | AY60: Saldo inicial | AZ60: Aporte do mês | BA60: Custo de entrada | BB60: Rendimento bruto | BC60: Taxa de administração | BD60: Taxa de performance | BE60: Come-cotas (IR) | BF60: Saldo final | BG60: Total aportado (base fiscal) | BH60: Come-cotas acumulado | BI60: Ganho tributável | BJ60: IR no resgate | BK60: Valor líquido se resgatar | BL60: Valor líquido em R$ de hoje | BN60: Saldo inicial | BO60: Aporte do mês | BP60: Custo de entrada | BQ60: Rendimento bruto | BR60: Taxa de administração | BS60: Taxa de performance | BT60: Come-cotas (IR) | BU60: Saldo final | BV60: Total aportado (base fiscal) | BW60: Come-cotas acumulado | BX60: Ganho tributável | BY60: IR no resgate | BZ60: Valor líquido se resgatar | CA60: Valor líquido em R$ de hoje | CC60: Saldo inicial | CD60: Aporte do mês | CE60: Custo de entrada | CF60: Rendimento bruto | CG60: Taxa de administração | CH60: Taxa de performance | CI60: Come-cotas (IR) | CJ60: Saldo final | CK60: Total aportado (base fiscal) | CL60: Come-cotas acumulado | CM60: Ganho tributável | CN60: IR no resgate | CO60: Valor líquido se resgatar | CP60: Valor líquido em R$ de hoje
A61: 0 | B61: =EDATE(DATA_INICIO,$A61) -> 46257 | C61: =$A61*30 -> 0 | D61: =(1+IPCA_CENARIO)^($A61/12) -> 1 | F61: =0 -> 0 | G61: =IF($B$9=0,0,IN_CAPITAL) -> 150000 | H61: =G61*$B$24 -> 0 | I61: =0 -> 0 | J61: =0 -> 0 | K61: =0 -> 0 | L61: =0 -> 0 | M61: =F61+I61-J61-K61+G61-H61-L61 -> 150000 | N61: =G61-H61 -> 150000 | O61: =L61 -> 0 | P61: =M61+O61-N61 -> 0 | Q61: =MAX(0,IFERROR(INDEX(TAB_IR,MATCH($C61,TAB_IR_DIAS,1),MATCH($B$8,TAB_IR_REGIMES,0)),0)*IF($B$26=2,M61,MAX(0,P61))-O61) -> 0 | R61: =MAX(0,M61-Q61-M61*$B$25) -> 150000 | S61: =R61/$D61 -> 150000 | U61: =0 -> 0 | V61: =IF($C$9=0,0,IN_CAPITAL) -> 150000 | W61: =V61*$C$24 -> 0 | X61: =0 -> 0 | Y61: =0 -> 0 | Z61: =0 -> 0 | AA61: =0 -> 0 | AB61: =U61+X61-Y61-Z61+V61-W61-AA61 -> 150000 | AC61: =V61-W61 -> 150000 | AD61: =AA61 -> 0 | AE61: =AB61+AD61-AC61 -> 0 | AF61: =MAX(0,IFERROR(INDEX(TAB_IR,MATCH($C61,TAB_IR_DIAS,1),MATCH($C$8,TAB_IR_REGIMES,0)),0)*IF($C$26=2,AB61,MAX(0,AE61))-AD61) -> 0 | AG61: =MAX(0,AB61-AF61-AB61*$C$25) -> 150000 | AH61: =AG61/$D61 -> 150000 | AJ61: =0 -> 0 | AK61: =IF($D$9=0,0,IN_CAPITAL) -> 150000 | AL61: =AK61*$D$24 -> 0 | AM61: =0 -> 0 | AN61: =0 -> 0 | AO61: =0 -> 0 | AP61: =0 -> 0 | AQ61: =AJ61+AM61-AN61-AO61+AK61-AL61-AP61 -> 150000 | AR61: =AK61-AL61 -> 150000 | AS61: =AP61 -> 0 | AT61: =AQ61+AS61-AR61 -> 0 | AU61: =MAX(0,IFERROR(INDEX(TAB_IR,MATCH($C61,TAB_IR_DIAS,1),MATCH($D$8,TAB_IR_REGIMES,0)),0)*IF($D$26=2,AQ61,MAX(0,AT61))-AS61) -> 0 | AV61: =MAX(0,AQ61-AU61-AQ61*$D$25) -> 150000 | AW61: =AV61/$D61 -> 150000 | AY61: =0 -> 0 | AZ61: =IF($E$9=0,0,IN_CAPITAL) -> 150000 | BA61: =AZ61*$E$24 -> 0 | BB61: =0 -> 0 | BC61: =0 -> 0 | BD61: =0 -> 0 | BE61: =0 -> 0 | BF61: =AY61+BB61-BC61-BD61+AZ61-BA61-BE61 -> 150000 | BG61: =AZ61-BA61 -> 150000 | BH61: =BE61 -> 0 | BI61: =BF61+BH61-BG61 -> 0 | BJ61: =MAX(0,IFERROR(INDEX(TAB_IR,MATCH($C61,TAB_IR_DIAS,1),MATCH($E$8,TAB_IR_REGIMES,0)),0)*IF($E$26=2,BF61,MAX(0,BI61))-BH61) -> 0 | BK61: =MAX(0,BF61-BJ61-BF61*$E$25) -> 150000 | BL61: =BK61/$D61 -> 150000 | BN61: =0 -> 0 | BO61: =IF($F$9=0,0,IN_CAPITAL) -> 150000 | BP61: =BO61*$F$24 -> 0 | BQ61: =0 -> 0 | BR61: =0 -> 0 | BS61: =0 -> 0 | BT61: =0 -> 0 | BU61: =BN61+BQ61-BR61-BS61+BO61-BP61-BT61 -> 150000 | BV61: =BO61-BP61 -> 150000 | BW61: =BT61 -> 0 | BX61: =BU61+BW61-BV61 -> 0 | BY61: =MAX(0,IFERROR(INDEX(TAB_IR,MATCH($C61,TAB_IR_DIAS,1),MATCH($F$8,TAB_IR_REGIMES,0)),0)*IF($F$26=2,BU61,MAX(0,BX61))-BW61) -> 52500 | BZ61: =MAX(0,BU61-BY61-BU61*$F$25) -> 97500 | CA61: =BZ61/$D61 -> 97500 | CC61: =0 -> 0 | CD61: =IF($G$9=0,0,IN_CAPITAL) -> 150000 | CE61: =CD61*$G$24 -> 0 | CF61: =0 -> 0 | CG61: =0 -> 0 | CH61: =0 -> 0 | CI61: =0 -> 0 | CJ61: =CC61+CF61-CG61-CH61+CD61-CE61-CI61 -> 150000 | CK61: =CD61-CE61 -> 150000 | CL61: =CI61 -> 0 | CM61: =CJ61+CL61-CK61 -> 0 | CN61: =MAX(0,IFERROR(INDEX(TAB_IR,MATCH($C61,TAB_IR_DIAS,1),MATCH($G$8,TAB_IR_REGIMES,0)),0)*IF($G$26=2,CJ61,MAX(0,CM61))-CL61) -> 0 | CO61: =MAX(0,CJ61-CN61-CJ61*$G$25) -> 150000 | CP61: =CO61/$D61 -> 150000
A62: 1 | B62: =EDATE(DATA_INICIO,$A62) -> 46288 | C62: =$A62*30 -> 30 | D62: =(1+IPCA_CENARIO)^($A62/12) -> 1.0032737 | F62: =M61 -> 150000 | G62: =IF($B$9=0,0,IF($A62>IN_PRAZO,0,IF(APORTE_CORRIGIDO="Sim",IN_APORTE*$D62,IN_APORTE))+IF(AND($B$35=1,PGBL_REINVESTE="Sim",$A62>=13,$A62<=IN_PRAZO,MONTH($B62)=5),PGBL_BENEFICIO,0)) -> 0 | H62: =G62*$B$24 -> 0 | I62: =F62*$B$19 -> 1423.3189 | J62: =F62*$B$22 -> 25 | K62: =$B$23*MAX(0,I62-F62*$B$18) -> 0 | L62: =IF(AND($B$27=1,OR(MONTH($B62)=5,MONTH($B62)=11)),MAX(0,$B$28*MAX(0,(F62+I62-J62-K62+G62-H62)+O61-N62)-O61),0) -> 0 | M62: =F62+I62-J62-K62+G62-H62-L62 -> 151398.32 | N62: =N61+G62-H62 -> 150000 | O62: =O61+L62 -> 0 | P62: =M62+O62-N62 -> 1398.3189 | Q62: =MAX(0,IFERROR(INDEX(TAB_IR,MATCH($C62,TAB_IR_DIAS,1),MATCH($B$8,TAB_IR_REGIMES,0)),0)*IF($B$26=2,M62,MAX(0,P62))-O62) -> 314.62176 | R62: =MAX(0,M62-Q62-M62*$B$25) -> 151083.7 | S62: =R62/$D62 -> 150590.7 | U62: =AB61 -> 150000 | V62: =IF($C$9=0,0,IF($A62>IN_PRAZO,0,IF(APORTE_CORRIGIDO="Sim",IN_APORTE*$D62,IN_APORTE))+IF(AND($C$35=1,PGBL_REINVESTE="Sim",$A62>=13,$A62<=IN_PRAZO,MONTH($B62)=5),PGBL_BENEFICIO,0)) -> 0 | W62: =V62*$C$24 -> 0 | X62: =U62*$C$19 -> 1223.5838 | Y62: =U62*$C$22 -> 25 | Z62: =$C$23*MAX(0,X62-U62*$C$18) -> 0 | AA62: =IF(AND($C$27=1,OR(MONTH($B62)=5,MONTH($B62)=11)),MAX(0,$C$28*MAX(0,(U62+X62-Y62-Z62+V62-W62)+AD61-AC62)-AD61),0) -> 0 | AB62: =U62+X62-Y62-Z62+V62-W62-AA62 -> 151198.58 | AC62: =AC61+V62-W62 -> 150000 | AD62: =AD61+AA62 -> 0 | AE62: =AB62+AD62-AC62 -> 1198.5838 | AF62: =MAX(0,IFERROR(INDEX(TAB_IR,MATCH($C62,TAB_IR_DIAS,1),MATCH($C$8,TAB_IR_REGIMES,0)),0)*IF($C$26=2,AB62,MAX(0,AE62))-AD62) -> 269.68136 | AG62: =MAX(0,AB62-AF62-AB62*$C$25) -> 150928.9 | AH62: =AG62/$D62 -> 150436.41 | AJ62: =AQ61 -> 150000 | AK62: =IF($D$9=0,0,IF($A62>IN_PRAZO,0,IF(APORTE_CORRIGIDO="Sim",IN_APORTE*$D62,IN_APORTE))+IF(AND($D$35=1,PGBL_REINVESTE="Sim",$A62>=13,$A62<=IN_PRAZO,MONTH($B62)=5),PGBL_BENEFICIO,0)) -> 0 | AL62: =AK62*$D$24 -> 0 | AM62: =AJ62*$D$19 -> 1348.3046 | AN62: =AJ62*$D$22 -> 125 | AO62: =$D$23*MAX(0,AM62-AJ62*$D$18) -> 0 | AP62: =IF(AND($D$27=1,OR(MONTH($B62)=5,MONTH($B62)=11)),MAX(0,$D$28*MAX(0,(AJ62+AM62-AN62-AO62+AK62-AL62)+AS61-AR62)-AS61),0) -> 0 | AQ62: =AJ62+AM62-AN62-AO62+AK62-AL62-AP62 -> 151223.3 | AR62: =AR61+AK62-AL62 -> 150000 | AS62: =AS61+AP62 -> 0 | AT62: =AQ62+AS62-AR62 -> 1223.3046 | AU62: =MAX(0,IFERROR(INDEX(TAB_IR,MATCH($C62,TAB_IR_DIAS,1),MATCH($D$8,TAB_IR_REGIMES,0)),0)*IF($D$26=2,AQ62,MAX(0,AT62))-AS62) -> 275.24353 | AV62: =MAX(0,AQ62-AU62-AQ62*$D$25) -> 150948.06 | AW62: =AV62/$D62 -> 150455.51 | AY62: =BF61 -> 150000 | AZ62: =IF($E$9=0,0,IF($A62>IN_PRAZO,0,IF(APORTE_CORRIGIDO="Sim",IN_APORTE*$D62,IN_APORTE))+IF(AND($E$35=1,PGBL_REINVESTE="Sim",$A62>=13,$A62<=IN_PRAZO,MONTH($B62)=5),PGBL_BENEFICIO,0)) -> 0 | BA62: =AZ62*$E$24 -> 0 | BB62: =AY62*$E$19 -> 1468.3118 | BC62: =AY62*$E$22 -> 187.5 | BD62: =$E$23*MAX(0,BB62-AY62*$E$18) -> 0 | BE62: =IF(AND($E$27=1,OR(MONTH($B62)=5,MONTH($B62)=11)),MAX(0,$E$28*MAX(0,(AY62+BB62-BC62-BD62+AZ62-BA62)+BH61-BG62)-BH61),0) -> 0 | BF62: =AY62+BB62-BC62-BD62+AZ62-BA62-BE62 -> 151280.81 | BG62: =BG61+AZ62-BA62 -> 150000 | BH62: =BH61+BE62 -> 0 | BI62: =BF62+BH62-BG62 -> 1280.8118 | BJ62: =MAX(0,IFERROR(INDEX(TAB_IR,MATCH($C62,TAB_IR_DIAS,1),MATCH($E$8,TAB_IR_REGIMES,0)),0)*IF($E$26=2,BF62,MAX(0,BI62))-BH62) -> 448.28413 | BK62: =MAX(0,BF62-BJ62-BF62*$E$25) -> 150832.53 | BL62: =BK62/$D62 -> 150340.35 | BN62: =BU61 -> 150000 | BO62: =IF($F$9=0,0,IF($A62>IN_PRAZO,0,IF(APORTE_CORRIGIDO="Sim",IN_APORTE*$D62,IN_APORTE))+IF(AND($F$35=1,PGBL_REINVESTE="Sim",$A62>=13,$A62<=IN_PRAZO,MONTH($B62)=5),PGBL_BENEFICIO,0)) -> 0 | BP62: =BO62*$F$24 -> 0 | BQ62: =BN62*$F$19 -> 1468.3118 | BR62: =BN62*$F$22 -> 187.5 | BS62: =$F$23*MAX(0,BQ62-BN62*$F$18) -> 0 | BT62: =IF(AND($F$27=1,OR(MONTH($B62)=5,MONTH($B62)=11)),MAX(0,$F$28*MAX(0,(BN62+BQ62-BR62-BS62+BO62-BP62)+BW61-BV62)-BW61),0) -> 0 | BU62: =BN62+BQ62-BR62-BS62+BO62-BP62-BT62 -> 151280.81 | BV62: =BV61+BO62-BP62 -> 150000 | BW62: =BW61+BT62 -> 0 | BX62: =BU62+BW62-BV62 -> 1280.8118 | BY62: =MAX(0,IFERROR(INDEX(TAB_IR,MATCH($C62,TAB_IR_DIAS,1),MATCH($F$8,TAB_IR_REGIMES,0)),0)*IF($F$26=2,BU62,MAX(0,BX62))-BW62) -> 52948.284 | BZ62: =MAX(0,BU62-BY62-BU62*$F$25) -> 98332.528 | CA62: =BZ62/$D62 -> 98011.663 | CC62: =CJ61 -> 150000 | CD62: =IF($G$9=0,0,IF($A62>IN_PRAZO,0,IF(APORTE_CORRIGIDO="Sim",IN_APORTE*$D62,IN_APORTE))+IF(AND($G$35=1,PGBL_REINVESTE="Sim",$A62>=13,$A62<=IN_PRAZO,MONTH($B62)=5),PGBL_BENEFICIO,0)) -> 0 | CE62: =CD62*$G$24 -> 0 | CF62: =CC62*$G$19 -> 1223.5838 | CG62: =CC62*$G$22 -> 125 | CH62: =$G$23*MAX(0,CF62-CC62*$G$18) -> 0 | CI62: =IF(AND($G$27=1,OR(MONTH($B62)=5,MONTH($B62)=11)),MAX(0,$G$28*MAX(0,(CC62+CF62-CG62-CH62+CD62-CE62)+CL61-CK62)-CL61),0) -> 0 | CJ62: =CC62+CF62-CG62-CH62+CD62-CE62-CI62 -> 151098.58 | CK62: =CK61+CD62-CE62 -> 150000 | CL62: =CL61+CI62 -> 0 | CM62: =CJ62+CL62-CK62 -> 1098.5838 | CN62: =MAX(0,IFERROR(INDEX(TAB_IR,MATCH($C62,TAB_IR_DIAS,1),MATCH($G$8,TAB_IR_REGIMES,0)),0)*IF($G$26=2,CJ62,MAX(0,CM62))-CL62) -> 247.18136 | CO62: =MAX(0,CJ62-CN62-CJ62*$G$25) -> 150851.4 | CP62: =CO62/$D62 -> 150359.17
A63: 2 | B63: =EDATE(DATA_INICIO,$A63) -> 46318 | C63: =$A63*30 -> 60 | D63: =(1+IPCA_CENARIO)^($A63/12) -> 1.0065582 | F63: =M62 -> 151398.32 | G63: =IF($B$9=0,0,IF($A63>IN_PRAZO,0,IF(APORTE_CORRIGIDO="Sim",IN_APORTE*$D63,IN_APORTE))+IF(AND($B$35=1,PGBL_REINVESTE="Sim",$A63>=13,$A63<=IN_PRAZO,MONTH($B63)=5),PGBL_BENEFICIO,0)) -> 0 | H63: =G63*$B$24 -> 0 | I63: =F63*$B$19 -> 1436.5873 | J63: =F63*$B$22 -> 25.233053 | K63: =$B$23*MAX(0,I63-F63*$B$18) -> 0 | L63: =IF(AND($B$27=1,OR(MONTH($B63)=5,MONTH($B63)=11)),MAX(0,$B$28*MAX(0,(F63+I63-J63-K63+G63-H63)+O62-N63)-O62),0) -> 0 | M63: =F63+I63-J63-K63+G63-H63-L63 -> 152809.67 | N63: =N62+G63-H63 -> 150000 | O63: =O62+L63 -> 0 | P63: =M63+O63-N63 -> 2809.6732 | Q63: =MAX(0,IFERROR(INDEX(TAB_IR,MATCH($C63,TAB_IR_DIAS,1),MATCH($B$8,TAB_IR_REGIMES,0)),0)*IF($B$26=2,M63,MAX(0,P63))-O63) -> 632.17647 | R63: =MAX(0,M63-Q63-M63*$B$25) -> 152177.5 | S63: =R63/$D63 -> 151185.99 | U63: =AB62 -> 151198.58 | V63: =IF($C$9=0,0,IF($A63>IN_PRAZO,0,IF(APORTE_CORRIGIDO="Sim",IN_APORTE*$D63,IN_APORTE))+IF(AND($C$35=1,PGBL_REINVESTE="Sim",$A63>=13,$A63<=IN_PRAZO,MONTH($B63)=5),PGBL_BENEFICIO,0)) -> 0 | W63: =V63*$C$24 -> 0 | X63: =U63*$C$19 -> 1233.3609 | Y63: =U63*$C$22 -> 25.199764 | Z63: =$C$23*MAX(0,X63-U63*$C$18) -> 0 | AA63: =IF(AND($C$27=1,OR(MONTH($B63)=5,MONTH($B63)=11)),MAX(0,$C$28*MAX(0,(U63+X63-Y63-Z63+V63-W63)+AD62-AC63)-AD62),0) -> 0 | AB63: =U63+X63-Y63-Z63+V63-W63-AA63 -> 152406.74 | AC63: =AC62+V63-W63 -> 150000 | AD63: =AD62+AA63 -> 0 | AE63: =AB63+AD63-AC63 -> 2406.745 | AF63: =MAX(0,IFERROR(INDEX(TAB_IR,MATCH($C63,TAB_IR_DIAS,1),MATCH($C$8,TAB_IR_REGIMES,0)),0)*IF($C$26=2,AB63,MAX(0,AE63))-AD63) -> 541.51762 | AG63: =MAX(0,AB63-AF63-AB63*$C$25) -> 151865.23 | AH63: =AG63/$D63 -> 150875.75 | AJ63: =AQ62 -> 151223.3 | AK63: =IF($D$9=0,0,IF($A63>IN_PRAZO,0,IF(APORTE_CORRIGIDO="Sim",IN_APORTE*$D63,IN_APORTE))+IF(AND($D$35=1,PGBL_REINVESTE="Sim",$A63>=13,$A63<=IN_PRAZO,MONTH($B63)=5),PGBL_BENEFICIO,0)) -> 0 | AL63: =AK63*$D$24 -> 0 | AM63: =AJ63*$D$19 -> 1359.3005 | AN63: =AJ63*$D$22 -> 126.01942 | AO63: =$D$23*MAX(0,AM63-AJ63*$D$18) -> 0 | AP63: =IF(AND($D$27=1,OR(MONTH($B63)=5,MONTH($B63)=11)),MAX(0,$D$28*MAX(0,(AJ63+AM63-AN63-AO63+AK63-AL63)+AS62-AR63)-AS62),0) -> 0 | AQ63: =AJ63+AM63-AN63-AO63+AK63-AL63-AP63 -> 152456.59 | AR63: =AR62+AK63-AL63 -> 150000 | AS63: =AS62+AP63 -> 0 | AT63: =AQ63+AS63-AR63 -> 2456.5856 | AU63: =MAX(0,IFERROR(INDEX(TAB_IR,MATCH($C63,TAB_IR_DIAS,1),MATCH($D$8,TAB_IR_REGIMES,0)),0)*IF($D$26=2,AQ63,MAX(0,AT63))-AS63) -> 552.73176 | AV63: =MAX(0,AQ63-AU63-AQ63*$D$25) -> 151903.85 | AW63: =AV63/$D63 -> 150914.13 | AY63: =BF62 -> 151280.81 | AZ63: =IF($E$9=0,0,IF($A63>IN_PRAZO,0,IF(APORTE_CORRIGIDO="Sim",IN_APORTE*$D63,IN_APORTE))+IF(AND($E$35=1,PGBL_REINVESTE="Sim",$A63>=13,$A63<=IN_PRAZO,MONTH($B63)=5),PGBL_BENEFICIO,0)) -> 0 | BA63: =AZ63*$E$24 -> 0 | BB63: =AY63*$E$19 -> 1480.8493 | BC63: =AY63*$E$22 -> 189.10101 | BD63: =$E$23*MAX(0,BB63-AY63*$E$18) -> 0 | BE63: =IF(AND($E$27=1,OR(MONTH($B63)=5,MONTH($B63)=11)),MAX(0,$E$28*MAX(0,(AY63+BB63-BC63-BD63+AZ63-BA63)+BH62-BG63)-BH62),0) -> 0 | BF63: =AY63+BB63-BC63-BD63+AZ63-BA63-BE63 -> 152572.56 | BG63: =BG62+AZ63-BA63 -> 150000 | BH63: =BH62+BE63 -> 0 | BI63: =BF63+BH63-BG63 -> 2572.5601 | BJ63: =MAX(0,IFERROR(INDEX(TAB_IR,MATCH($C63,TAB_IR_DIAS,1),MATCH($E$8,TAB_IR_REGIMES,0)),0)*IF($E$26=2,BF63,MAX(0,BI63))-BH63) -> 900.39605 | BK63: =MAX(0,BF63-BJ63-BF63*$E$25) -> 151672.16 | BL63: =BK63/$D63 -> 150683.95 | BN63: =BU62 -> 151280.81 | BO63: =IF($F$9=0,0,IF($A63>IN_PRAZO,0,IF(APORTE_CORRIGIDO="Sim",IN_APORTE*$D63,IN_APORTE))+IF(AND($F$35=1,PGBL_REINVESTE="Sim",$A63>=13,$A63<=IN_PRAZO,MONTH($B63)=5),PGBL_BENEFICIO,0)) -> 0 | BP63: =BO63*$F$24 -> 0 | BQ63: =BN63*$F$19 -> 1480.8493 | BR63: =BN63*$F$22 -> 189.10101 | BS63: =$F$23*MAX(0,BQ63-BN63*$F$18) -> 0 | BT63: =IF(AND($F$27=1,OR(MONTH($B63)=5,MONTH($B63)=11)),MAX(0,$F$28*MAX(0,(BN63+BQ63-BR63-BS63+BO63-BP63)+BW62-BV63)-BW62),0) -> 0 | BU63: =BN63+BQ63-BR63-BS63+BO63-BP63-BT63 -> 152572.56 | BV63: =BV62+BO63-BP63 -> 150000 | BW63: =BW62+BT63 -> 0 | BX63: =BU63+BW63-BV63 -> 2572.5601 | BY63: =MAX(0,IFERROR(INDEX(TAB_IR,MATCH($C63,TAB_IR_DIAS,1),MATCH($F$8,TAB_IR_REGIMES,0)),0)*IF($F$26=2,BU63,MAX(0,BX63))-BW63) -> 53400.396 | BZ63: =MAX(0,BU63-BY63-BU63*$F$25) -> 99172.164 | CA63: =BZ63/$D63 -> 98526.011 | CC63: =CJ62 -> 151098.58 | CD63: =IF($G$9=0,0,IF($A63>IN_PRAZO,0,IF(APORTE_CORRIGIDO="Sim",IN_APORTE*$D63,IN_APORTE))+IF(AND($G$35=1,PGBL_REINVESTE="Sim",$A63>=13,$A63<=IN_PRAZO,MONTH($B63)=5),PGBL_BENEFICIO,0)) -> 0 | CE63: =CD63*$G$24 -> 0 | CF63: =CC63*$G$19 -> 1232.5452 | CG63: =CC63*$G$22 -> 125.91549 | CH63: =$G$23*MAX(0,CF63-CC63*$G$18) -> 0 | CI63: =IF(AND($G$27=1,OR(MONTH($B63)=5,MONTH($B63)=11)),MAX(0,$G$28*MAX(0,(CC63+CF63-CG63-CH63+CD63-CE63)+CL62-CK63)-CL62),0) -> 0 | CJ63: =CC63+CF63-CG63-CH63+CD63-CE63-CI63 -> 152205.21 | CK63: =CK62+CD63-CE63 -> 150000 | CL63: =CL62+CI63 -> 0 | CM63: =CJ63+CL63-CK63 -> 2205.2135 | CN63: =MAX(0,IFERROR(INDEX(TAB_IR,MATCH($C63,TAB_IR_DIAS,1),MATCH($G$8,TAB_IR_REGIMES,0)),0)*IF($G$26=2,CJ63,MAX(0,CM63))-CL63) -> 496.17305 | CO63: =MAX(0,CJ63-CN63-CJ63*$G$25) -> 151709.04 | CP63: =CO63/$D63 -> 150720.59
A64: 3 | B64: =EDATE(DATA_INICIO,$A64) -> 46349 | C64: =$A64*30 -> 90 | D64: =(1+IPCA_CENARIO)^($A64/12) -> 1.0098534 | F64: =M63 -> 152809.67 | G64: =IF($B$9=0,0,IF($A64>IN_PRAZO,0,IF(APORTE_CORRIGIDO="Sim",IN_APORTE*$D64,IN_APORTE))+IF(AND($B$35=1,PGBL_REINVESTE="Sim",$A64>=13,$A64<=IN_PRAZO,MONTH($B64)=5),PGBL_BENEFICIO,0)) -> 0 | H64: =G64*$B$24 -> 0 | I64: =F64*$B$19 -> 1449.9793 | J64: =F64*$B$22 -> 25.468279 | K64: =$B$23*MAX(0,I64-F64*$B$18) -> 0 | L64: =IF(AND($B$27=1,OR(MONTH($B64)=5,MONTH($B64)=11)),MAX(0,$B$28*MAX(0,(F64+I64-J64-K64+G64-H64)+O63-N64)-O63),0) -> 0 | M64: =F64+I64-J64-K64+G64-H64-L64 -> 154234.18 | N64: =N63+G64-H64 -> 150000 | O64: =O63+L64 -> 0 | P64: =M64+O64-N64 -> 4234.1843 | Q64: =MAX(0,IFERROR(INDEX(TAB_IR,MATCH($C64,TAB_IR_DIAS,1),MATCH($B$8,TAB_IR_REGIMES,0)),0)*IF($B$26=2,M64,MAX(0,P64))-O64) -> 952.69146 | R64: =MAX(0,M64-Q64-M64*$B$25) -> 153281.49 | S64: =R64/$D64 -> 151785.88 | U64: =AB63 -> 152406.74 | V64: =IF($C$9=0,0,IF($A64>IN_PRAZO,0,IF(APORTE_CORRIGIDO="Sim",IN_APORTE*$D64,IN_APORTE))+IF(AND($C$35=1,PGBL_REINVESTE="Sim",$A64>=13,$A64<=IN_PRAZO,MONTH($B64)=5),PGBL_BENEFICIO,0)) -> 0 | W64: =V64*$C$24 -> 0 | X64: =U64*$C$19 -> 1243.2162 | Y64: =U64*$C$22 -> 25.401124 | Z64: =$C$23*MAX(0,X64-U64*$C$18) -> 0 | AA64: =IF(AND($C$27=1,OR(MONTH($B64)=5,MONTH($B64)=11)),MAX(0,$C$28*MAX(0,(U64+X64-Y64-Z64+V64-W64)+AD63-AC64)-AD63),0) -> 0 | AB64: =U64+X64-Y64-Z64+V64-W64-AA64 -> 153624.56 | AC64: =AC63+V64-W64 -> 150000 | AD64: =AD63+AA64 -> 0 | AE64: =AB64+AD64-AC64 -> 3624.56 | AF64: =MAX(0,IFERROR(INDEX(TAB_IR,MATCH($C64,TAB_IR_DIAS,1),MATCH($C$8,TAB_IR_REGIMES,0)),0)*IF($C$26=2,AB64,MAX(0,AE64))-AD64) -> 815.52601 | AG64: =MAX(0,AB64-AF64-AB64*$C$25) -> 152809.03 | AH64: =AG64/$D64 -> 151318.04 | AJ64: =AQ63 -> 152456.59 | AK64: =IF($D$9=0,0,IF($A64>IN_PRAZO,0,IF(APORTE_CORRIGIDO="Sim",IN_APORTE*$D64,IN_APORTE))+IF(AND($D$35=1,PGBL_REINVESTE="Sim",$A64>=13,$A64<=IN_PRAZO,MONTH($B64)=5),PGBL_BENEFICIO,0)) -> 0 | AL64: =AK64*$D$24 -> 0 | AM64: =AJ64*$D$19 -> 1370.3861 | AN64: =AJ64*$D$22 -> 127.04715 | AO64: =$D$23*MAX(0,AM64-AJ64*$D$18) -> 0 | AP64: =IF(AND($D$27=1,OR(MONTH($B64)=5,MONTH($B64)=11)),MAX(0,$D$28*MAX(0,(AJ64+AM64-AN64-AO64+AK64-AL64)+AS63-AR64)-AS63),0) -> 554.98868 | AQ64: =AJ64+AM64-AN64-AO64+AK64-AL64-AP64 -> 153144.94 | AR64: =AR63+AK64-AL64 -> 150000 | AS64: =AS63+AP64 -> 554.98868 | AT64: =AQ64+AS64-AR64 -> 3699.9245 | AU64: =MAX(0,IFERROR(INDEX(TAB_IR,MATCH($C64,TAB_IR_DIAS,1),MATCH($D$8,TAB_IR_REGIMES,0)),0)*IF($D$26=2,AQ64,MAX(0,AT64))-AS64) -> 277.49434 | AV64: =MAX(0,AQ64-AU64-AQ64*$D$25) -> 152867.44 | AW64: =AV64/$D64 -> 151375.87 | AY64: =BF63 -> 152572.56 | AZ64: =IF($E$9=0,0,IF($A64>IN_PRAZO,0,IF(APORTE_CORRIGIDO="Sim",IN_APORTE*$D64,IN_APORTE))+IF(AND($E$35=1,PGBL_REINVESTE="Sim",$A64>=13,$A64<=IN_PRAZO,MONTH($B64)=5),PGBL_BENEFICIO,0)) -> 0 | BA64: =AZ64*$E$24 -> 0 | BB64: =AY64*$E$19 -> 1493.4939 | BC64: =AY64*$E$22 -> 190.7157 | BD64: =$E$23*MAX(0,BB64-AY64*$E$18) -> 0 | BE64: =IF(AND($E$27=1,OR(MONTH($B64)=5,MONTH($B64)=11)),MAX(0,$E$28*MAX(0,(AY64+BB64-BC64-BD64+AZ64-BA64)+BH63-BG64)-BH63),0) -> 0 | BF64: =AY64+BB64-BC64-BD64+AZ64-BA64-BE64 -> 153875.34 | BG64: =BG63+AZ64-BA64 -> 150000 | BH64: =BH63+BE64 -> 0 | BI64: =BF64+BH64-BG64 -> 3875.3384 | BJ64: =MAX(0,IFERROR(INDEX(TAB_IR,MATCH($C64,TAB_IR_DIAS,1),MATCH($E$8,TAB_IR_REGIMES,0)),0)*IF($E$26=2,BF64,MAX(0,BI64))-BH64) -> 1356.3684 | BK64: =MAX(0,BF64-BJ64-BF64*$E$25) -> 152518.97 | BL64: =BK64/$D64 -> 151030.8 | BN64: =BU63 -> 152572.56 | BO64: =IF($F$9=0,0,IF($A64>IN_PRAZO,0,IF(APORTE_CORRIGIDO="Sim",IN_APORTE*$D64,IN_APORTE))+IF(AND($F$35=1,PGBL_REINVESTE="Sim",$A64>=13,$A64<=IN_PRAZO,MONTH($B64)=5),PGBL_BENEFICIO,0)) -> 0 | BP64: =BO64*$F$24 -> 0 | BQ64: =BN64*$F$19 -> 1493.4939 | BR64: =BN64*$F$22 -> 190.7157 | BS64: =$F$23*MAX(0,BQ64-BN64*$F$18) -> 0 | BT64: =IF(AND($F$27=1,OR(MONTH($B64)=5,MONTH($B64)=11)),MAX(0,$F$28*MAX(0,(BN64+BQ64-BR64-BS64+BO64-BP64)+BW63-BV64)-BW63),0) -> 0 | BU64: =BN64+BQ64-BR64-BS64+BO64-BP64-BT64 -> 153875.34 | BV64: =BV63+BO64-BP64 -> 150000 | BW64: =BW63+BT64 -> 0 | BX64: =BU64+BW64-BV64 -> 3875.3384 | BY64: =MAX(0,IFERROR(INDEX(TAB_IR,MATCH($C64,TAB_IR_DIAS,1),MATCH($F$8,TAB_IR_REGIMES,0)),0)*IF($F$26=2,BU64,MAX(0,BX64))-BW64) -> 53856.368 | BZ64: =MAX(0,BU64-BY64-BU64*$F$25) -> 100018.97 | CA64: =BZ64/$D64 -> 99043.058 | CC64: =CJ63 -> 152205.21 | CD64: =IF($G$9=0,0,IF($A64>IN_PRAZO,0,IF(APORTE_CORRIGIDO="Sim",IN_APORTE*$D64,IN_APORTE))+IF(AND($G$35=1,PGBL_REINVESTE="Sim",$A64>=13,$A64<=IN_PRAZO,MONTH($B64)=5),PGBL_BENEFICIO,0)) -> 0 | CE64: =CD64*$G$24 -> 0 | CF64: =CC64*$G$19 -> 1241.5722 | CG64: =CC64*$G$22 -> 126.83768 | CH64: =$G$23*MAX(0,CF64-CC64*$G$18) -> 0 | CI64: =IF(AND($G$27=1,OR(MONTH($B64)=5,MONTH($B64)=11)),MAX(0,$G$28*MAX(0,(CC64+CF64-CG64-CH64+CD64-CE64)+CL63-CK64)-CL63),0) -> 497.99222 | CJ64: =CC64+CF64-CG64-CH64+CD64-CE64-CI64 -> 152821.96 | CK64: =CK63+CD64-CE64 -> 150000 | CL64: =CL63+CI64 -> 497.99222 | CM64: =CJ64+CL64-CK64 -> 3319.9481 | CN64: =MAX(0,IFERROR(INDEX(TAB_IR,MATCH($C64,TAB_IR_DIAS,1),MATCH($G$8,TAB_IR_REGIMES,0)),0)*IF($G$26=2,CJ64,MAX(0,CM64))-CL64) -> 248.99611 | CO64: =MAX(0,CJ64-CN64-CJ64*$G$25) -> 152572.96 | CP64: =CO64/$D64 -> 151084.27
